{
    "topic_word_count": {
        "topic0": [
            {
                "word": "government",
                "count": 54
            },
            {
                "word": "people",
                "count": 101
            },
            {
                "word": "coronavirus",
                "count": 155
            },
            {
                "word": "measures",
                "count": 46
            },
            {
                "word": "need",
                "count": 56
            },
            {
                "word": "europe",
                "count": 48
            },
            {
                "word": "restaurants",
                "count": 25
            },
            {
                "word": "france",
                "count": 54
            },
            {
                "word": "reduce",
                "count": 38
            },
            {
                "word": "mass",
                "count": 42
            }
        ],
        "topic1": [
            {
                "word": "coronavirus",
                "count": 155
            },
            {
                "word": "italy",
                "count": 93
            },
            {
                "word": "people",
                "count": 101
            },
            {
                "word": "cases",
                "count": 47
            },
            {
                "word": "need",
                "count": 56
            },
            {
                "word": "closing",
                "count": 35
            },
            {
                "word": "france",
                "count": 54
            },
            {
                "word": "countries",
                "count": 81
            },
            {
                "word": "practice",
                "count": 29
            },
            {
                "word": "spread",
                "count": 74
            }
        ],
        "topic2": [
            {
                "word": "coronavirus",
                "count": 155
            },
            {
                "word": "countries",
                "count": 81
            },
            {
                "word": "china",
                "count": 37
            },
            {
                "word": "spread",
                "count": 74
            },
            {
                "word": "italy",
                "count": 93
            },
            {
                "word": "italy_spain",
                "count": 30
            },
            {
                "word": "reduce",
                "count": 38
            },
            {
                "word": "closing",
                "count": 35
            },
            {
                "word": "number",
                "count": 32
            },
            {
                "word": "new",
                "count": 40
            }
        ],
        "topic3": [
            {
                "word": "coronavirus",
                "count": 155
            },
            {
                "word": "closing",
                "count": 35
            },
            {
                "word": "need",
                "count": 56
            },
            {
                "word": "day",
                "count": 32
            },
            {
                "word": "world",
                "count": 49
            },
            {
                "word": "need_know",
                "count": 28
            },
            {
                "word": "new",
                "count": 40
            },
            {
                "word": "italy",
                "count": 93
            },
            {
                "word": "number",
                "count": 32
            },
            {
                "word": "know",
                "count": 32
            }
        ],
        "topic4": [
            {
                "word": "people",
                "count": 101
            },
            {
                "word": "country",
                "count": 27
            },
            {
                "word": "world",
                "count": 49
            },
            {
                "word": "coronavirus",
                "count": 155
            },
            {
                "word": "measures",
                "count": 46
            },
            {
                "word": "outbreak",
                "count": 33
            },
            {
                "word": "france",
                "count": 54
            },
            {
                "word": "covid",
                "count": 35
            },
            {
                "word": "day",
                "count": 32
            },
            {
                "word": "spread",
                "count": 74
            }
        ],
        "topic5": [
            {
                "word": "need",
                "count": 56
            },
            {
                "word": "france",
                "count": 54
            },
            {
                "word": "things_need",
                "count": 36
            },
            {
                "word": "things",
                "count": 36
            },
            {
                "word": "europe",
                "count": 48
            },
            {
                "word": "countries",
                "count": 81
            },
            {
                "word": "country",
                "count": 27
            },
            {
                "word": "announced",
                "count": 26
            },
            {
                "word": "including",
                "count": 43
            },
            {
                "word": "covid_19",
                "count": 33
            }
        ],
        "topic6": [
            {
                "word": "covid",
                "count": 35
            },
            {
                "word": "covid_19",
                "count": 33
            },
            {
                "word": "spread",
                "count": 74
            },
            {
                "word": "coronavirus",
                "count": 155
            },
            {
                "word": "said",
                "count": 39
            },
            {
                "word": "including",
                "count": 43
            },
            {
                "word": "new",
                "count": 40
            },
            {
                "word": "italy",
                "count": 93
            },
            {
                "word": "cases",
                "count": 47
            },
            {
                "word": "government",
                "count": 54
            }
        ],
        "topic7": [
            {
                "word": "coronavirus",
                "count": 155
            },
            {
                "word": "italy",
                "count": 93
            },
            {
                "word": "people",
                "count": 101
            },
            {
                "word": "cases",
                "count": 47
            },
            {
                "word": "need",
                "count": 56
            },
            {
                "word": "closing",
                "count": 35
            },
            {
                "word": "france",
                "count": 54
            },
            {
                "word": "countries",
                "count": 81
            },
            {
                "word": "practice",
                "count": 29
            },
            {
                "word": "spread",
                "count": 74
            }
        ],
        "topic8": [
            {
                "word": "said",
                "count": 39
            },
            {
                "word": "countries",
                "count": 81
            },
            {
                "word": "imposed",
                "count": 35
            },
            {
                "word": "bans",
                "count": 40
            },
            {
                "word": "europe",
                "count": 48
            },
            {
                "word": "reduce",
                "count": 38
            },
            {
                "word": "italy",
                "count": 93
            },
            {
                "word": "people",
                "count": 101
            },
            {
                "word": "country",
                "count": 27
            },
            {
                "word": "covid",
                "count": 35
            }
        ],
        "topic9": [
            {
                "word": "coronavirus",
                "count": 155
            },
            {
                "word": "people",
                "count": 101
            },
            {
                "word": "spread",
                "count": 74
            },
            {
                "word": "countries",
                "count": 81
            },
            {
                "word": "bans",
                "count": 40
            },
            {
                "word": "world",
                "count": 49
            },
            {
                "word": "practice",
                "count": 29
            },
            {
                "word": "italy",
                "count": 93
            },
            {
                "word": "imposed",
                "count": 35
            },
            {
                "word": "mass",
                "count": 42
            }
        ]
    },
    "data": {
        "vocab": [
            "adopted",
            "announced",
            "bans",
            "cases",
            "china",
            "closing",
            "coronavirus",
            "countries",
            "country",
            "covid",
            "covid_19",
            "day",
            "deaths",
            "europe",
            "france",
            "government",
            "imposed",
            "including",
            "italy",
            "italy_spain",
            "know",
            "mass",
            "measures",
            "need",
            "need_know",
            "new",
            "number",
            "numbers",
            "outbreak",
            "people",
            "practice",
            "reduce",
            "restaurants",
            "said",
            "slow",
            "spread",
            "things",
            "things_need",
            "transmission",
            "world"
        ],
        "freq": [
            31,
            26,
            40,
            47,
            37,
            35,
            155,
            81,
            27,
            35,
            33,
            32,
            36,
            48,
            54,
            54,
            35,
            43,
            93,
            30,
            32,
            42,
            46,
            56,
            28,
            40,
            32,
            27,
            33,
            101,
            29,
            38,
            25,
            39,
            25,
            74,
            36,
            36,
            25,
            49
        ],
        "topic_term_dists": [
            [
                0.04250039853573905,
                0.00021144493067351845,
                0.00021144493052533745,
                0.043449919974721585,
                0.00021144493059599239,
                0.00021144493075279258,
                0.06426394337303433,
                0.0002114539804721595,
                0.00021144661034005243,
                0.00021144628160566338,
                0.00021144637262463466,
                0.0002114449305965834,
                0.00021144493064004688,
                0.046987741444738884,
                0.046149533970388214,
                0.10775324227884522,
                0.00021144636836988736,
                0.04461473874981667,
                0.04352187255546917,
                0.0430599571825212,
                0.00021144493056381871,
                0.044614838530799075,
                0.0615330839770494,
                0.053072588109666786,
                0.00021144493052938288,
                0.000211450671719202,
                0.00021144845733207695,
                0.0002114449305102976,
                0.00021144493064592876,
                0.09222714408615054,
                0.0002114520963644953,
                0.04499027472511661,
                0.046493441690666,
                0.00021145770893129804,
                0.04141304571842796,
                0.00021144928080083227,
                0.042500403639430036,
                0.042500403639430036,
                0.043913029589573535,
                0.00021145109382172966
            ],
            [
                0.02499999836437621,
                0.025000000568983098,
                0.024999998215467154,
                0.02500000290533755,
                0.024999999338911873,
                0.025000001830131287,
                0.025000003613142755,
                0.025000001051877243,
                0.02500000060950345,
                0.02499999892639917,
                0.024999998676335716,
                0.024999999345232282,
                0.02500000003632086,
                0.025000000201976423,
                0.025000001412257576,
                0.024999998811765865,
                0.02499999890802728,
                0.025000000079179824,
                0.025000003157420344,
                0.024999999100603226,
                0.02499999882683791,
                0.024999999169124185,
                0.02500000044635989,
                0.025000002104810605,
                0.024999998279232428,
                0.025000000334745028,
                0.024999999756740023,
                0.02499999797684504,
                0.025000000131428113,
                0.025000002998156117,
                0.02500000090884511,
                0.024999999361603204,
                0.024999998692191563,
                0.02500000037899934,
                0.024999999819641048,
                0.025000000777826107,
                0.02499999863113081,
                0.02499999863113081,
                0.02499999849777759,
                0.02499999912332584
            ],
            [
                0.0005985170019746169,
                0.03650970045412513,
                0.0005985170018997381,
                0.027836382322139763,
                0.0843912298709331,
                0.048480321868270296,
                0.19596453345457326,
                0.10212592559105958,
                0.0005985501082339633,
                0.0005985325586107441,
                0.0005985336069132539,
                0.000598611193424368,
                0.0005985170028200865,
                0.011836712939499418,
                0.01942700548172667,
                0.0005985170022005082,
                0.0005985170022504438,
                0.0005986555752817084,
                0.06559614591725504,
                0.05886621372613151,
                0.02760848811573708,
                0.0005985170023818211,
                0.0005985921093405278,
                0.0005986213550193351,
                0.0005985604442095364,
                0.03723262972828997,
                0.03766362764330253,
                0.0005985170017789228,
                0.006583259743233244,
                0.000598531289054881,
                0.02453907252144827,
                0.0559285697558053,
                0.019221708674475688,
                0.0005985315372170906,
                0.023368352912467787,
                0.07832337065601186,
                0.0005985170021095741,
                0.0005985170021095741,
                0.02652585882432467,
                0.0005985170023590671
            ],
            [
                0.0478164666309274,
                0.00043078194045760056,
                0.0004307783839443031,
                0.0004308230755121511,
                0.04781644424575713,
                0.06504698397725855,
                0.1022451276900683,
                0.0004307845870954244,
                0.0004307819327882841,
                0.0004307819611555534,
                0.000430781956786031,
                0.057873681530972346,
                0.04904401098669223,
                0.0004307819284909132,
                0.00043078192880095453,
                0.0004307783841001368,
                0.0004307783841255522,
                0.0004307819526173386,
                0.05165782481755309,
                0.00043078885540223763,
                0.05119437297404124,
                0.00043077838419380913,
                0.047816485331065736,
                0.06219689541102651,
                0.05345885331583651,
                0.052911786213298485,
                0.051293530213145595,
                0.0490427866432751,
                0.049042869523976004,
                0.04781645739406087,
                0.0004308054795449738,
                0.0004307783842440545,
                0.0004307783840689797,
                0.00043077838451098554,
                0.0004307912653579361,
                0.04781623636261597,
                0.00043078192808815075,
                0.00043078192808815075,
                0.0004307783840181305,
                0.05643192894503732
            ],
            [
                0.0015596392280937447,
                0.001559639235724263,
                0.0015596877667913857,
                0.036822482733903455,
                0.0015596392314513596,
                0.0015596392400415732,
                0.09784328037072794,
                0.018993739212351778,
                0.12235942418131303,
                0.049880025900705456,
                0.0338061755638254,
                0.04834898993225102,
                0.001559639233873086,
                0.0015596741544647561,
                0.05035081919959053,
                0.001559700471131053,
                0.01820669008028956,
                0.0015597833757429744,
                0.0015599283937659176,
                0.0015599498357784245,
                0.0015596392296878061,
                0.001559639230869966,
                0.09511777874978071,
                0.0015596392409968644,
                0.001559639227802208,
                0.0015596392348902676,
                0.0015597717149220495,
                0.0015596392267589493,
                0.07954164740646925,
                0.12633585884176815,
                0.001559639236871805,
                0.0015597076102640774,
                0.0015597009254016854,
                0.0015602180142936862,
                0.02822756838249657,
                0.04443703649122974,
                0.0015596392290126461,
                0.0015596392290126461,
                0.001559639228550807,
                0.11073577220710348
            ],
            [
                0.00031947708647322434,
                0.051269468573980216,
                0.0003194770864519001,
                0.00031956573499975784,
                0.00031947708661313575,
                0.00031972563059619313,
                0.02307495852142761,
                0.05143550136992255,
                0.051376888081331874,
                0.050975452020063386,
                0.05103499955049208,
                0.05036649866208751,
                0.050481561823774404,
                0.051435777021103746,
                0.05143591617158173,
                0.00031947708653761727,
                0.00031947708655152043,
                0.051098266554810166,
                0.05022882647531381,
                0.00031947708657924706,
                0.05048705281593165,
                0.0003194770865888916,
                0.00031947708677265604,
                0.05354982355010645,
                0.05044595848263226,
                0.05098885643151194,
                0.0003194770866734578,
                0.0505262872115072,
                0.05052632471305114,
                0.0003194770871395299,
                0.0003194845478239924,
                0.0003194770866166657,
                0.00031947708652044974,
                0.0003194770867627834,
                0.00031947708668265604,
                0.00031947752015326554,
                0.05143584757487936,
                0.05143584757487936,
                0.00031947708649233584,
                0.0003194770865823521
            ],
            [
                0.001081893501158082,
                0.034102413288185966,
                0.0010819623204702262,
                0.04153426182177417,
                0.0010819626442515134,
                0.001081893506898511,
                0.09186955954963148,
                0.0010820179105379174,
                0.0148557979156326,
                0.17468124089606832,
                0.16399207882306252,
                0.0010819002525297454,
                0.01204969887751949,
                0.0010819596139924603,
                0.0010819001111556554,
                0.035048463710200616,
                0.001081995715089922,
                0.06713884771854466,
                0.04797048083112852,
                0.0010819942189907999,
                0.0010819002350362895,
                0.0010819399093687343,
                0.0010820849286990704,
                0.0010823468539748952,
                0.0010819002397972977,
                0.06422385161424889,
                0.0010820558076944584,
                0.001081900228237724,
                0.0010820114147694296,
                0.01239631148311463,
                0.0010823651099175014,
                0.0010820711821138565,
                0.0010818935017025573,
                0.08996338369603939,
                0.0010818935035692438,
                0.12204217984794179,
                0.0010819001065774253,
                0.0010819001065774253,
                0.0010818935013789598,
                0.001081893502417297
            ],
            [
                0.02499999836437621,
                0.025000000568983098,
                0.024999998215467154,
                0.02500000290533755,
                0.024999999338911873,
                0.025000001830131287,
                0.025000003613142755,
                0.025000001051877243,
                0.02500000060950345,
                0.02499999892639917,
                0.024999998676335716,
                0.024999999345232282,
                0.02500000003632086,
                0.025000000201976423,
                0.025000001412257576,
                0.024999998811765865,
                0.02499999890802728,
                0.025000000079179824,
                0.025000003157420344,
                0.024999999100603226,
                0.02499999882683791,
                0.024999999169124185,
                0.02500000044635989,
                0.025000002104810605,
                0.024999998279232428,
                0.025000000334745028,
                0.024999999756740023,
                0.02499999797684504,
                0.025000000131428113,
                0.025000002998156117,
                0.02500000090884511,
                0.024999999361603204,
                0.024999998692191563,
                0.02500000037899934,
                0.024999999819641048,
                0.025000000777826107,
                0.02499999863113081,
                0.02499999863113081,
                0.02499999849777759,
                0.02499999912332584
            ],
            [
                0.0013487715291326055,
                0.0013490319585276606,
                0.11215518739414222,
                0.001348997807358276,
                0.0013487715316483628,
                0.0013487715380653962,
                0.0013489650462531514,
                0.1788284367998583,
                0.001349508160689566,
                0.001349241295443267,
                0.0013489595122239246,
                0.0013488136814696708,
                0.0013487715334437322,
                0.10925203082098386,
                0.0013487888406149336,
                0.0013490059045957248,
                0.1555852670577772,
                0.0013488930064032786,
                0.09725873525141446,
                0.0013488083974778405,
                0.0013487715303243343,
                0.0013488486066220965,
                0.0013488446024580878,
                0.001348900678442576,
                0.0013487715289139657,
                0.0013488696865841677,
                0.001348771532726191,
                0.0013487715281353346,
                0.0013491369257920788,
                0.0013503120840717253,
                0.0013487715356903752,
                0.10355754983594813,
                0.0013487715299794704,
                0.19884828338126959,
                0.0013488007552209147,
                0.001348875080582916,
                0.0013487715298215412,
                0.0013487715298215412,
                0.00134877152947759,
                0.0013488775205940046
            ],
            [
                0.000249286359231747,
                0.0027419383262104937,
                0.07948403824854065,
                0.040135125866072166,
                0.030163469566907825,
                0.030163589507811037,
                0.11677280726552369,
                0.08440953924150178,
                0.005234727024039807,
                0.00024928660950828215,
                0.00024928662542372495,
                0.00024928635931786955,
                0.020192084838898044,
                0.0002492898729369164,
                0.025177799062327366,
                0.0002492910714891447,
                0.056331968478353034,
                0.0002492863593818798,
                0.056833137671715245,
                0.00024928635929631014,
                0.00024928635927225706,
                0.052599446011444624,
                0.0002493029934082704,
                0.000249298384982398,
                0.00024928635922435066,
                0.0002492870165314612,
                0.03514931707102248,
                0.0002492863591978461,
                0.00024928635938657143,
                0.09357256361405228,
                0.06257078925967492,
                0.00024928703770327995,
                0.0002492863592605115,
                0.04048827275043949,
                0.00024929882199627114,
                0.0902022169415259,
                0.0002492863592550614,
                0.0002492863592550614,
                0.00024928635924342725,
                0.07254210450863655
            ]
        ],
        "doc_topic_dists": [
            [
                0.004762568338951273,
                0.00476190502449053,
                0.0047629713295038855,
                0.004762918642161261,
                0.004762726366017906,
                0.9571370096625994,
                0.004762987836548022,
                0.00476190502449053,
                0.00476244047363887,
                0.004762567301598429
            ],
            [
                0.005000576283281925,
                0.005000000244449344,
                0.005000906295242512,
                0.9549953181075882,
                0.005000909537584138,
                0.005000739480699013,
                0.005000531405032594,
                0.005000000244449344,
                0.005000146869353535,
                0.005000871532319453
            ],
            [
                0.9590874866614185,
                0.004545454777313888,
                0.0045460886424990255,
                0.004545898944165772,
                0.004545959001482002,
                0.004545994328676108,
                0.004545808584352263,
                0.004545454777313888,
                0.004545888328187023,
                0.004545965954591432
            ],
            [
                0.005000498939538405,
                0.0050000002591412945,
                0.005000459806708528,
                0.005000743606429556,
                0.005000571047824673,
                0.954995955530593,
                0.005000874680045826,
                0.0050000002591412945,
                0.005000592764443957,
                0.005000303106133401
            ],
            [
                0.005000498939538405,
                0.0050000002591412945,
                0.005000459806708528,
                0.005000743606429556,
                0.005000571047824673,
                0.954995955530593,
                0.005000874680045826,
                0.0050000002591412945,
                0.005000592764443957,
                0.005000303106133401
            ],
            [
                0.005556031611474268,
                0.005555555817109901,
                0.0055569453456358105,
                0.005556563731945318,
                0.0055561791162059785,
                0.005555739304255827,
                0.005556361438746739,
                0.005555555817109901,
                0.005556822997797716,
                0.9499942448197185
            ],
            [
                0.007145545151993146,
                0.0071428577734369714,
                0.007144136024312689,
                0.007145703488527337,
                0.007145977247890544,
                0.007145099392111187,
                0.9356975686301761,
                0.0071428577734369714,
                0.007143958000642716,
                0.007146296517472489
            ],
            [
                0.9608659022059362,
                0.004347826298680818,
                0.004348566488668847,
                0.004348326499090834,
                0.004348341101247428,
                0.0043483388751105285,
                0.004348248224862578,
                0.004347826298680818,
                0.004348221788687423,
                0.004348402219034492
            ],
            [
                0.011114484217116857,
                0.011111112297093231,
                0.5677238438162048,
                0.343371683139421,
                0.01111315395567363,
                0.011114328398815994,
                0.011113417186246567,
                0.011111112297093231,
                0.011111829728402831,
                0.011115034963931769
            ],
            [
                0.3205257793128763,
                0.005263158293034024,
                0.6373616252998017,
                0.0052639336088725844,
                0.005264167763614147,
                0.005264484865882363,
                0.005264091345226104,
                0.005263158293034024,
                0.0052653568202541455,
                0.005264244397404658
            ],
            [
                0.0034486820420603554,
                0.0034482760308152333,
                0.003448950813361019,
                0.003448890304832652,
                0.0034488576977113835,
                0.003448672125777863,
                0.003448653138254634,
                0.0034482760308152333,
                0.0034487707877069607,
                0.9689619710286647
            ],
            [
                0.9590874866614185,
                0.004545454777313888,
                0.0045460886424990255,
                0.004545898944165772,
                0.004545959001482002,
                0.004545994328676108,
                0.004545808584352263,
                0.004545454777313888,
                0.004545888328187023,
                0.004545965954591432
            ],
            [
                0.005556031611474268,
                0.005555555817109901,
                0.0055569453456358105,
                0.005556563731945318,
                0.0055561791162059785,
                0.005555739304255827,
                0.005556361438746739,
                0.005555555817109901,
                0.005556822997797716,
                0.9499942448197185
            ],
            [
                0.004762458088955263,
                0.004761905122235268,
                0.004762670906542346,
                0.004762437490726708,
                0.004766294510700298,
                0.004763353866982785,
                0.004762605737703052,
                0.004761905122235268,
                0.004763225179962871,
                0.9571331439739561
            ],
            [
                0.006250601141372534,
                0.006250000300425205,
                0.9437454347033861,
                0.006251160444107475,
                0.006250197502935377,
                0.006250631177868697,
                0.0062505087052639186,
                0.006250000300425205,
                0.006250640594653462,
                0.006250825129562176
            ],
            [
                0.004762568338951273,
                0.00476190502449053,
                0.0047629713295038855,
                0.004762918642161261,
                0.004762726366017906,
                0.9571370096625994,
                0.004762987836548022,
                0.00476190502449053,
                0.00476244047363887,
                0.004762567301598429
            ],
            [
                0.9590874866614185,
                0.004545454777313888,
                0.0045460886424990255,
                0.004545898944165772,
                0.004545959001482002,
                0.004545994328676108,
                0.004545808584352263,
                0.004545454777313888,
                0.004545888328187023,
                0.004545965954591432
            ],
            [
                0.004762425664666562,
                0.004761904994105349,
                0.004762719925239347,
                0.9571380255880928,
                0.0047632349762754605,
                0.004762571039913246,
                0.004762385101932318,
                0.004761904994105349,
                0.004762037523337322,
                0.004762790192332069
            ],
            [
                0.005263741892798998,
                0.005263158124247939,
                0.005264012996917018,
                0.005263927358211867,
                0.005264081130450733,
                0.005263790484573067,
                0.005263643217528187,
                0.005263158124247939,
                0.005264492021979322,
                0.952625994649045
            ],
            [
                0.006250601141372534,
                0.006250000300425205,
                0.9437454347033861,
                0.006251160444107475,
                0.006250197502935377,
                0.006250631177868697,
                0.0062505087052639186,
                0.006250000300425205,
                0.006250640594653462,
                0.006250825129562176
            ],
            [
                0.006250601141372534,
                0.006250000300425205,
                0.9437454347033861,
                0.006251160444107475,
                0.006250197502935377,
                0.006250631177868697,
                0.0062505087052639186,
                0.006250000300425205,
                0.006250640594653462,
                0.006250825129562176
            ],
            [
                0.00909407913945626,
                0.00909090952561368,
                0.009091681506254808,
                0.009092437799653538,
                0.00909454279843444,
                0.009091408589209109,
                0.00909155935875578,
                0.00909090952561368,
                0.795829784927684,
                0.13143268682932477
            ],
            [
                0.007144543569381851,
                0.007142857666883722,
                0.9357059712415717,
                0.0071438539613851715,
                0.0071437896216147755,
                0.00714428794119018,
                0.007144188496130611,
                0.007142857666883722,
                0.007143411448008031,
                0.0071442383869502295
            ],
            [
                0.004762385452799531,
                0.004761905163652589,
                0.004763181996475252,
                0.08051502354417552,
                0.00476245469280771,
                0.8813851860720469,
                0.0047627533572449495,
                0.004761905163652589,
                0.004762478420106425,
                0.004762726137038479
            ],
            [
                0.00909407913945626,
                0.00909090952561368,
                0.009091681506254808,
                0.009092437799653538,
                0.00909454279843444,
                0.009091408589209109,
                0.00909155935875578,
                0.00909090952561368,
                0.795829784927684,
                0.13143268682932477
            ],
            [
                0.005556323267721904,
                0.005555555972735987,
                0.9499883013189534,
                0.005557304210379169,
                0.00555784489107338,
                0.005557743157570089,
                0.005555913419590385,
                0.005555555972735987,
                0.0055588278382982205,
                0.005556629950941516
            ],
            [
                0.42243365632450225,
                0.006666667206550913,
                0.006667496093034045,
                0.00666837710965842,
                0.006667910362964229,
                0.006668349030250517,
                0.25793829413849173,
                0.006666667206550913,
                0.272954561608742,
                0.006668020919254837
            ],
            [
                0.005263741892798998,
                0.005263158124247939,
                0.005264012996917018,
                0.005263927358211867,
                0.005264081130450733,
                0.005263790484573067,
                0.005263643217528187,
                0.005263158124247939,
                0.005264492021979322,
                0.952625994649045
            ],
            [
                0.9608659022059362,
                0.004347826298680818,
                0.004348566488668847,
                0.004348326499090834,
                0.004348341101247428,
                0.0043483388751105285,
                0.004348248224862578,
                0.004347826298680818,
                0.004348221788687423,
                0.004348402219034492
            ],
            [
                0.9590874866614185,
                0.004545454777313888,
                0.0045460886424990255,
                0.004545898944165772,
                0.004545959001482002,
                0.004545994328676108,
                0.004545808584352263,
                0.004545454777313888,
                0.004545888328187023,
                0.004545965954591432
            ],
            [
                0.9590874866614185,
                0.004545454777313888,
                0.0045460886424990255,
                0.004545898944165772,
                0.004545959001482002,
                0.004545994328676108,
                0.004545808584352263,
                0.004545454777313888,
                0.004545888328187023,
                0.004545965954591432
            ],
            [
                0.47650659263560957,
                0.01111111180058726,
                0.434592615543756,
                0.01111286828311005,
                0.011114019679788723,
                0.011111991252854872,
                0.011113323075803894,
                0.01111111180058726,
                0.011112035015508222,
                0.011114330912394275
            ],
            [
                0.005556031611474268,
                0.005555555817109901,
                0.0055569453456358105,
                0.005556563731945318,
                0.0055561791162059785,
                0.005555739304255827,
                0.005556361438746739,
                0.005555555817109901,
                0.005556822997797716,
                0.9499942448197185
            ],
            [
                0.9590874866614185,
                0.004545454777313888,
                0.0045460886424990255,
                0.004545898944165772,
                0.004545959001482002,
                0.004545994328676108,
                0.004545808584352263,
                0.004545454777313888,
                0.004545888328187023,
                0.004545965954591432
            ],
            [
                0.004000507974313739,
                0.0040000004998276975,
                0.004001508684255411,
                0.004000403730311472,
                0.0040021996356106124,
                0.0040023749605890705,
                0.004001261582892214,
                0.0040000004998276975,
                0.004000735617330636,
                0.9639910068150415
            ],
            [
                0.005000498939538405,
                0.0050000002591412945,
                0.005000459806708528,
                0.005000743606429556,
                0.005000571047824673,
                0.954995955530593,
                0.005000874680045826,
                0.0050000002591412945,
                0.005000592764443957,
                0.005000303106133401
            ],
            [
                0.010002818590259366,
                0.010000000960573099,
                0.5980626455756958,
                0.3219241469398994,
                0.010001848361905628,
                0.010002740305496501,
                0.010001984018995986,
                0.010000000960573099,
                0.010000564646132908,
                0.010003249640468283
            ],
            [
                0.004167412424943319,
                0.00416666686064918,
                0.004167201498036571,
                0.004166963725308554,
                0.004167372893624074,
                0.004167252266740032,
                0.004166811422945982,
                0.00416666686064918,
                0.004168085699209016,
                0.9624955663478941
            ],
            [
                0.006667750435479479,
                0.006666667066298613,
                0.5206707294457824,
                0.0066676630779409305,
                0.006667110829967584,
                0.006667699539456867,
                0.4259898648587103,
                0.006666667066298613,
                0.0066678923730433695,
                0.006667955307021859
            ],
            [
                0.005556031611474268,
                0.005555555817109901,
                0.0055569453456358105,
                0.005556563731945318,
                0.0055561791162059785,
                0.005555739304255827,
                0.005556361438746739,
                0.005555555817109901,
                0.005556822997797716,
                0.9499942448197185
            ],
            [
                0.005000576283281925,
                0.005000000244449344,
                0.005000906295242512,
                0.9549953181075882,
                0.005000909537584138,
                0.005000739480699013,
                0.005000531405032594,
                0.005000000244449344,
                0.005000146869353535,
                0.005000871532319453
            ],
            [
                0.009091981430781505,
                0.009090909658076142,
                0.009093086368921442,
                0.00909235123639021,
                0.8194685812024733,
                0.00909230209268029,
                0.009091260123342096,
                0.009090909658076142,
                0.10779490079258224,
                0.009093717436676467
            ],
            [
                0.9590874866614185,
                0.004545454777313888,
                0.0045460886424990255,
                0.004545898944165772,
                0.004545959001482002,
                0.004545994328676108,
                0.004545808584352263,
                0.004545454777313888,
                0.004545888328187023,
                0.004545965954591432
            ],
            [
                0.020001198251482458,
                0.020000000448116922,
                0.02000524058999997,
                0.020002544364021685,
                0.02000294930403833,
                0.020001398265269078,
                0.8199832138121047,
                0.020000000448116922,
                0.02000000002140452,
                0.02000345449544551
            ],
            [
                0.020001198251482458,
                0.020000000448116922,
                0.02000524058999997,
                0.020002544364021685,
                0.02000294930403833,
                0.020001398265269078,
                0.8199832138121047,
                0.020000000448116922,
                0.02000000002140452,
                0.02000345449544551
            ],
            [
                0.008333945465587465,
                0.008333333628496439,
                0.008335110066466677,
                0.008334054904443996,
                0.00833425742806678,
                0.008333990385940083,
                0.9249921458266526,
                0.008333333628496439,
                0.008334930235976345,
                0.008334898429873188
            ],
            [
                0.005000576283281925,
                0.005000000244449344,
                0.005000906295242512,
                0.9549953181075882,
                0.005000909537584138,
                0.005000739480699013,
                0.005000531405032594,
                0.005000000244449344,
                0.005000146869353535,
                0.005000871532319453
            ],
            [
                0.006668157529333803,
                0.00666666724378029,
                0.0066672218727769446,
                0.006666900399628405,
                0.006670976294001902,
                0.006669029385715671,
                0.4446858447173706,
                0.00666666724378029,
                0.5019707794814084,
                0.00666775583220366
            ],
            [
                0.005556031611474268,
                0.005555555817109901,
                0.0055569453456358105,
                0.005556563731945318,
                0.0055561791162059785,
                0.005555739304255827,
                0.005556361438746739,
                0.005555555817109901,
                0.005556822997797716,
                0.9499942448197185
            ],
            [
                0.005556031611474268,
                0.005555555817109901,
                0.0055569453456358105,
                0.005556563731945318,
                0.0055561791162059785,
                0.005555739304255827,
                0.005556361438746739,
                0.005555555817109901,
                0.005556822997797716,
                0.9499942448197185
            ],
            [
                0.005556031611474268,
                0.005555555817109901,
                0.0055569453456358105,
                0.005556563731945318,
                0.0055561791162059785,
                0.005555739304255827,
                0.005556361438746739,
                0.005555555817109901,
                0.005556822997797716,
                0.9499942448197185
            ],
            [
                0.005000576283281925,
                0.005000000244449344,
                0.005000906295242512,
                0.9549953181075882,
                0.005000909537584138,
                0.005000739480699013,
                0.005000531405032594,
                0.005000000244449344,
                0.005000146869353535,
                0.005000871532319453
            ],
            [
                0.005556031611474268,
                0.005555555817109901,
                0.0055569453456358105,
                0.005556563731945318,
                0.0055561791162059785,
                0.005555739304255827,
                0.005556361438746739,
                0.005555555817109901,
                0.005556822997797716,
                0.9499942448197185
            ],
            [
                0.014288919411197231,
                0.014285714709924862,
                0.014286202386273391,
                0.014286009894826736,
                0.014286587176174087,
                0.014286625926719691,
                0.8714222219194365,
                0.014285714709924862,
                0.014285714305981714,
                0.014286289559540881
            ],
            [
                0.004762385452799531,
                0.004761905163652589,
                0.004763181996475252,
                0.08051502354417552,
                0.00476245469280771,
                0.8813851860720469,
                0.0047627533572449495,
                0.004761905163652589,
                0.004762478420106425,
                0.004762726137038479
            ],
            [
                0.004546047935778358,
                0.004545454898256299,
                0.004546892039447143,
                0.09930974871725588,
                0.004546177250147511,
                0.8643214345517223,
                0.004546445725552721,
                0.004545454898256299,
                0.004545984242170752,
                0.004546359741412602
            ],
            [
                0.005556031611474268,
                0.005555555817109901,
                0.0055569453456358105,
                0.005556563731945318,
                0.0055561791162059785,
                0.005555739304255827,
                0.005556361438746739,
                0.005555555817109901,
                0.005556822997797716,
                0.9499942448197185
            ],
            [
                0.009091822988521714,
                0.009090909820723112,
                0.009091873904023487,
                0.009092503469112808,
                0.14272600592390294,
                0.009093306892408629,
                0.27547950745707206,
                0.009090909820723112,
                0.5181502306030555,
                0.00909292912045645
            ],
            [
                0.004546964606238331,
                0.0045454549732174224,
                0.004546873035787991,
                0.004546366879834092,
                0.004546807231719314,
                0.8627750883244931,
                0.10085415979235858,
                0.0045454549732174224,
                0.004545986284395355,
                0.004546843898738313
            ],
            [
                0.011112735538505236,
                0.01111111156200015,
                0.011115145177507188,
                0.01111311175654411,
                0.011112693348829566,
                0.0111124786647553,
                0.01111349427073839,
                0.01111111156200015,
                0.3621249039516916,
                0.5489732141674283
            ],
            [
                0.005000576283281925,
                0.005000000244449344,
                0.005000906295242512,
                0.9549953181075882,
                0.005000909537584138,
                0.005000739480699013,
                0.005000531405032594,
                0.005000000244449344,
                0.005000146869353535,
                0.005000871532319453
            ],
            [
                0.006667564318016979,
                0.006666666955187039,
                0.006667460603412255,
                0.006667497836817256,
                0.9399930186007288,
                0.006667472417455546,
                0.006668966168796974,
                0.006666666955187039,
                0.00666666668046252,
                0.006668019463935395
            ],
            [
                0.4901807141139589,
                0.007692308280118428,
                0.007694066727050972,
                0.007694242617897982,
                0.007695873828311552,
                0.0076930536573344655,
                0.007693765772200496,
                0.007692308280118428,
                0.007695319358158705,
                0.44826834736485005
            ],
            [
                0.005000498939538405,
                0.0050000002591412945,
                0.005000459806708528,
                0.005000743606429556,
                0.005000571047824673,
                0.954995955530593,
                0.005000874680045826,
                0.0050000002591412945,
                0.005000592764443957,
                0.005000303106133401
            ],
            [
                0.004546047935778358,
                0.004545454898256299,
                0.004546892039447143,
                0.09930974871725588,
                0.004546177250147511,
                0.8643214345517223,
                0.004546445725552721,
                0.004545454898256299,
                0.004545984242170752,
                0.004546359741412602
            ],
            [
                0.004762568338951273,
                0.00476190502449053,
                0.0047629713295038855,
                0.004762918642161261,
                0.004762726366017906,
                0.9571370096625994,
                0.004762987836548022,
                0.00476190502449053,
                0.00476244047363887,
                0.004762567301598429
            ],
            [
                0.0076931523562264355,
                0.007692308129658145,
                0.007694365050238107,
                0.0076934774664368264,
                0.32325051876366745,
                0.00769391638619347,
                0.007695709999752228,
                0.007692308129658145,
                0.6151998380131501,
                0.0076944057050190254
            ],
            [
                0.006667564318016979,
                0.006666666955187039,
                0.006667460603412255,
                0.006667497836817256,
                0.9399930186007288,
                0.006667472417455546,
                0.006668966168796974,
                0.006666666955187039,
                0.00666666668046252,
                0.006668019463935395
            ],
            [
                0.00909407913945626,
                0.00909090952561368,
                0.009091681506254808,
                0.009092437799653538,
                0.00909454279843444,
                0.009091408589209109,
                0.00909155935875578,
                0.00909090952561368,
                0.795829784927684,
                0.13143268682932477
            ],
            [
                0.006250601141372534,
                0.006250000300425205,
                0.9437454347033861,
                0.006251160444107475,
                0.006250197502935377,
                0.006250631177868697,
                0.0062505087052639186,
                0.006250000300425205,
                0.006250640594653462,
                0.006250825129562176
            ],
            [
                0.010002697125004864,
                0.010000001244947548,
                0.010002218886596246,
                0.010004032768105386,
                0.010000531504478423,
                0.15728661953660517,
                0.6542785265032556,
                0.010000001244947548,
                0.010000000059404459,
                0.11842537112665465
            ],
            [
                0.008335810620778141,
                0.00833333413585005,
                0.258431166788894,
                0.008335544124322804,
                0.5618627005964751,
                0.008335368625922376,
                0.00833578625557079,
                0.00833333413585005,
                0.12136127934111124,
                0.008335675375225636
            ],
            [
                0.004762568338951273,
                0.00476190502449053,
                0.0047629713295038855,
                0.004762918642161261,
                0.004762726366017906,
                0.9571370096625994,
                0.004762987836548022,
                0.00476190502449053,
                0.00476244047363887,
                0.004762567301598429
            ],
            [
                0.007144543569381851,
                0.007142857666883722,
                0.9357059712415717,
                0.0071438539613851715,
                0.0071437896216147755,
                0.00714428794119018,
                0.007144188496130611,
                0.007142857666883722,
                0.007143411448008031,
                0.0071442383869502295
            ],
            [
                0.005556031611474268,
                0.005555555817109901,
                0.0055569453456358105,
                0.005556563731945318,
                0.0055561791162059785,
                0.005555739304255827,
                0.005556361438746739,
                0.005555555817109901,
                0.005556822997797716,
                0.9499942448197185
            ],
            [
                0.4901807141139589,
                0.007692308280118428,
                0.007694066727050972,
                0.007694242617897982,
                0.007695873828311552,
                0.0076930536573344655,
                0.007693765772200496,
                0.007692308280118428,
                0.007695319358158705,
                0.44826834736485005
            ],
            [
                0.9608659022059362,
                0.004347826298680818,
                0.004348566488668847,
                0.004348326499090834,
                0.004348341101247428,
                0.0043483388751105285,
                0.004348248224862578,
                0.004347826298680818,
                0.004348221788687423,
                0.004348402219034492
            ],
            [
                0.009092031820576371,
                0.009090909677869583,
                0.00909282295408326,
                0.009091114064640655,
                0.009091274217763665,
                0.009093537290559488,
                0.39574202299507316,
                0.009090909677869583,
                0.5315233977217154,
                0.009091979579848669
            ],
            [
                0.9624965738988706,
                0.004166666872069297,
                0.004167387356589257,
                0.004167124992290997,
                0.0041671669908632004,
                0.0041671362860765185,
                0.00416705330511572,
                0.004166666872069297,
                0.0041670290932132965,
                0.004167194332841742
            ],
            [
                0.005000498939538405,
                0.0050000002591412945,
                0.005000459806708528,
                0.005000743606429556,
                0.005000571047824673,
                0.954995955530593,
                0.005000874680045826,
                0.0050000002591412945,
                0.005000592764443957,
                0.005000303106133401
            ],
            [
                0.005000498939538405,
                0.0050000002591412945,
                0.005000459806708528,
                0.005000743606429556,
                0.005000571047824673,
                0.954995955530593,
                0.005000874680045826,
                0.0050000002591412945,
                0.005000592764443957,
                0.005000303106133401
            ],
            [
                0.9590874866614185,
                0.004545454777313888,
                0.0045460886424990255,
                0.004545898944165772,
                0.004545959001482002,
                0.004545994328676108,
                0.004545808584352263,
                0.004545454777313888,
                0.004545888328187023,
                0.004545965954591432
            ],
            [
                0.008336101834081245,
                0.008333334174761805,
                0.6173250168585828,
                0.3159979275593687,
                0.008334865925389087,
                0.008335305512335058,
                0.008334639376343758,
                0.008333334174761805,
                0.0083339582446965,
                0.008335516339679305
            ],
            [
                0.006667750435479479,
                0.006666667066298613,
                0.5206707294457824,
                0.0066676630779409305,
                0.006667110829967584,
                0.006667699539456867,
                0.4259898648587103,
                0.006666667066298613,
                0.0066678923730433695,
                0.006667955307021859
            ],
            [
                0.9590874866614185,
                0.004545454777313888,
                0.0045460886424990255,
                0.004545898944165772,
                0.004545959001482002,
                0.004545994328676108,
                0.004545808584352263,
                0.004545454777313888,
                0.004545888328187023,
                0.004545965954591432
            ],
            [
                0.9590874866614185,
                0.004545454777313888,
                0.0045460886424990255,
                0.004545898944165772,
                0.004545959001482002,
                0.004545994328676108,
                0.004545808584352263,
                0.004545454777313888,
                0.004545888328187023,
                0.004545965954591432
            ],
            [
                0.9590874866614185,
                0.004545454777313888,
                0.0045460886424990255,
                0.004545898944165772,
                0.004545959001482002,
                0.004545994328676108,
                0.004545808584352263,
                0.004545454777313888,
                0.004545888328187023,
                0.004545965954591432
            ],
            [
                0.9590874866614185,
                0.004545454777313888,
                0.0045460886424990255,
                0.004545898944165772,
                0.004545959001482002,
                0.004545994328676108,
                0.004545808584352263,
                0.004545454777313888,
                0.004545888328187023,
                0.004545965954591432
            ],
            [
                0.9590874866614185,
                0.004545454777313888,
                0.0045460886424990255,
                0.004545898944165772,
                0.004545959001482002,
                0.004545994328676108,
                0.004545808584352263,
                0.004545454777313888,
                0.004545888328187023,
                0.004545965954591432
            ],
            [
                0.005263741892798998,
                0.005263158124247939,
                0.005264012996917018,
                0.005263927358211867,
                0.005264081130450733,
                0.005263790484573067,
                0.005263643217528187,
                0.005263158124247939,
                0.005264492021979322,
                0.952625994649045
            ],
            [
                0.005556031611474268,
                0.005555555817109901,
                0.0055569453456358105,
                0.005556563731945318,
                0.0055561791162059785,
                0.005555739304255827,
                0.005556361438746739,
                0.005555555817109901,
                0.005556822997797716,
                0.9499942448197185
            ],
            [
                0.9608659022059362,
                0.004347826298680818,
                0.004348566488668847,
                0.004348326499090834,
                0.004348341101247428,
                0.0043483388751105285,
                0.004348248224862578,
                0.004347826298680818,
                0.004348221788687423,
                0.004348402219034492
            ],
            [
                0.005000576283281925,
                0.005000000244449344,
                0.005000906295242512,
                0.9549953181075882,
                0.005000909537584138,
                0.005000739480699013,
                0.005000531405032594,
                0.005000000244449344,
                0.005000146869353535,
                0.005000871532319453
            ],
            [
                0.4901807141139589,
                0.007692308280118428,
                0.007694066727050972,
                0.007694242617897982,
                0.007695873828311552,
                0.0076930536573344655,
                0.007693765772200496,
                0.007692308280118428,
                0.007695319358158705,
                0.44826834736485005
            ],
            [
                0.004762425664666562,
                0.004761904994105349,
                0.004762719925239347,
                0.9571380255880928,
                0.0047632349762754605,
                0.004762571039913246,
                0.004762385101932318,
                0.004761904994105349,
                0.004762037523337322,
                0.004762790192332069
            ],
            [
                0.004762568338951273,
                0.00476190502449053,
                0.0047629713295038855,
                0.004762918642161261,
                0.004762726366017906,
                0.9571370096625994,
                0.004762987836548022,
                0.00476190502449053,
                0.00476244047363887,
                0.004762567301598429
            ],
            [
                0.020001198244334183,
                0.020000000794435365,
                0.02000612129248795,
                0.020004802948573243,
                0.020001721166240775,
                0.020003163761332925,
                0.8199762856525914,
                0.020000000794435365,
                0.020003751277582006,
                0.02000295406798675
            ],
            [
                0.9624965738988706,
                0.004166666872069297,
                0.004167387356589257,
                0.004167124992290997,
                0.0041671669908632004,
                0.0041671362860765185,
                0.00416705330511572,
                0.004166666872069297,
                0.0041670290932132965,
                0.004167194332841742
            ],
            [
                0.9624965738988706,
                0.004166666872069297,
                0.004167387356589257,
                0.004167124992290997,
                0.0041671669908632004,
                0.0041671362860765185,
                0.00416705330511572,
                0.004166666872069297,
                0.0041670290932132965,
                0.004167194332841742
            ],
            [
                0.005000576283281925,
                0.005000000244449344,
                0.005000906295242512,
                0.9549953181075882,
                0.005000909537584138,
                0.005000739480699013,
                0.005000531405032594,
                0.005000000244449344,
                0.005000146869353535,
                0.005000871532319453
            ],
            [
                0.011111702992374503,
                0.011111111342966528,
                0.011111934845983076,
                0.011111347423897107,
                0.011111173990055885,
                0.011111678379442708,
                0.011111697669611913,
                0.011111111342966528,
                0.8999958268884005,
                0.011112415124301134
            ],
            [
                0.005000576283281925,
                0.005000000244449344,
                0.005000906295242512,
                0.9549953181075882,
                0.005000909537584138,
                0.005000739480699013,
                0.005000531405032594,
                0.005000000244449344,
                0.005000146869353535,
                0.005000871532319453
            ],
            [
                0.25500081269642383,
                0.006666667296986346,
                0.5142851453630831,
                0.006668426226870031,
                0.1840395568586991,
                0.00666833086218558,
                0.006668291835388282,
                0.006666667296986346,
                0.006667797118740819,
                0.006668304444636532
            ],
            [
                0.005556031611474268,
                0.005555555817109901,
                0.0055569453456358105,
                0.005556563731945318,
                0.0055561791162059785,
                0.005555739304255827,
                0.005556361438746739,
                0.005555555817109901,
                0.005556822997797716,
                0.9499942448197185
            ],
            [
                0.014287624202246964,
                0.014285715007207428,
                0.014287729307984779,
                0.014288326008032452,
                0.7285634568822745,
                0.01428695442599114,
                0.01428954012879277,
                0.014285715007207428,
                0.15713669770705987,
                0.014288241323202572
            ],
            [
                0.009094271254047069,
                0.009090909689793496,
                0.009092960262204646,
                0.009092895807293095,
                0.21226954611103838,
                0.00909223153955853,
                0.714990119989703,
                0.009090909689793496,
                0.00909336122123866,
                0.00909279443532955
            ],
            [
                0.005556209049108046,
                0.0055555558354575514,
                0.0055564277354883335,
                0.005556536351079511,
                0.0055563844340912215,
                0.005556520749384345,
                0.005556005522277063,
                0.0055555558354575514,
                0.005556679755056632,
                0.9499941247325998
            ],
            [
                0.005000576283281925,
                0.005000000244449344,
                0.005000906295242512,
                0.9549953181075882,
                0.005000909537584138,
                0.005000739480699013,
                0.005000531405032594,
                0.005000000244449344,
                0.005000146869353535,
                0.005000871532319453
            ]
        ],
        "doc_length": [
            20,
            19,
            21,
            19,
            19,
            17,
            13,
            22,
            8,
            18,
            28,
            21,
            17,
            20,
            15,
            20,
            21,
            20,
            18,
            15,
            15,
            10,
            13,
            20,
            10,
            17,
            14,
            18,
            22,
            21,
            21,
            8,
            17,
            21,
            24,
            19,
            9,
            23,
            14,
            17,
            19,
            10,
            21,
            4,
            4,
            11,
            19,
            14,
            17,
            17,
            17,
            19,
            17,
            6,
            20,
            21,
            17,
            10,
            21,
            8,
            19,
            14,
            12,
            19,
            21,
            20,
            12,
            14,
            10,
            15,
            9,
            11,
            20,
            13,
            17,
            12,
            22,
            10,
            23,
            19,
            19,
            21,
            11,
            14,
            21,
            21,
            21,
            21,
            21,
            18,
            17,
            22,
            19,
            12,
            20,
            20,
            4,
            23,
            23,
            19,
            8,
            19,
            14,
            17,
            6,
            10,
            17,
            19
        ],
        "model": [
            [
                20.099984642166383,
                0.10000000013241644,
                0.10000000006233625,
                20.549047874477196,
                0.10000000009575155,
                0.10000000016990807,
                30.392756758665023,
                0.10000428011142762,
                0.10000079450782703,
                0.10000063903737501,
                0.10000068208355782,
                0.10000000009603106,
                0.10000000011658652,
                22.222212354435587,
                21.825793545627715,
                50.96042836226924,
                0.10000068007133303,
                21.09993304960397,
                20.583076867564742,
                20.36462028310643,
                0.10000000008053544,
                21.099980239660603,
                29.10123400098888,
                25.09995771045008,
                0.10000000006424949,
                0.1000027152817808,
                0.10000166801754944,
                0.10000000005522336,
                0.10000000011936827,
                43.617571683795894,
                0.10000338904836893,
                21.277537674411484,
                21.988440017991806,
                0.10000604343539647,
                19.585735936705646,
                0.10000205746588181,
                20.099987055887524,
                20.099987055887524,
                20.76806925937871,
                0.10000291490942233
            ],
            [
                0.10000000896963937,
                0.1000000177880683,
                0.10000000837400307,
                0.10000002713348755,
                0.10000001286778264,
                0.10000002283266184,
                0.10000002996470882,
                0.10000001971964517,
                0.10000001795014973,
                0.10000001121773157,
                0.10000001021747759,
                0.10000001289306427,
                0.10000001565741902,
                0.10000001632004137,
                0.10000002116116674,
                0.10000001075919827,
                0.100000011144244,
                0.1000000158288549,
                0.1000000281418189,
                0.1000000119145479,
                0.10000001081948647,
                0.10000001218863178,
                0.10000001729757539,
                0.10000002393137929,
                0.10000000862906419,
                0.10000001685111587,
                0.1000000145390955,
                0.10000000741951445,
                0.10000001603784808,
                0.10000002750476188,
                0.10000001914751656,
                0.10000001295854798,
                0.100000010280901,
                0.10000001702813315,
                0.10000001479069963,
                0.10000001862344046,
                0.10000001003665794,
                0.10000001003665794,
                0.10000000950324497,
                0.10000001200543837
            ],
            [
                0.10000000018940026,
                6.100027301283411,
                0.10000000017688955,
                4.650892503141036,
                14.100055596139832,
                8.100074317044749,
                32.74168205401147,
                17.063162023393534,
                0.10000553157101515,
                0.10000259938643316,
                0.10000277453643028,
                0.10001573766212346,
                0.10000000033066102,
                1.9776736371509425,
                3.2458569187555626,
                0.1000000002271421,
                0.10000000023548532,
                0.10002315296649712,
                10.959779893483502,
                9.835345302374684,
                4.612816023094112,
                0.10000000025743579,
                0.10001254910042626,
                0.10001743545766693,
                0.100007258502006,
                6.220814058075447,
                6.292825030931177,
                0.10000000015670377,
                1.0999286125511187,
                0.10000238726950726,
                4.099979196408198,
                9.344524830074265,
                3.211556003833764,
                0.10000242873235783,
                3.9043757954462524,
                13.086239913979625,
                0.10000000021194888,
                0.10000000021194888,
                4.431930719937958,
                0.10000000025363406
            ],
            [
                11.100015338258327,
                0.1000008257287519,
                0.10000000012713525,
                0.10001037473495462,
                11.100010141811351,
                15.099871879450284,
                23.734971769910707,
                0.1000014401137642,
                0.10000082394841268,
                0.10000083053353172,
                0.10000082951919986,
                13.434676335113625,
                11.384974937689895,
                0.10000082295082993,
                0.10000082302280228,
                0.10000000016331016,
                0.10000000016921005,
                0.10000082855148826,
                11.991740256379119,
                0.10000243094965053,
                11.884155507149691,
                0.10000000018505507,
                11.100019679269634,
                14.438258233993086,
                12.409827274600076,
                12.28283225265295,
                11.907173662871088,
                11.384690721149715,
                11.384709960903635,
                11.100013194031296,
                0.10000629004364803,
                0.10000000019671892,
                0.10000000015607742,
                0.10000000025868375,
                0.1000029903917654,
                11.099961884250348,
                0.10000082285733349,
                0.10000082285733349,
                0.10000000014427339,
                13.099990881640544
            ],
            [
                0.1000000004958305,
                0.10000000098507944,
                0.10000311267055702,
                2.360961577087703,
                0.10000000071111201,
                0.10000000126189411,
                6.273456007864899,
                1.2178290315090021,
                7.845367222364693,
                3.1981771969785124,
                2.1675638264604324,
                3.1000111629068337,
                0.1000000008663868,
                0.10000223988366812,
                3.2283632356943275,
                0.10000392723968951,
                1.1673654934171442,
                0.10000924286722947,
                0.10001854104472141,
                0.10001991585065262,
                0.10000000059803756,
                0.10000000067383456,
                6.098703950763057,
                0.10000000132314489,
                0.10000000047713792,
                0.10000000093160583,
                0.10000849520579773,
                0.1000000004102469,
                5.100003024294283,
                8.100325844111575,
                0.10000000105865683,
                0.1000043849822835,
                0.10000395636633794,
                0.10003711075776708,
                1.809878080391602,
                2.8491869088131936,
                0.10000000055474806,
                0.10000000055474806,
                0.10000000052513613,
                7.100088966825426
            ],
            [
                0.10000000010092555,
                16.04793294933881,
                0.10000000009425082,
                0.10002774810864704,
                0.10000000014471944,
                0.10007779726815384,
                7.22272723826473,
                16.09990312283162,
                16.081556489807987,
                15.955902388568623,
                15.974541450025626,
                15.765292988278658,
                15.801309080410093,
                16.099989404819638,
                16.10003296051863,
                0.10000000012108129,
                0.10000000012543313,
                15.994344749561238,
                15.722200011429383,
                0.1000000001341119,
                15.803027824068177,
                0.10000000013713073,
                0.10000000019465112,
                16.76171026701784,
                15.79016482541168,
                15.960098123420865,
                0.10000000016360093,
                15.815308640839188,
                15.815320379253482,
                0.10000000030948686,
                0.10000233558947592,
                0.10000000014582434,
                0.10000000011570764,
                0.10000000019156087,
                0.10000000016648009,
                0.10000013584776313,
                16.10001148896234,
                16.10001148896234,
                0.10000000010690767,
                0.1000000001350838
            ],
            [
                0.10000000034292793,
                3.1521044694906393,
                0.10000636134909965,
                3.8390342413322185,
                0.1000063912763788,
                0.10000000087351886,
                8.49155298246442,
                0.10001149956906515,
                1.3731294208418217,
                16.145881392957488,
                15.157876372295101,
                0.1000006243758553,
                1.1137601719525088,
                0.10000611118789873,
                0.10000061130857187,
                3.2395484206971346,
                0.10000944803182531,
                6.205679937712506,
                4.433937438785247,
                0.10000930974657582,
                0.10000062275892573,
                0.10000428987889072,
                0.10001769409387845,
                0.1000419039885162,
                0.1000006231989883,
                5.936245274210799,
                0.10001500242370197,
                0.10000062213053067,
                0.10001089916167726,
                1.1457977621970892,
                0.10004359139514626,
                0.1000164234895864,
                0.10000000039325406,
                8.315364119319527,
                0.1000000005657929,
                11.280424564508607,
                0.10000061088540357,
                0.10000061088540357,
                0.10000000036334378,
                0.10000000045931784
            ],
            [
                0.10000000896963937,
                0.1000000177880683,
                0.10000000837400307,
                0.10000002713348755,
                0.10000001286778264,
                0.10000002283266184,
                0.10000002996470882,
                0.10000001971964517,
                0.10000001795014973,
                0.10000001121773157,
                0.10000001021747759,
                0.10000001289306427,
                0.10000001565741902,
                0.10000001632004137,
                0.10000002116116674,
                0.10000001075919827,
                0.100000011144244,
                0.1000000158288549,
                0.1000000281418189,
                0.1000000119145479,
                0.10000001081948647,
                0.10000001218863178,
                0.10000001729757539,
                0.10000002393137929,
                0.10000000862906419,
                0.10000001685111587,
                0.1000000145390955,
                0.10000000741951445,
                0.10000001603784808,
                0.10000002750476188,
                0.10000001914751656,
                0.10000001295854798,
                0.100000010280901,
                0.10000001702813315,
                0.10000001479069963,
                0.10000001862344046,
                0.10000001003665794,
                0.10000001003665794,
                0.10000000950324497,
                0.10000001200543837
            ],
            [
                0.10000000042803518,
                0.10001930906486098,
                8.31535849116958,
                0.10001677704451556,
                0.10000000061455731,
                0.10000000109032606,
                0.1000143480856773,
                13.258615985192945,
                0.10005461542725505,
                0.10003482962649657,
                0.1000139377842192,
                0.100003125667287,
                0.10000000074766877,
                8.100113987346763,
                0.10000128392802228,
                0.10001737738618267,
                11.535331548983224,
                0.10000900694015152,
                7.210912565025978,
                0.10000273390398694,
                0.1000000005163918,
                0.10000571507192825,
                0.10000541819703586,
                0.10000957575697221,
                0.1000000004118249,
                0.10000727797281296,
                0.10000000069446915,
                0.100000000354096,
                0.10002709149966185,
                0.10011421954613184,
                0.10000000091423834,
                7.6779163885382955,
                0.10000000049082305,
                14.742918273214848,
                0.1000021672952772,
                0.10000767789219552,
                0.10000000047911395,
                0.10000000047911395,
                0.10000000045361286,
                0.10000785879837912
            ],
            [
                0.10000000007873197,
                1.099915108399596,
                31.884632017602026,
                16.10000884980636,
                12.09992784347053,
                12.099975957175458,
                46.842838780803234,
                33.86047257783907,
                2.0998850656304024,
                0.10000010047593627,
                0.10000010686033807,
                0.10000000011327961,
                8.099955776571099,
                0.10000140958432348,
                10.099950578821689,
                0.1000018903776701,
                22.597292806677707,
                0.10000000013895703,
                22.798334370003232,
                0.10000000010463117,
                0.10000000009498239,
                21.100009729757645,
                0.10000667279704187,
                0.10000482414961077,
                0.10000000007576498,
                0.10000026375128782,
                14.099976110614204,
                0.10000000006513281,
                0.10000000014083904,
                37.5361748537291,
                25.099965157247023,
                0.10000027224425904,
                0.10000000009027073,
                16.241671990033407,
                0.10000499945558211,
                36.18417681999525,
                0.10000000008808445,
                0.10000000008808445,
                0.10000000008341746,
                29.09990935296713
            ]
        ]
    },
    "doc_count": 108,
    "place": "Spain",
    "folder": "socialdistancing",
    "date": "20200316"
}