{"mdsDat": {"x": [0.1894146033647806, -0.31576666378268753, -0.044339576947450894, 0.09707951537498148, 0.1959769828484996, 0.15242673927452194, -0.28211612010085413, -0.0003932849895117268, 0.08337226592991985, -0.07565446097219909], "y": [-0.12821536584545765, -0.06609848678483604, -0.11806224948063579, -0.0199641326499916, -0.01985505563074796, -0.13670581941110027, -0.041805625117756276, 0.3362957275667854, 0.17539490466282276, 0.01901610269091671], "topics": [1, 2, 3, 4, 5, 6, 7, 8, 9, 10], "cluster": [1, 1, 1, 1, 1, 1, 1, 1, 1, 1], "Freq": [28.87916177512036, 16.16218667797863, 14.565801345090673, 9.008209938160821, 7.982555899725559, 7.559617315670322, 4.6134722855406745, 4.064639214876102, 3.7226862037275423, 3.4416693441093362]}, "tinfo": {"Category": ["Default", "Default", "Default", "Default", "Default", "Default", "Default", "Default", "Default", "Default", "Default", "Default", "Default", "Default", "Default", "Default", "Default", "Default", "Default", "Default", "Default", "Default", "Default", "Default", "Default", "Default", "Default", "Default", "Default", "Default", "Topic1", "Topic1", "Topic1", "Topic1", "Topic1", "Topic1", "Topic1", "Topic1", "Topic1", "Topic1", "Topic1", "Topic1", "Topic1", "Topic1", "Topic1", "Topic1", "Topic1", "Topic1", "Topic1", "Topic1", "Topic1", "Topic1", "Topic1", "Topic1", "Topic1", "Topic1", "Topic1", "Topic1", "Topic1", "Topic1", "Topic1", "Topic1", "Topic1", "Topic1", "Topic1", "Topic1", "Topic1", "Topic1", "Topic1", "Topic1", "Topic1", "Topic1", "Topic1", "Topic1", "Topic1", "Topic1", "Topic1", "Topic1", "Topic1", "Topic1", "Topic1", "Topic1", "Topic1", "Topic1", "Topic1", "Topic1", "Topic1", "Topic1", "Topic1", "Topic1", "Topic1", "Topic1", "Topic1", "Topic1", "Topic1", "Topic1", "Topic1", "Topic1", "Topic1", "Topic1", "Topic2", "Topic2", "Topic2", "Topic2", "Topic2", "Topic2", "Topic2", "Topic2", "Topic2", "Topic2", "Topic2", "Topic2", "Topic2", "Topic2", "Topic2", "Topic2", "Topic2", "Topic2", "Topic2", "Topic2", "Topic2", "Topic2", "Topic2", "Topic2", "Topic2", "Topic2", "Topic2", "Topic2", "Topic2", "Topic2", "Topic2", "Topic2", "Topic2", "Topic2", "Topic2", "Topic2", "Topic2", "Topic2", "Topic2", "Topic2", "Topic2", "Topic2", "Topic2", "Topic2", "Topic2", "Topic2", "Topic2", "Topic2", "Topic2", "Topic2", "Topic3", "Topic3", "Topic3", "Topic3", "Topic3", "Topic3", "Topic3", "Topic3", "Topic3", "Topic3", "Topic3", "Topic3", "Topic3", "Topic3", "Topic3", "Topic3", "Topic3", "Topic3", "Topic3", "Topic3", "Topic3", "Topic3", "Topic3", "Topic3", "Topic3", "Topic3", "Topic3", "Topic3", "Topic3", "Topic3", "Topic3", "Topic3", "Topic3", "Topic3", "Topic3", "Topic3", "Topic3", "Topic3", "Topic3", "Topic3", "Topic3", "Topic3", "Topic3", "Topic3", "Topic3", "Topic3", "Topic3", "Topic3", "Topic3", "Topic3", "Topic3", "Topic3", "Topic3", "Topic3", "Topic3", "Topic3", "Topic3", "Topic3", "Topic3", "Topic4", "Topic4", "Topic4", "Topic4", "Topic4", "Topic4", "Topic4", "Topic4", "Topic4", "Topic4", "Topic4", "Topic4", "Topic4", "Topic4", "Topic4", "Topic4", "Topic4", "Topic4", "Topic4", "Topic4", "Topic4", "Topic4", "Topic4", "Topic4", "Topic4", "Topic4", "Topic4", "Topic4", "Topic4", "Topic4", "Topic4", "Topic4", "Topic4", "Topic4", "Topic4", "Topic4", "Topic4", "Topic4", "Topic4", "Topic4", "Topic4", "Topic4", "Topic4", "Topic4", "Topic4", "Topic4", "Topic4", "Topic4", "Topic4", "Topic4", "Topic4", "Topic4", "Topic4", "Topic4", "Topic4", "Topic4", "Topic4", "Topic4", "Topic5", "Topic5", "Topic5", "Topic5", "Topic5", "Topic5", "Topic5", "Topic5", "Topic5", "Topic5", "Topic5", "Topic5", "Topic5", "Topic5", "Topic5", "Topic5", "Topic5", "Topic5", "Topic5", "Topic5", "Topic5", "Topic5", "Topic5", "Topic5", "Topic5", "Topic5", "Topic5", "Topic5", "Topic5", "Topic5", "Topic5", "Topic5", "Topic5", "Topic5", "Topic5", "Topic5", "Topic5", "Topic5", "Topic5", "Topic5", "Topic5", "Topic5", "Topic5", "Topic5", "Topic5", "Topic5", "Topic5", "Topic5", "Topic5", "Topic5", "Topic5", "Topic5", "Topic5", "Topic6", "Topic6", "Topic6", "Topic6", "Topic6", "Topic6", "Topic6", "Topic6", "Topic6", "Topic6", "Topic6", "Topic6", "Topic6", "Topic6", "Topic6", "Topic6", "Topic6", "Topic6", "Topic6", "Topic6", "Topic6", "Topic6", "Topic6", "Topic6", "Topic6", "Topic6", "Topic6", "Topic6", "Topic6", "Topic6", "Topic6", "Topic6", "Topic6", "Topic6", "Topic6", "Topic6", "Topic6", "Topic6", "Topic6", "Topic6", "Topic6", "Topic6", "Topic6", "Topic6", "Topic6", "Topic6", "Topic6", "Topic6", "Topic6", "Topic6", "Topic6", "Topic6", "Topic6", "Topic6", "Topic6", "Topic6", "Topic6", "Topic7", "Topic7", "Topic7", "Topic7", "Topic7", "Topic7", "Topic7", "Topic7", "Topic7", "Topic7", "Topic7", "Topic7", "Topic7", "Topic7", "Topic7", "Topic7", "Topic7", "Topic7", "Topic7", "Topic7", "Topic7", "Topic7", "Topic7", "Topic7", "Topic7", "Topic7", "Topic7", "Topic7", "Topic7", "Topic7", "Topic7", "Topic7", "Topic7", "Topic7", "Topic7", "Topic7", "Topic7", "Topic7", "Topic7", "Topic7", "Topic7", "Topic7", "Topic7", "Topic7", "Topic7", "Topic8", "Topic8", "Topic8", "Topic8", "Topic8", "Topic8", "Topic8", "Topic8", "Topic8", "Topic8", "Topic8", "Topic8", "Topic8", "Topic8", "Topic8", "Topic8", "Topic8", "Topic8", "Topic8", "Topic8", "Topic8", "Topic8", "Topic8", "Topic8", "Topic8", "Topic8", "Topic8", "Topic8", "Topic8", "Topic8", "Topic8", "Topic8", "Topic8", "Topic8", "Topic8", "Topic8", "Topic8", "Topic8", "Topic8", "Topic8", "Topic8", "Topic8", "Topic9", "Topic9", "Topic9", "Topic9", "Topic9", "Topic9", "Topic9", "Topic9", "Topic9", "Topic9", "Topic9", "Topic9", "Topic9", "Topic9", "Topic9", "Topic9", "Topic9", "Topic9", "Topic9", "Topic9", "Topic9", "Topic9", "Topic9", "Topic9", "Topic9", "Topic9", "Topic9", "Topic9", "Topic9", "Topic9", "Topic9", "Topic9", "Topic9", "Topic9", "Topic9", "Topic9", "Topic9", "Topic9", "Topic9", "Topic9", "Topic9", "Topic9", "Topic9", "Topic9", "Topic10", "Topic10", "Topic10", "Topic10", "Topic10", "Topic10", "Topic10", "Topic10", "Topic10", "Topic10", "Topic10", "Topic10", "Topic10", "Topic10", "Topic10", "Topic10", "Topic10", "Topic10", "Topic10", "Topic10", "Topic10", "Topic10", "Topic10", "Topic10", "Topic10", "Topic10", "Topic10", "Topic10", "Topic10", "Topic10", "Topic10", "Topic10", "Topic10", "Topic10", "Topic10", "Topic10", "Topic10", "Topic10", "Topic10", "Topic10"], "Freq": [966.0, 769.0, 520.0, 696.0, 537.0, 332.0, 327.0, 286.0, 329.0, 321.0, 321.0, 171.0, 180.0, 437.0, 360.0, 454.0, 205.0, 198.0, 701.0, 198.0, 139.0, 114.0, 114.0, 361.0, 811.0, 595.0, 172.0, 370.0, 369.0, 272.0, 137.81872178990616, 127.07451546729676, 109.49311201426545, 70.42329433704407, 53.818644197649505, 52.841899133542086, 116.25102000912614, 48.93485670280224, 46.98139858023418, 46.98138947883832, 46.00469287412936, 46.00464382513448, 121.64075080845363, 43.074458103876395, 43.07444697444456, 39.16742567417965, 39.16729149849419, 38.19073024522902, 37.21395524190741, 37.21395027949902, 36.23720841287759, 36.23720048494792, 35.26046484806875, 35.26040517495061, 33.30700740510911, 33.30700740510911, 32.3302396086403, 31.3534603102144, 29.399993265704083, 28.42326252605592, 176.43865466715786, 142.0829155531367, 138.14594338443698, 138.1459433844341, 138.74019219747635, 139.32718499744234, 173.03635572164617, 153.75786093792664, 161.48698392674837, 138.00196288984523, 231.17205099613722, 89.64110165567776, 202.29236605735835, 104.34955801744502, 180.8905906531692, 155.58902607552486, 151.26002036897304, 279.31108584452465, 138.35863266522367, 100.36829485644793, 143.66640158412994, 109.33911247657153, 350.8542121431916, 387.1072912882428, 312.1290827078718, 258.7263723234279, 200.84670576163944, 201.01978408511087, 291.97108714560596, 232.87047007172805, 211.21230774287733, 238.88534201610648, 182.57570844346614, 196.95995455380123, 243.37462271129613, 183.06857965778508, 151.31643314102286, 143.9615834064203, 144.4116059662516, 139.862071196249, 149.88105064443795, 146.90526102741322, 146.90526102741322, 81.43768960339847, 78.46185270490794, 76.47801739431402, 76.47800972208074, 75.48608998746964, 75.48608998746964, 75.48608998746964, 75.48608998746964, 75.4860849780314, 75.4860849780314, 75.4860849780314, 75.4860849780314, 74.49415765216254, 74.494156234323, 74.494156234323, 74.49415411115278, 74.49410544943612, 74.49408417134485, 73.50222688752785, 73.50222688752785, 73.50222688752785, 73.50222688752785, 73.50222688752785, 73.50222688752785, 73.50222688752785, 73.50222688752785, 73.50222688752785, 87.49158874057264, 73.50222688752785, 259.6600502134119, 147.89719211099145, 86.08839305492035, 73.50222688752785, 271.74121174814564, 106.91804436877115, 156.20687883376587, 152.86167901254123, 86.5112562136341, 83.6988450023003, 106.87093955191786, 82.99648216434088, 87.83210929608008, 90.32926016577402, 77.46995065801678, 77.04074767201614, 75.84960365022793, 75.54281707061223, 44.543533229973, 44.543533229973, 44.543533229972994, 44.543533229972994, 43.55587512391637, 41.58049165462332, 39.605237303985376, 39.605190251482476, 39.6051185437562, 39.605054494709904, 38.617583843838, 38.617583843838, 38.617583843838, 38.617583843838, 38.617583843838, 38.617583843838, 38.617583843838, 38.617583843838, 38.61748880190019, 37.62991022136762, 37.62991022136762, 37.6298785595599, 37.62984621840011, 36.64225755847647, 36.64225631184553, 36.64225631184553, 36.642253114629696, 36.64223901817327, 36.64223901817327, 36.642231754646616, 36.642231754646616, 42.413320034836914, 76.42958824515968, 38.61759411383445, 40.48609870940117, 45.73139395078126, 239.96171467046224, 97.05229217721437, 171.1314482919558, 72.05907898997795, 64.8652208845412, 74.65068825748313, 98.56042451015203, 59.358474227418476, 73.23387579246841, 76.32429911657714, 43.098436245318155, 87.87781677712651, 71.82277750009042, 72.54950167826492, 68.61488825474096, 42.48253643531736, 53.94518584054491, 60.24863329689214, 41.68901415742383, 41.222049840163685, 47.94826456515633, 42.33080288520206, 43.10589042983592, 71.4279434806096, 67.44919022080573, 59.5397931763697, 59.5397610891003, 56.567748731563725, 55.57707467518728, 55.57707013481288, 54.586426527825836, 54.586426527825836, 54.586426527825836, 54.58642165227284, 54.58642164714333, 54.58642086541086, 54.58641904183273, 54.5864188688077, 53.595748886490966, 53.595748886490966, 53.595748886490966, 53.595748886490966, 53.595748886490966, 53.595748886490966, 53.595748886490966, 53.595748886490966, 53.595748886490966, 53.595748886490966, 53.595748886490966, 53.595748886490966, 53.595748886490966, 53.595748886490966, 53.595748886490966, 53.595748886490966, 127.63129780037269, 58.71296146108855, 57.953654758527584, 58.63411056421966, 129.04832523706733, 128.15800295229946, 116.54201569163686, 58.65580945574144, 59.01211253470629, 59.14882499094999, 56.28460009973847, 56.9786949083567, 57.29224462224347, 63.161992157571525, 63.16199196545357, 70.99821128343801, 67.69649064591238, 56.89231669819021, 57.10909844814296, 58.79403360692497, 58.19379570814856, 56.97639660649187, 57.78488616994955, 57.80170923720571, 57.774455141483855, 57.73099761762969, 57.08649976874937, 53.886388743509904, 29.65874263021448, 28.673406058658557, 24.732057562093804, 37.44303498781871, 33.488033973563034, 33.38181102011612, 33.368094250912506, 34.937371371921074, 37.45563262870116, 34.219431533031695, 21.05505661816405, 66.19550890884804, 23.588724373944984, 25.59291639431255, 35.592574300598436, 42.011859335518565, 42.20355937177841, 38.73537746999202, 77.71282216551693, 34.45558153582122, 32.567043416586934, 91.28214154853367, 19.206298131652225, 25.718654080716558, 31.4397325787791, 18.01156164565422, 59.3485221514787, 27.26701323820044, 23.746763070513094, 98.96303466203962, 77.51431834852349, 44.31608851722652, 51.489458885221275, 145.1964436397059, 65.20275231992288, 164.51042312844174, 132.03616899640747, 86.99854494391559, 52.46278231339913, 70.10928850614563, 69.65468796057182, 60.893436820740504, 81.27692142405542, 48.16508566494912, 74.0740399523243, 79.14047546030709, 65.64247166946662, 64.97628649080333, 54.108203977554936, 58.820250235231065, 54.000989190146996, 42.53621508076745, 26.683494753182373, 27.675005361717023, 36.24712659876526, 28.24939403059975, 26.322119689208517, 27.11648043872346, 23.89519370904946, 24.638721118740346, 33.51927836838332, 33.519278296626, 27.6132494896257, 25.088566197840095, 25.088566197839064, 23.567248051539885, 24.12553265927062, 16.4599567033055, 23.933250603388316, 35.55660368301626, 35.26096957257305, 35.785834447541546, 34.27738032835959, 34.277380314050355, 39.00740380829525, 37.2109635781031, 36.54244418854162, 44.01256590006681, 38.62144770647483, 34.97762144527505, 14.415253452732383, 14.415214799185632, 32.07786340860281, 38.30711526309944, 42.63602654109209, 40.610161215769054, 48.2917919370491, 115.05892051164507, 115.05890442868326, 113.74222878199696, 160.1761041938169, 42.837483204437774, 55.35460668000128, 91.19267401096575, 46.730460301736734, 87.46117231813035, 59.03333969586863, 54.46361390729405, 63.27718334388291, 65.53297555114976, 69.01978078832376, 62.69858196211287, 49.16626522743933, 52.16285027986382, 53.44118347852017, 44.63421598668643, 37.73629869274481, 39.02366033871378, 37.04093842615512, 57.50423986924034, 48.596558280226574, 34.74011266219118, 34.74011266219118, 34.74011266219118, 31.770814491112773, 31.770805266379124, 27.811756642977105, 24.842654799909788, 24.8426535182912, 24.84264628877634, 28.66345913869731, 24.680741219942078, 23.85294827491596, 23.727557685320072, 27.65752786683618, 23.78105461611373, 61.319412493060774, 28.135163584929153, 23.193513470059518, 26.276133733443025, 77.12022903093806, 77.1202290309375, 32.9838868225291, 29.299095349416138, 27.412955775465633, 25.51083475977499, 54.98382765875593, 98.22327683231185, 46.617143175982, 44.701967281842485, 51.422298886765695, 83.67822098904175, 75.64638159606882, 66.35647666935418, 58.36560506857382, 40.82808509423862, 40.4355721418205, 40.43556716158192, 33.548051786294536, 30.126655491145552, 35.27487857456908, 32.492524776876664, 30.916874679694967, 29.928435694521276, 55.308356840297975, 51.36480600765597, 35.590572144123705, 30.66114834850574, 30.661146884300322, 30.66111369268027, 28.689370817203006, 27.70348157623084, 27.703480602672432, 27.703480602672432, 27.703467967135037, 27.703461616642077, 26.717583245447916, 25.731700883612802, 25.731697867129473, 25.731697867129473, 25.731614873993372, 24.745814709174873, 24.745814709174873, 24.74581383475101, 24.745791750912463, 23.74552466697692, 23.739957389137942, 24.4529427866831, 22.760749218873993, 33.38899112243339, 32.37391819935299, 46.611220154402176, 25.093113027018806, 25.239431267278192, 66.39096767130323, 45.02634211253171, 33.48510759831662, 32.020021594002436, 53.83454767653118, 34.92479912867357, 30.089431268985596, 29.57605154034902, 39.57987344985368, 28.501763314091342, 26.713729434380422, 25.731757820629618, 24.25654376612489, 37.01348037165649, 35.08708383199108, 27.06868525835135, 22.36735162586753, 23.45403173747967, 20.671345927200125, 38.28265306138121, 32.295505389684486, 19.560075158639595, 29.937510644368157, 16.650804028057202, 17.781556236286324, 20.48161702294106, 24.00560314592543, 19.293569014887638, 10.912311163161874, 42.16040366707506, 29.782375158100663, 13.476194008491792, 21.69229075229205, 9.696141460126464, 12.850313882908567, 25.632221304702938, 10.912326284847362, 25.346149486313145, 25.411070879452943, 24.310412608756366, 12.143722410276155, 49.909115377173, 43.844909405930856, 21.189600206250997, 51.26447918149091, 24.083756448328565, 34.93406255167812, 37.05359107910368, 56.48314831938074, 80.46246602013241, 51.947032514585175, 43.868002366508605, 35.53175746200386, 25.423570456952067, 32.726968095736574, 25.704899284467704, 31.042510104029333, 31.042502881567472, 28.09853043512023, 22.634728595480762, 31.277924088186865, 14.920163528441194, 41.55264772791958, 28.87136486140564, 27.163569567467054, 52.03936207100691, 33.367969959099604, 28.46104867048099, 10.073032550556224, 21.542794978726757, 20.27303332772206, 66.26620127194572, 21.595106827233824, 11.7922782778463, 19.06216044170485, 18.962996838921743, 52.36670366234852, 16.613241054735767, 28.326367689673685, 15.395801747628273, 17.057862416037047, 17.0906673813052, 24.435001568626312, 24.435000986044972, 23.96493323945441, 22.093279281487774, 22.505065798499956, 89.73765163538751, 62.36416546432425, 35.81116393643648, 56.450673406735696, 21.74340303237814, 34.4724436056744, 22.180072492519088, 24.639579963906126, 21.98846259893067], "Term": ["said", "cases", "virus", "cuomo", "health", "county", "florida", "symptoms", "19", "covid_19", "covid", "seattle", "worker", "patient", "sunday", "positive", "governor", "people", "state", "death", "care", "king_county", "king", "cuomo_said", "case", "iran", "resident", "andrew", "andrew_cuomo", "officials", "condition_controlled", "first_positive", "patient_respiratory", "learned", "thirties", "late_thirties", "iran_currently", "state_officials", "coronavirus_", "lived", "19_", "woman_lived", "currently_isolated", "_covid", "thirties_contracted", "say_woman", "traveling_iran", "cuomo_statement", "virus_iran", "anxiety_general", "home_patient", "managing_situation", "patient_contracted", "cuomo_confirmed", "learned_first", "evening_learned", "low_ny", "positive_test", "wadsworth", "wadsworth_lab", "late", "controlled", "since_arriving", "arriving_new", "situation_since", "controlled_situation", "condition", "woman_late", "serious_condition", "arriving", "contracted", "confirmed_new", "contracted_virus", "patient_woman", "situation", "traveling", "virus_traveling", "patient", "positive_case", "case_coronavirus", "respiratory_symptoms", "late_30s", "cuomo", "case", "woman", "confirmed", "andrew_cuomo", "andrew", "state", "virus", "positive", "iran", "sunday", "home", "said", "isolated", "symptoms", "respiratory", "30s", "isolated_home", "adult", "one_adult", "adult_resident", "cases_florida", "30s_recently", "individuals", "cared", "appropriately_cared", "individuals_isolated", "appropriately", "isolated_appropriately", "manatee_county", "hillsborough_county", "hillsborough", "manatee", "resident_hillsborough", "case_involves", "involves", "florida_department", "york_case", "covid19", "via_twitter", "positive_covid19", "florida_2", "covid19_cases", "resident_manatee", "cared_new", "county_individuals", "twitter_one", "involves_woman", "recently_traveled", "county_one", "florida", "resident", "traveled_iran", "2_presumptive", "cases", "florida_new", "county", "isolated", "traveled", "recently", "health", "department", "new_cases", "reported", "department_health", "isolated_home", "cases_reported", "home", "beginning", "would_positive", "matter_would", "said_beginning", "beginning_matter", "buying", "told_cnn", "hospital_patients", "declared", "bringing", "spokesperson_told", "patient_went", "condition_statement", "hospital_manhattan", "health_spokesperson", "cnn_cause", "manhattan_remains", "remains_isolated", "need_isolated", "dow_constantine", "constantine", "also_reported", "executive", "patients_need", "executive_dow", "county_executive", "six_washington", "four_people", "died_coronavirus", "hampshire", "new_hampshire", "state_department", "hospital", "went_hospital", "statement_said", "matter", "said", "new_cases", "cases", "seattle", "department", "washington", "health", "department_health", "manhattan", "county", "surprise", "state", "home", "isolated", "reported", "expected", "china", "virus", "cnn", "cause_surprise", "positive_case", "coronavirus_new", "positive", "health_worker", "returned_iran", "knew_take", "iran_cuomo", "female", "hundreds", "positive_novel", "precautions_fortunate", "fortunate", "take_precautions", "somewhat", "first_patient", "coming_back", "female_health", "cuomo_revealed", "coronavirus_female", "worker_coming", "reported_hundreds", "patient_test", "worker_lives", "hundreds_confirmed", "iran_reported", "isolation_apartment", "manhattan_returned", "unique_case", "somewhat_unique", "apartment_somewhat", "back_iran", "revealed_state", "cases_isolation", "said_knew", "worker", "knew", "revealed", "test_positive", "health", "iran", "cuomo", "apartment", "precautions", "returned", "case_woman", "confirmed_cases", "care_worker", "novel", "novel_coronavirus", "state", "case", "coming", "health_care", "manhattan", "gov", "york_gov", "gov_andrew", "andrew_cuomo", "andrew", "cuomo_said", "woman", "quarantine_home", "residents", "affected", "calm", "korea", "south_korea", "coronavirus_test", "officials_said", "south", "reuters", "testing", "remain", "news", "iran_quarantine", "said_twitter", "president", "say", "italy", "state_confirmed", "quarantine", "trump", "restrictions", "first_coronavirus", "travel_restrictions", "pence", "confirms_first", "americans", "governor_andrew", "travelers", "reporting", "governor", "coronavirus_case", "confirmed_first", "woman_30s", "state", "test", "said", "cuomo", "cuomo_said", "city", "andrew", "andrew_cuomo", "york_state", "woman", "travel", "iran", "case", "virus", "confirmed", "officials", "home", "sunday", "confirms", "low_new", "ago", "reported_first", "york_said", "saying", "sunday_woman", "virus_recent", "facility", "de_blasio", "blasio", "quarantined_manhattan", "bill_de", "mayor_bill", "case_reported", "home_respiratory", "one_confirmed", "state_new", "risk_remains", "managing", "general_risk", "diligently_managing", "diligently", "reason", "reason_undue", "general", "said_woman", "low", "remains_low", "said_would", "infectious_disease", "mayor", "disease", "risk", "patients", "case_covid", "covid_19", "covid", "19", "said", "isolation", "city", "woman", "york_city", "case", "manhattan", "respiratory", "reported", "confirmed", "cuomo", "state", "york_state", "cuomo_said", "virus", "situation", "anxiety", "gov", "andrew", "public_health", "kirkland", "center_kirkland", "care_center", "life_care", "flu", "common", "health_agency", "effort", "seattle_area", "second_victim", "help", "ground", "team", "protocols", "infection", "dozens", "center", "agency", "10", "like", "king_county", "king", "life", "area", "victim", "time", "public", "seattle", "seattle_king", "nursing", "according", "county", "symptoms", "health", "cases", "19", "covid_19", "covid", "person", "illness", "officials", "reported", "people", "care", "stocks", "stock", "economy", "markets", "oil", "essential", "stock_markets", "largest", "non_essential", "non", "financial", "companies", "fall", "financial_crisis", "since_2008", "2008", "key", "setting", "index", "noting", "plunged", "protect", "ministers", "month", "begun", "crisis", "workers", "conference", "worldwide", "border", "week", "global", "last_week", "world", "sunday", "travel", "united", "united_states", "cases", "confirms", "states", "said_sunday", "tested_positive", "toll", "death_toll", "saturday", "government", "likely", "infectious", "tested", "local", "coronavirus_outbreak", "times", "update", "us_death", "place", "york_times", "000", "infectious_disease", "outbreak", "disease", "travel_restrictions", "last_week", "report", "3_000", "monday", "exactly", "live", "quarantined", "updates", "released", "travel", "quarantine", "live_updates", "death", "year", "second", "china", "positive", "said", "virus", "patient", "officials", "week", "case", "health", "year_old", "old", "39", "california", "coronavirus_cases", "americans", "health_care", "including", "monday", "care", "care_worker", "year", "new_coronavirus", "2020", "announced", "people", "tested", "total", "ship", "cruise", "worker", "weekend", "outbreak", "isolated_manhattan", "cruise_ship", "york_first", "rhode_island", "rhode", "island", "deaths", "health_officials", "cases", "health", "washington", "virus", "recently", "reported", "city", "case", "florida"], "Total": [966.0, 769.0, 520.0, 696.0, 537.0, 332.0, 327.0, 286.0, 329.0, 321.0, 321.0, 171.0, 180.0, 437.0, 360.0, 454.0, 205.0, 198.0, 701.0, 198.0, 139.0, 114.0, 114.0, 361.0, 811.0, 595.0, 172.0, 370.0, 369.0, 272.0, 138.71240586393859, 127.96820944585966, 110.38679709077242, 71.31699254212586, 54.71232474965685, 53.73557962236958, 118.25007264574262, 49.828599960258515, 47.87510946505643, 47.87510910938063, 46.89836352931683, 46.89836398681723, 124.0975449461435, 43.96812811243319, 43.968128352789094, 40.061148250695915, 40.061150148362515, 39.08440244439259, 38.10765839004306, 38.10765867378207, 37.13091281224338, 37.13091360713741, 36.15416812294858, 36.15416888463204, 34.20067680955936, 34.20067680955936, 33.22393258681736, 32.247187109882795, 30.293696849269015, 29.316951448490286, 207.35105060863785, 165.09454788710372, 160.16661148966529, 160.16661148966543, 161.16121812690506, 162.15616360232698, 206.55772355833292, 181.86241378270702, 192.7692827285055, 162.2180476661322, 299.70554712941225, 102.6788040848859, 261.5017753453187, 123.24153336870415, 242.4150610209164, 208.58761864873887, 201.7278653152142, 437.3737167982425, 187.10181206242393, 125.32975835893538, 199.71065348893435, 141.88838750087385, 696.8703743768303, 811.9368034324327, 657.7327888190305, 540.7427297719167, 369.4378108057645, 370.43050078191527, 701.9798359918593, 520.9963151529183, 454.3993837272009, 595.7833380847496, 360.28073208248543, 447.6369550578645, 966.0358626782252, 480.9634710934794, 286.82848313277077, 230.36578844886373, 280.0494695217956, 245.64925361777497, 150.7732093917903, 147.79741065081316, 147.79741065081316, 82.32983967536204, 79.35404101952734, 77.370175185602, 77.37017527584626, 76.37824234188497, 76.37824234188497, 76.37824234188497, 76.37824234188497, 76.37824223402221, 76.37824223402221, 76.37824223402221, 76.37824223402221, 75.38630939020987, 75.38630942988704, 75.38630942988704, 75.38630935536892, 75.38630906196077, 75.38630994304782, 74.3943765124321, 74.3943765124321, 74.3943765124321, 74.3943765124321, 74.3943765124321, 74.3943765124321, 74.3943765124321, 74.3943765124321, 74.3943765124321, 89.26746123971338, 74.3943765124321, 327.2855844382265, 172.54328484786095, 90.29194303757414, 74.3943765124321, 769.6080113437984, 146.5370593319427, 332.75464969148527, 480.9634710934794, 118.92377234892726, 115.17794402904401, 537.7338249873151, 150.54951821953293, 235.58720938416388, 428.1208272379449, 137.62183125193798, 245.64925361777497, 138.58365281990473, 447.6369550578645, 45.43613479634432, 45.43613479634432, 45.43613479634431, 45.43613479634431, 44.44847270657394, 42.473148961246906, 40.49782447426163, 40.497825264730686, 40.49782629305008, 40.49782507557789, 39.510162372007265, 39.510162372007265, 39.510162372007265, 39.510162372007265, 39.510162372007265, 39.510162372007265, 39.510162372007265, 39.510162372007265, 39.510162067514926, 38.522500371551885, 38.522500371551885, 38.52250096598417, 38.52250021786818, 37.53483834454345, 37.5348382781823, 37.5348382781823, 37.53483833194178, 37.53483827222282, 37.53483827222282, 37.534838613386604, 37.534838613386604, 45.4125925256687, 107.44788233779082, 40.51014002654384, 43.48340291366431, 52.28648114227108, 966.0358626782252, 235.58720938416388, 769.6080113437984, 171.07597374088778, 150.54951821953293, 220.3293170052836, 537.7338249873151, 137.62183125193798, 273.1699399601928, 332.75464969148527, 56.16435854456964, 701.9798359918593, 447.6369550578645, 480.9634710934794, 428.1208272379449, 58.16628023732919, 173.0416812711006, 520.9963151529183, 56.14877954631206, 53.21338245868964, 187.10181206242393, 82.71193230505219, 454.3993837272009, 72.32025311752695, 68.3574134123502, 60.43210124775376, 60.432101320875205, 57.46006328510581, 56.46938384401987, 56.46938401578193, 55.47870443810983, 55.47870443810983, 55.47870443810983, 55.47870438120617, 55.47870447547457, 55.47870434507924, 55.47870449449816, 55.478704365840535, 54.488025120663934, 54.488025120663934, 54.488025120663934, 54.488025120663934, 54.488025120663934, 54.488025120663934, 54.488025120663934, 54.488025120663934, 54.488025120663934, 54.488025120663934, 54.488025120663934, 54.488025120663934, 54.488025120663934, 54.488025120663934, 54.488025120663934, 54.488025120663934, 180.79031425153553, 62.43981777939296, 61.40304070140129, 68.40564682312946, 537.7338249873151, 595.7833380847496, 696.8703743768303, 80.1908841100104, 86.87809746830577, 95.14758139719933, 78.06454244722345, 87.17011093530685, 91.45251122560194, 234.14895983867913, 234.14895987470172, 701.9798359918593, 811.9368034324327, 93.0100714701768, 99.45405357840319, 273.1699399601928, 233.37093467445175, 138.88813236845365, 219.39365923936705, 369.4378108057645, 370.43050078191527, 361.7494606199403, 657.7327888190305, 55.181667462915435, 30.551633574599897, 29.56629118407749, 25.624919131497986, 39.460434440849575, 35.51957426975009, 35.46784531683437, 37.421237886493145, 39.500319757935884, 44.33272237807098, 41.41663641757609, 27.582691744178987, 92.87172328138288, 33.428903027829534, 38.33011662505679, 55.998784239734626, 66.80687508799255, 68.00846687309459, 62.86342319141174, 133.08138853303052, 59.13975875702146, 56.14334999552067, 158.5491628833249, 33.47700566606891, 45.16843000973371, 56.041746007207195, 33.72455830811416, 114.81078178497535, 53.211050442469144, 46.46209889137934, 205.9937477650537, 178.0810378379754, 107.84239660743224, 134.43882544706565, 701.9798359918593, 200.01196989634713, 966.0358626782252, 696.8703743768303, 361.7494606199403, 176.46017467225516, 370.43050078191527, 369.4378108057645, 260.9564769735001, 657.7327888190305, 144.92086052628878, 595.7833380847496, 811.9368034324327, 520.9963151529183, 540.7427297719167, 272.9339094694169, 447.6369550578645, 360.28073208248543, 124.02759534860179, 27.572610391260483, 29.570336741758776, 39.76040244706809, 31.54945266132785, 30.48672382578074, 32.581976960667866, 32.33193969410013, 34.37570896448082, 47.52695436827025, 47.52695436567237, 39.36648370863683, 36.38295497668552, 36.38295497668549, 35.247543383560306, 36.24919589568984, 26.139753046713423, 38.194108169016246, 59.22431891291415, 59.21112965233635, 60.21129092808371, 58.19050271750346, 58.19050271686506, 67.19223387661583, 64.18185213777515, 63.175281840027864, 77.45328457168591, 68.17759147380782, 62.12872372947015, 26.048531488938938, 26.118324376819352, 60.253412062440844, 73.31610601866498, 84.08087040152587, 80.39131139642073, 100.8157814849984, 321.4749368794538, 321.4749362514849, 329.2782585908743, 966.0358626782252, 101.35503748495465, 176.46017467225516, 657.7327888190305, 138.5771934014304, 811.9368034324327, 273.1699399601928, 230.36578844886373, 428.1208272379449, 540.7427297719167, 696.8703743768303, 701.9798359918593, 260.9564769735001, 361.7494606199403, 520.9963151529183, 242.4150610209164, 88.82389772087876, 233.37093467445175, 370.43050078191527, 58.39670105889506, 49.488972908129824, 35.632506982384704, 35.632506982384704, 35.632506982384704, 32.66326379643362, 32.663263995825105, 28.704272931915987, 25.73503124200493, 25.735031231857935, 25.735031156494607, 30.695425787919945, 26.73668223905993, 26.789995116085393, 26.794121351366027, 31.776426659367036, 27.708118532443997, 76.15874898872586, 35.58807969655097, 32.72827209204487, 37.61334119817198, 114.73477033184976, 114.73477033184977, 49.8623270066732, 45.470186280560505, 44.32695623019081, 43.67358232859411, 94.87680506799825, 171.07597374088778, 83.06531146228438, 82.07361407653985, 132.51302821019138, 332.75464969148527, 286.82848313277077, 537.7338249873151, 769.6080113437984, 329.2782585908743, 321.4749368794538, 321.4749362514849, 153.86748419659475, 82.41917269231146, 272.9339094694169, 428.1208272379449, 198.62660731899024, 139.15065784789178, 56.20113077454732, 52.25757438513275, 36.48334913970257, 31.553903701234123, 31.553903705321037, 31.553903924633136, 29.582125547718043, 28.596236468124236, 28.596236469022017, 28.596236469022017, 28.596236554206815, 28.596236724480544, 27.610347447174124, 26.62445832879155, 26.62445834811419, 26.62445834811419, 26.624459779999206, 25.63856924390119, 25.63856924390119, 25.638569244430276, 25.63856920286503, 25.638015715448237, 26.618804195063284, 27.642709539550083, 26.616023850719262, 40.43795660922228, 39.66939869684326, 58.16700137648177, 31.55081986521977, 34.48778208347004, 95.63138365380105, 89.68945941949627, 57.14202668603074, 53.24910293071909, 360.28073208248543, 144.92086052628878, 71.80580758214442, 65.8925018902994, 769.6080113437984, 124.02759534860179, 104.71974515384441, 86.35591888753181, 36.53877695433045, 56.18441011380934, 54.21792265412137, 43.39567371307096, 36.297897272922434, 40.21606390552464, 35.95209505117351, 67.40862168981319, 60.157715542717035, 36.53232046047562, 57.83733134196367, 32.529134126947845, 35.29155291140796, 43.36403750378123, 50.95964655148083, 41.50091134292248, 26.118324376819352, 101.70825855817851, 73.31610601866498, 33.47700566606891, 57.14202668603074, 25.665490381442797, 34.57599735945856, 71.30197607028776, 30.363491755503944, 72.12224062775479, 72.78265594034993, 70.1519843620682, 35.25516552069966, 144.92086052628878, 133.08138853303052, 66.21335862688476, 198.6503792648157, 78.32140344930271, 142.30661188262258, 173.0416812711006, 454.3993837272009, 966.0358626782252, 520.9963151529183, 437.3737167982425, 272.9339094694169, 95.63138365380105, 811.9368034324327, 537.7338249873151, 31.991927476120733, 31.991927637752482, 28.990741540772408, 27.97527266321842, 53.74385157620344, 33.72455830811416, 99.45405357840319, 74.6258468366162, 71.30197607028776, 139.15065784789178, 91.45251122560194, 78.32140344930271, 28.000537447546684, 62.39477737725335, 60.403872951744454, 198.62660731899024, 67.40862168981319, 37.706218235305606, 63.635668572190966, 63.63487075133605, 180.79031425153553, 58.5134114495264, 101.70825855817851, 55.50113995796926, 61.63567785830473, 62.945947688302596, 92.25739526258081, 92.25739525490286, 94.19624128038615, 90.03925096158278, 93.2771754484927, 769.6080113437984, 537.7338249873151, 220.3293170052836, 520.9963151529183, 115.17794402904401, 428.1208272379449, 176.46017467225516, 811.9368034324327, 327.2855844382265], "loglift": [30.0, 29.0, 28.0, 27.0, 26.0, 25.0, 24.0, 23.0, 22.0, 21.0, 20.0, 19.0, 18.0, 17.0, 16.0, 15.0, 14.0, 13.0, 12.0, 11.0, 10.0, 9.0, 8.0, 7.0, 6.0, 5.0, 4.0, 3.0, 2.0, 1.0, 1.2356, 1.235, 1.2339, 1.2294, 1.2256, 1.2253, 1.225, 1.224, 1.2232, 1.2232, 1.2228, 1.2228, 1.2221, 1.2215, 1.2215, 1.2195, 1.2195, 1.2189, 1.2183, 1.2183, 1.2177, 1.2177, 1.217, 1.217, 1.2156, 1.2156, 1.2148, 1.2139, 1.2121, 1.2111, 1.0806, 1.0919, 1.0941, 1.0941, 1.0922, 1.0903, 1.065, 1.0742, 1.065, 1.0804, 0.9824, 1.1063, 0.9853, 1.0757, 0.9493, 0.9489, 0.9541, 0.7936, 0.9402, 1.0199, 0.9127, 0.9815, 0.5558, 0.5013, 0.4967, 0.5049, 0.6326, 0.6308, 0.3648, 0.4368, 0.4759, 0.3282, 0.5623, 0.4211, -0.1365, 0.2761, 0.6025, 0.7719, 0.5798, 0.6788, 1.8166, 1.8164, 1.8164, 1.8116, 1.8112, 1.8109, 1.8109, 1.8107, 1.8107, 1.8107, 1.8107, 1.8107, 1.8107, 1.8107, 1.8107, 1.8106, 1.8106, 1.8106, 1.8106, 1.8106, 1.8106, 1.8104, 1.8104, 1.8104, 1.8104, 1.8104, 1.8104, 1.8104, 1.8104, 1.8104, 1.8024, 1.8104, 1.591, 1.6684, 1.7748, 1.8104, 0.7815, 1.5073, 1.0663, 0.6762, 1.5043, 1.5032, 0.2068, 1.227, 0.8358, 0.2666, 1.2479, 0.6629, 1.2198, 0.0432, 1.9067, 1.9067, 1.9067, 1.9067, 1.9062, 1.9053, 1.9042, 1.9042, 1.9042, 1.9042, 1.9036, 1.9036, 1.9036, 1.9036, 1.9036, 1.9036, 1.9036, 1.9036, 1.9036, 1.9031, 1.9031, 1.903, 1.903, 1.9024, 1.9024, 1.9024, 1.9024, 1.9024, 1.9024, 1.9024, 1.9024, 1.8582, 1.5859, 1.8786, 1.8551, 1.7925, 0.5338, 1.0397, 0.423, 1.0619, 1.0845, 0.8442, 0.2298, 1.0856, 0.6101, 0.4541, 1.6617, -0.1515, 0.0967, 0.035, 0.0956, 1.6123, 0.7609, -0.2308, 1.6287, 1.6712, 0.565, 1.2566, -0.4288, 2.3946, 2.3937, 2.3922, 2.3922, 2.3914, 2.3911, 2.3911, 2.3908, 2.3908, 2.3908, 2.3908, 2.3908, 2.3908, 2.3908, 2.3908, 2.3905, 2.3905, 2.3905, 2.3905, 2.3905, 2.3905, 2.3905, 2.3905, 2.3905, 2.3905, 2.3905, 2.3905, 2.3905, 2.3905, 2.3905, 2.3905, 2.0588, 2.3455, 2.3492, 2.2529, 0.9799, 0.8704, 0.6187, 2.0943, 2.0203, 1.9317, 2.0799, 1.9818, 1.9394, 1.0968, 1.0968, 0.1158, -0.0774, 1.9155, 1.8523, 0.871, 1.0182, 1.516, 1.0729, 0.5521, 0.5489, 0.5719, -0.0372, 2.5042, 2.4983, 2.4972, 2.4924, 2.4754, 2.469, 2.4673, 2.4133, 2.4052, 2.3593, 2.337, 2.2579, 2.1893, 2.1793, 2.124, 2.0747, 2.0641, 2.0508, 2.0437, 1.99, 1.9877, 1.9833, 1.9758, 1.9723, 1.9647, 1.9499, 1.9007, 1.8681, 1.8593, 1.8567, 1.7948, 1.6961, 1.6386, 1.5682, 0.9521, 1.407, 0.7577, 0.8644, 1.1029, 1.3149, 0.8633, 0.8595, 1.0727, 0.437, 1.4264, 0.4431, 0.1997, 0.4564, 0.409, 0.9097, 0.4984, 0.63, 1.4578, 2.5496, 2.5161, 2.4898, 2.4719, 2.4355, 2.3987, 2.28, 2.2493, 2.2332, 2.2332, 2.2277, 2.2107, 2.2107, 2.1798, 2.1752, 2.1198, 2.1149, 2.0721, 2.064, 2.062, 2.0531, 2.0531, 2.0385, 2.0372, 2.0349, 2.0171, 2.014, 2.0078, 1.9907, 1.988, 1.952, 1.9332, 1.9033, 1.8995, 1.8463, 1.5549, 1.5549, 1.5194, 0.7854, 1.7211, 1.423, 0.6065, 1.4953, 0.3541, 1.0504, 1.1402, 0.6705, 0.472, 0.2701, 0.1668, 0.9132, 0.6458, 0.3052, 0.8902, 1.7263, 0.7939, 0.2797, 3.0608, 3.058, 3.0508, 3.0508, 3.0508, 3.0485, 3.0485, 3.0446, 3.0409, 3.0409, 3.0409, 3.0077, 2.9962, 2.9601, 2.9546, 2.9374, 2.9234, 2.8595, 2.8412, 2.7318, 2.7175, 2.6789, 2.6789, 2.6629, 2.6367, 2.5956, 2.5385, 2.5306, 2.5213, 2.4985, 2.4686, 2.1296, 1.6958, 1.7434, 0.9839, 0.497, 0.9887, 1.003, 1.003, 1.5531, 2.0698, 1.0301, 0.4978, 1.2161, 1.5394, 3.1868, 3.1856, 3.1781, 3.1741, 3.1741, 3.1741, 3.1722, 3.1711, 3.1711, 3.1711, 3.1711, 3.1711, 3.17, 3.1687, 3.1687, 3.1687, 3.1687, 3.1674, 3.1674, 3.1674, 3.1674, 3.1262, 3.0884, 3.0802, 3.0464, 3.0113, 2.9996, 2.9814, 2.9738, 2.8906, 2.8379, 2.5137, 2.6684, 2.6942, 1.3019, 1.7799, 2.3331, 2.4018, 0.2353, 1.7323, 1.8367, 1.9921, 2.881, 2.8734, 2.8555, 2.8187, 2.8066, 2.7515, 2.7373, 2.7249, 2.6687, 2.666, 2.6322, 2.621, 2.6052, 2.5406, 2.538, 2.5248, 2.418, 2.4101, 2.3899, 2.3808, 2.3221, 2.3173, 2.3009, 2.2677, 2.2674, 2.245, 2.2384, 2.231, 2.2249, 2.2247, 2.1804, 2.1514, 1.9362, 2.1114, 1.8862, 1.7496, 1.2057, 0.8053, 0.9852, 0.9911, 1.2519, 1.9659, 0.0795, 0.25, 3.3391, 3.3391, 3.338, 3.1574, 2.8279, 2.5537, 2.4965, 2.4196, 2.4042, 2.3857, 2.361, 2.3569, 2.3469, 2.3058, 2.2775, 2.2715, 2.2309, 2.2068, 2.1637, 2.1585, 2.1301, 2.1102, 2.0909, 2.0869, 2.0846, 2.0655, 2.0406, 2.0406, 2.0004, 1.9642, 1.9474, 1.2202, 1.2148, 1.5523, 1.1468, 1.702, 0.85, 1.2953, -0.1259, 0.6689], "logprob": [30.0, 29.0, 28.0, 27.0, 26.0, 25.0, 24.0, 23.0, 22.0, 21.0, 20.0, 19.0, 18.0, 17.0, 16.0, 15.0, 14.0, 13.0, 12.0, 11.0, 10.0, 9.0, 8.0, 7.0, 6.0, 5.0, 4.0, 3.0, 2.0, 1.0, -4.741, -4.8221, -4.971, -5.4124, -5.6813, -5.6996, -4.9111, -5.7764, -5.8171, -5.8171, -5.8381, -5.8382, -4.8658, -5.904, -5.904, -5.999, -5.9991, -6.0243, -6.0502, -6.0502, -6.0768, -6.0768, -6.1041, -6.1041, -6.1611, -6.1611, -6.1909, -6.2216, -6.2859, -6.3197, -4.4939, -4.7105, -4.7386, -4.7386, -4.7343, -4.7301, -4.5134, -4.6315, -4.5825, -4.7396, -4.2237, -5.1711, -4.3572, -5.0191, -4.469, -4.6197, -4.6479, -4.0346, -4.737, -5.058, -4.6994, -4.9724, -3.8065, -3.7082, -3.9235, -4.1111, -4.3644, -4.3635, -3.9902, -4.2164, -4.314, -4.1909, -4.4597, -4.3839, -4.1723, -4.457, -4.6475, -4.6973, -4.6942, -4.7262, -4.0766, -4.0967, -4.0967, -4.6866, -4.7238, -4.7494, -4.7494, -4.7625, -4.7625, -4.7625, -4.7625, -4.7625, -4.7625, -4.7625, -4.7625, -4.7757, -4.7757, -4.7757, -4.7757, -4.7757, -4.7757, -4.7891, -4.7891, -4.7891, -4.7891, -4.7891, -4.7891, -4.7891, -4.7891, -4.7891, -4.6149, -4.7891, -3.5271, -4.0899, -4.6311, -4.7891, -3.4816, -4.4144, -4.0353, -4.0569, -4.6262, -4.6592, -4.4148, -4.6676, -4.611, -4.583, -4.7366, -4.7421, -4.7577, -4.7617, -5.186, -5.186, -5.186, -5.186, -5.2084, -5.2548, -5.3035, -5.3035, -5.3035, -5.3035, -5.3287, -5.3287, -5.3287, -5.3287, -5.3287, -5.3287, -5.3287, -5.3287, -5.3287, -5.3546, -5.3546, -5.3547, -5.3547, -5.3812, -5.3812, -5.3812, -5.3812, -5.3812, -5.3812, -5.3812, -5.3812, -5.235, -4.6461, -5.3287, -5.2815, -5.1597, -3.502, -4.4072, -3.84, -4.705, -4.8101, -4.6696, -4.3918, -4.8989, -4.6888, -4.6475, -5.219, -4.5065, -4.7082, -4.6982, -4.7539, -5.2334, -4.9945, -4.884, -5.2522, -5.2635, -5.1123, -5.2369, -5.2188, -4.2332, -4.2905, -4.4153, -4.4153, -4.4665, -4.4841, -4.4841, -4.5021, -4.5021, -4.5021, -4.5021, -4.5021, -4.5021, -4.5021, -4.5021, -4.5204, -4.5204, -4.5204, -4.5204, -4.5204, -4.5204, -4.5204, -4.5204, -4.5204, -4.5204, -4.5204, -4.5204, -4.5204, -4.5204, -4.5204, -4.5204, -3.6528, -4.4292, -4.4423, -4.4306, -3.6417, -3.6486, -3.7437, -4.4302, -4.4242, -4.4219, -4.4715, -4.4592, -4.4537, -4.3562, -4.3562, -4.2393, -4.2869, -4.4607, -4.4569, -4.4279, -4.4381, -4.4593, -4.4452, -4.4449, -4.4454, -4.4461, -4.4573, -4.3942, -4.9913, -5.0251, -5.1729, -4.7582, -4.8698, -4.873, -4.8734, -4.8275, -4.7579, -4.8482, -5.3339, -4.1884, -5.2203, -5.1387, -4.8089, -4.6431, -4.6385, -4.7243, -4.028, -4.8414, -4.8977, -3.8671, -5.4258, -5.1338, -4.933, -5.49, -4.2976, -5.0754, -5.2136, -3.7863, -4.0306, -4.5897, -4.4397, -3.4029, -4.2035, -3.2781, -3.498, -3.9151, -4.4209, -4.131, -4.1375, -4.2719, -3.9832, -4.5064, -4.076, -4.0098, -4.1968, -4.207, -4.39, -4.3065, -4.392, -4.6307, -5.0425, -5.0061, -4.7362, -4.9855, -5.0562, -5.0265, -5.1529, -5.1223, -4.8145, -4.8145, -5.0083, -5.1042, -5.1042, -5.1667, -5.1433, -5.5257, -5.1513, -4.7555, -4.7638, -4.749, -4.7921, -4.7921, -4.6628, -4.71, -4.7281, -4.5421, -4.6728, -4.7719, -5.6583, -5.6583, -4.8584, -4.681, -4.5739, -4.6226, -4.4493, -3.5811, -3.5811, -3.5927, -3.2503, -4.5692, -4.3128, -3.8136, -4.4822, -3.8554, -4.2485, -4.3291, -4.1791, -4.144, -4.0922, -4.1883, -4.4314, -4.3722, -4.348, -4.5281, -4.696, -4.6624, -4.7146, -3.7809, -3.9492, -4.2849, -4.2849, -4.2849, -4.3742, -4.3742, -4.5073, -4.6202, -4.6202, -4.6202, -4.4771, -4.6267, -4.6608, -4.6661, -4.5129, -4.6639, -3.7167, -4.4957, -4.6889, -4.5641, -3.4874, -3.4874, -4.3367, -4.4552, -4.5217, -4.5936, -3.8257, -3.2455, -3.9908, -4.0327, -3.8927, -3.4058, -3.5067, -3.6377, -3.766, -4.1234, -4.133, -4.133, -4.3198, -4.4273, -4.2696, -4.3517, -4.4015, -4.4339, -3.6932, -3.7671, -4.134, -4.2831, -4.2831, -4.2831, -4.3496, -4.3845, -4.3845, -4.3845, -4.3845, -4.3845, -4.4208, -4.4584, -4.4584, -4.4584, -4.4584, -4.4974, -4.4974, -4.4974, -4.4974, -4.5387, -4.5389, -4.5093, -4.5811, -4.1979, -4.2287, -3.8643, -4.4835, -4.4777, -3.5105, -3.8988, -4.195, -4.2397, -3.7202, -4.1529, -4.3019, -4.3191, -4.0278, -4.3561, -4.4209, -4.4584, -4.4295, -4.0069, -4.0604, -4.3198, -4.5106, -4.4632, -4.5895, -3.9732, -4.1433, -4.6447, -4.2191, -4.8058, -4.7401, -4.5987, -4.4399, -4.6584, -5.2283, -3.8767, -4.2243, -5.0173, -4.5413, -5.3465, -5.0648, -4.3744, -5.2283, -4.3856, -4.383, -4.4273, -5.1214, -3.708, -3.8376, -4.5647, -3.6812, -4.4367, -4.0648, -4.0059, -3.5843, -3.2304, -3.668, -3.837, -4.0478, -4.3825, -4.13, -4.3715, -4.1044, -4.1044, -4.204, -4.4202, -4.0968, -4.837, -3.8128, -4.1769, -4.2379, -3.5877, -4.0321, -4.1912, -5.2299, -4.4697, -4.5304, -3.346, -4.4673, -5.0723, -4.592, -4.5972, -3.5815, -4.7295, -4.1959, -4.8056, -4.7031, -4.7012, -4.3437, -4.3437, -4.3631, -4.4445, -4.426, -3.0428, -3.4067, -3.9615, -3.5064, -4.4604, -3.9996, -4.4405, -4.3354, -4.4492]}, "token.table": {"Topic": [4, 6, 9, 1, 7, 10, 1, 5, 6, 7, 1, 8, 1, 5, 6, 8, 10, 2, 1, 2, 3, 5, 6, 2, 10, 4, 9, 1, 1, 2, 6, 7, 9, 10, 2, 2, 5, 7, 9, 1, 6, 3, 5, 10, 1, 4, 5, 6, 10, 1, 4, 5, 6, 10, 1, 5, 6, 9, 10, 1, 5, 6, 1, 1, 4, 5, 10, 4, 2, 2, 7, 8, 1, 6, 1, 6, 4, 3, 3, 8, 9, 5, 6, 5, 6, 8, 9, 3, 3, 6, 9, 10, 5, 4, 7, 10, 7, 4, 10, 2, 2, 1, 2, 3, 4, 5, 6, 8, 9, 10, 1, 3, 5, 10, 1, 6, 2, 1, 6, 1, 4, 6, 8, 1, 2, 3, 4, 5, 6, 7, 8, 9, 10, 2, 4, 1, 2, 7, 8, 10, 1, 3, 6, 7, 9, 7, 2, 3, 5, 6, 9, 10, 1, 5, 6, 9, 10, 1, 3, 3, 3, 4, 9, 4, 7, 8, 1, 3, 6, 1, 3, 5, 8, 1, 2, 3, 4, 5, 6, 7, 9, 10, 4, 6, 7, 9, 1, 5, 1, 5, 1, 4, 5, 8, 9, 1, 5, 8, 3, 1, 3, 5, 10, 1, 3, 5, 10, 1, 6, 1, 6, 1, 1, 4, 5, 6, 8, 10, 1, 3, 6, 10, 4, 1, 3, 5, 8, 10, 6, 8, 9, 10, 1, 5, 2, 3, 4, 7, 3, 2, 2, 1, 5, 6, 7, 2, 2, 1, 5, 6, 7, 3, 8, 2, 10, 2, 10, 1, 3, 4, 5, 6, 10, 1, 4, 1, 3, 4, 5, 6, 1, 1, 10, 5, 6, 1, 4, 5, 8, 9, 4, 9, 1, 2, 3, 5, 10, 3, 2, 3, 6, 2, 3, 3, 1, 6, 1, 6, 6, 9, 10, 3, 3, 7, 8, 7, 8, 1, 1, 9, 3, 3, 1, 3, 5, 6, 9, 8, 4, 4, 8, 8, 1, 5, 6, 8, 10, 4, 1, 1, 2, 6, 7, 10, 2, 2, 1, 2, 7, 7, 4, 3, 1, 6, 1, 6, 1, 4, 8, 9, 10, 1, 3, 4, 6, 9, 10, 1, 3, 4, 6, 9, 10, 1, 9, 1, 5, 1, 5, 7, 10, 3, 2, 3, 4, 6, 7, 8, 9, 10, 7, 4, 10, 2, 3, 6, 10, 3, 4, 7, 10, 2, 2, 1, 2, 3, 5, 6, 10, 1, 1, 6, 3, 5, 6, 10, 3, 3, 4, 4, 1, 2, 6, 7, 2, 10, 8, 2, 2, 6, 7, 6, 9, 6, 9, 2, 2, 1, 2, 3, 4, 5, 6, 10, 4, 1, 6, 1, 5, 4, 1, 2, 3, 8, 10, 1, 2, 3, 6, 7, 10, 2, 1, 2, 6, 3, 10, 4, 6, 9, 4, 5, 8, 8, 3, 7, 3, 7, 7, 4, 10, 4, 5, 6, 8, 8, 9, 10, 1, 3, 6, 10, 1, 3, 6, 1, 1, 1, 6, 7, 8, 7, 6, 7, 8, 1, 9, 3, 4, 9, 4, 9, 1, 7, 9, 1, 6, 9, 6, 1, 1, 6, 1, 2, 2, 1, 3, 4, 6, 10, 3, 4, 8, 1, 3, 3, 5, 6, 9, 5, 6, 8, 9, 5, 8, 9, 10, 8, 10, 3, 2, 3, 7, 8, 10, 1, 3, 6, 10, 3, 1, 5, 6, 7, 8, 8, 8, 8, 1, 3, 4, 5, 6, 10, 1, 3, 4, 5, 6, 10, 3, 7, 1, 2, 3, 5, 7, 9, 10, 1, 5, 8, 10, 2, 1, 6, 1, 6, 8, 9, 10, 1, 3, 4, 5, 9, 10, 1, 1, 4, 3, 1, 5, 3, 6, 3, 1, 5, 2, 3, 5, 6, 7, 9, 10, 1, 2, 5, 6, 7, 8, 10, 6, 8, 9, 8, 1, 2, 3, 4, 5, 6, 8, 9, 10, 1, 3, 2, 4, 1, 4, 6, 9, 10, 4, 1, 5, 5, 8, 6, 7, 6, 7, 9, 10, 7, 5, 9, 10, 1, 5, 1, 6, 9, 1, 6, 10, 1, 6, 1, 6, 2, 5, 10, 2, 5, 1, 9, 5, 9, 3, 1, 6, 1, 6, 9, 1, 2, 3, 4, 5, 6, 7, 8, 9, 10, 2, 6, 4, 2, 5, 2, 7, 2, 2, 5, 1, 3, 6, 1, 3, 6, 5, 8, 9, 4, 6, 9, 10, 4, 5, 9, 4, 9, 4, 2, 3, 8, 10, 2, 3, 8, 10, 1, 6, 8, 9, 1, 6, 1, 3, 4, 5, 6, 8, 9, 3, 4, 1, 3, 8, 1, 5, 1, 5, 6, 1, 6, 1, 5, 6, 7, 9, 1, 5, 9, 1, 1, 6, 3, 7, 7, 3, 7, 1, 7, 8, 9, 7, 1, 3, 8, 2, 10, 8, 1, 6, 1, 3, 4, 6, 9, 1, 6, 3, 4, 4, 5, 6, 9, 5, 6, 3, 1, 3, 4, 5, 6, 8, 9, 10, 1, 5, 1, 3, 1, 6, 1, 1, 3, 6, 1, 2, 5, 8, 10, 8, 8, 8, 1, 2, 3, 5, 6, 8, 9, 6, 10, 1, 3, 1, 3, 6, 7, 4, 6, 7, 1, 3, 4, 5, 6, 9, 4, 5, 10, 1, 6, 9, 10, 1, 5, 6, 9, 5, 6, 9, 1, 1, 6, 7, 9, 1, 9, 3, 4, 9, 4, 5, 10, 5, 8, 9, 10, 5, 9, 2, 3, 9, 10, 2, 10, 5, 8, 9, 1, 3, 5, 1, 5, 8, 2, 4, 1, 5, 8, 1, 5, 8, 5, 8, 9, 10, 4, 9, 1, 9, 2, 1, 7, 1, 3, 5, 6, 9, 10, 1, 1, 6, 1, 3, 5, 1, 1, 1, 3, 4, 5, 6, 8, 10, 6, 8, 9, 10, 2, 3, 10, 3, 10, 1, 2, 3, 4, 5, 6, 8, 10, 1, 2, 5, 1, 3, 6, 1, 4, 10, 4, 4, 6, 8, 4, 8, 9, 5, 8, 3, 7, 9, 10, 10, 2, 1, 5, 6, 9, 10, 1, 5, 9, 10, 1, 3, 4, 6, 9, 10, 1, 6, 1, 3, 5, 6, 8, 1, 9], "Freq": [0.48191712790930746, 0.02409585639546537, 0.45782127151384205, 0.030554622535146486, 0.7027563183083692, 0.2444369802811719, 0.40391370073798727, 0.12451474985156, 0.3462117434897034, 0.12451474985156, 0.980844458916882, 0.9765456881807919, 0.3205396483599155, 0.04808094725398733, 0.08013491208997887, 0.2083507714339451, 0.3525936131959071, 0.9946988397386972, 0.5141948679491887, 0.2642390293627775, 0.007141595388183175, 0.1142655262109308, 0.09641153774047287, 0.9829367099377567, 0.9658255881665174, 0.6073577511497371, 0.3759833697593611, 0.9779811387476506, 0.18866069500989102, 0.3622285344189907, 0.015092855600791282, 0.38486781782017765, 0.007546427800395641, 0.04527856680237384, 0.994871705690226, 0.9946047048638955, 0.9808467291162154, 0.7867802994358706, 0.19669507485896764, 0.033817673729356464, 0.946894864421981, 0.9864364734147052, 0.533735678182898, 0.4447797318190817, 0.5426119058115448, 0.15657457978641592, 0.1889693204318813, 0.09988378365685154, 0.010798246881821788, 0.5440699195396588, 0.1569953001656727, 0.18947708640684635, 0.10015217424361879, 0.01082726208039122, 0.11588660888668798, 0.31454936697815306, 0.03311045968191085, 0.18210752825050966, 0.3311045968191085, 0.3039722495048023, 0.258939323652239, 0.42781279559935137, 0.9709334366809542, 0.012470245353925059, 0.7357444758815784, 0.18705368030887587, 0.06235122676962529, 0.991043442672345, 0.9819550398172863, 0.9819550398172863, 0.6377805408815344, 0.3298864866628626, 0.8507068232261283, 0.14178447053768806, 0.8616027942184711, 0.1311134686854195, 0.991043442672345, 0.990401146613831, 0.9899102785930458, 0.8641410951913637, 0.1127140558945257, 0.3023393786197104, 0.6871349514084327, 0.2735289936733165, 0.7153835219148278, 0.7248943970793204, 0.2319662070653825, 0.9877073626880248, 0.9888600451622126, 0.07149170712568526, 0.10723756068852787, 0.8221546319453804, 0.9756128349794541, 0.4024415038067205, 0.21559366275360026, 0.37369568210624043, 0.982249158536687, 0.6232743009034285, 0.36084301631251126, 0.9822906530719208, 0.9946988397386972, 0.4766380811461826, 0.09114009820366283, 0.04310680320443512, 0.08375036051147396, 0.09729821294715356, 0.10715119653673873, 0.028327327820057365, 0.04064355730703883, 0.030790573717453657, 0.7978950993714296, 0.05585265695600007, 0.10372636291828584, 0.03989475496857148, 0.5157922622237244, 0.47611593436036104, 0.9816105942793715, 0.3120784867274034, 0.6808985164961529, 0.23057843466089786, 0.7173551300561267, 0.025619826073433098, 0.012809913036716549, 0.023388529920018025, 0.35342667434693903, 0.22219103424017125, 0.07016558976005408, 0.025987255466686697, 0.03898088320003004, 0.07536304085339142, 0.051974510933373394, 0.023388529920018025, 0.11694264960009013, 0.9838474157048552, 0.991043442672345, 0.09380615776446624, 0.5484052300076488, 0.17318059894978383, 0.11545373263318923, 0.06494272460616894, 0.20671491816066134, 0.7704828767806469, 0.013130467783130664, 0.8009585347709706, 0.17069608118069865, 0.982249158536687, 0.25427399732129374, 0.3120635421670423, 0.12135804417607202, 0.005778954484574858, 0.21382131592926973, 0.08668431726862287, 0.1473420280144831, 0.2946840560289662, 0.31168505926140655, 0.11334002154960238, 0.12467402370456261, 0.24933756553787004, 0.74801269661361, 0.98708781889571, 0.3655518102779001, 0.6128368584070678, 0.02150304766340589, 0.9913713856383221, 0.9796938849739609, 0.9791498185504206, 0.8375382775321105, 0.14523785159516367, 0.014523785159516366, 0.9948641517714185, 0.98708781889571, 0.18911065964709586, 0.8080182730375913, 0.47897084091957226, 0.0018493082660987347, 0.06287648104735698, 0.10171195463543041, 0.12020503729641775, 0.12205434556251649, 0.04993132318466584, 0.03698616532197469, 0.02773962399148102, 0.6538938563735734, 0.01147182204164164, 0.2982673730826826, 0.034415466124924916, 0.5841858302661107, 0.408002802090617, 0.8765197530504527, 0.11686930040672702, 0.24188165476948595, 0.17737988016428968, 0.3466970385029299, 0.2338189329438364, 0.008062721825649532, 0.267657613630934, 0.5531590681705969, 0.16059456817856038, 0.9864364886361908, 0.7707565048846249, 0.09342503089510604, 0.09676163914135984, 0.03670269070879166, 0.772461294892758, 0.11089790867272269, 0.08030538214231643, 0.03059252653040626, 0.8601132006921487, 0.13325697475512163, 0.8571983753937634, 0.13567168531412083, 0.9817209929160545, 0.27515562911634633, 0.07861589403324182, 0.4380028381852044, 0.16284720906885805, 0.028077105011872078, 0.011230842004748831, 0.27910169368362986, 0.018606779578908657, 0.11164067747345194, 0.5768101669461684, 0.991043442672345, 0.374794774297716, 0.5077864684033572, 0.012090154009603742, 0.012090154009603742, 0.0846310780672262, 0.0547460433608044, 0.3284762601648264, 0.547460433608044, 0.0821190650412066, 0.028194551743050557, 0.9304202075206683, 0.4688138847785778, 0.22839650796905073, 0.048083475361905416, 0.25243824565000345, 0.9857508836399281, 0.9946988397386972, 0.9946988397386972, 0.4012754509082017, 0.11198384676507954, 0.3577261771662263, 0.12442649640564393, 0.9816105875974678, 0.9946988397386972, 0.4012754501243505, 0.11198384654633037, 0.35772617646744426, 0.1244264961625893, 0.14837544977808398, 0.8160649737794619, 0.691444792461941, 0.29857843310856547, 0.7138722494648687, 0.2758142782023356, 0.5036804733073613, 0.025829767861915966, 0.16789349110245377, 0.1894182976540504, 0.09901411013734454, 0.014349871034397759, 0.9680764647552819, 0.99137138526733, 0.36489342589146606, 0.0884590123373251, 0.16033195986140175, 0.24049793979210263, 0.1437458950481533, 0.9722548541982847, 0.9830976112617392, 0.016116354282979334, 0.2735289936583651, 0.7153835218757241, 0.2718343664877377, 0.1761889412420522, 0.18625688074159805, 0.10571336474523133, 0.2567324572384189, 0.3319935386464264, 0.6455429918124957, 0.1332752091098588, 0.08885013940657253, 0.45535696445868423, 0.0666376045549294, 0.24433788336807447, 0.9877073329949189, 0.551313620804608, 0.43175163075059664, 0.01328466556155682, 0.5595042537912436, 0.42871105160627754, 0.9857508837964377, 0.39525350230964795, 0.5842877860229578, 0.39525350230531164, 0.5842877860165476, 0.5183035769838332, 0.4091870344609209, 0.06819783907682016, 0.9864364886361908, 0.10827151603553446, 0.8661721282842757, 0.9867515140166622, 0.9714384942806984, 0.9824457878189607, 0.9648931857037472, 0.6257514831625351, 0.36227717446252033, 0.986436492571533, 0.9857508836399281, 0.1547288216347742, 0.7220678342956129, 0.10315254775651614, 0.7272577280029802, 0.26181278208107284, 0.9778942496706396, 0.9919933383500978, 0.991371382968295, 0.9791498243806805, 0.9765456888895176, 0.18290856585184795, 0.5739544652592471, 0.19552294970369954, 0.031535959629628955, 0.006307191925925792, 0.991371383308235, 0.9924339845806057, 0.04888696832603673, 0.7944132352980969, 0.009166306561131887, 0.07944132352980969, 0.06721958144830051, 0.9946988397386972, 0.9816105952496772, 0.09553897194215244, 0.7301907141293079, 0.17060530703955792, 0.97969389095446, 0.9913713839759207, 0.9857508837964377, 0.4115533677528669, 0.5856721002636952, 0.3985963368343251, 0.5978945052514877, 0.17839331515161297, 0.234141226136492, 0.5017311988639115, 0.04459832878790324, 0.02229916439395162, 0.5056328036934329, 0.025710142560683026, 0.24853137808660258, 0.16711592664443967, 0.012855071280341513, 0.038565213841024536, 0.5013818557079888, 0.027348101220435753, 0.2643649784642123, 0.14585653984232402, 0.013674050610217876, 0.04558016870072626, 0.3581474679443143, 0.6060957149826857, 0.5145787245974978, 0.4805971107089838, 0.47904908532900126, 0.5138890188074741, 0.935044960944227, 0.03740179843776908, 0.9857508748366949, 0.19898320512481074, 0.1841059561435165, 0.23989563982336998, 0.044631746943882784, 0.12273730409567767, 0.044631746943882784, 0.048351059189206354, 0.11529867960503053, 0.9754645263586205, 0.5731289771418403, 0.42230556210451387, 0.3323428250367431, 0.407387979077298, 0.010720736291507842, 0.24657693470468037, 0.98708781889571, 0.9817443515389608, 0.9447661746204813, 0.03257814395243039, 0.9819550412040213, 0.9819550412040213, 0.440088776795773, 0.1697804418095368, 0.16084462908271907, 0.13180323772056146, 0.07372045499624624, 0.024573484998748747, 0.9695425529137415, 0.3034550071580468, 0.662083651981193, 0.7073196636958736, 0.018613675360417727, 0.18613675360417728, 0.08376153912187977, 0.98708781889571, 0.9877073580747497, 0.9916878171485559, 0.991043442672345, 0.01213309922113894, 0.5338563657301134, 0.07279859532683364, 0.3639929766341682, 0.603008232503167, 0.3886053053909299, 0.9750934134496179, 0.9822906542176607, 0.9819550398172863, 0.0944096084861594, 0.881156345870821, 0.3894070701602417, 0.5841106052403625, 0.5360221351881723, 0.42116024907642113, 0.9816105942793715, 0.9946988397386972, 0.4011525410702279, 0.1258846886203644, 0.04867541293320757, 0.21484320191208858, 0.12420622610542621, 0.05874618802283672, 0.026855400239011073, 0.9928498047985973, 0.9809719132056396, 0.008456654424186548, 0.2692280985860501, 0.7179415962294671, 0.991043442672345, 0.03184840455650612, 0.3291001804172299, 0.21232269704337414, 0.180474292486868, 0.254787236452049, 0.38048627598255247, 0.3181114766411504, 0.15177867839741163, 0.07069143925358898, 0.0540581594292151, 0.022870759758514082, 0.9819550398172863, 0.569918279572048, 0.3134550537646264, 0.11398365591440959, 0.7026882696379662, 0.27026471909152544, 0.532780622847837, 0.42425123671216647, 0.039465231322062, 0.991043442672345, 0.6175701634088149, 0.36760128774334216, 0.9765456356613736, 0.322482887210077, 0.6711130355452954, 0.32248288721007706, 0.6711130355452954, 0.9901195583703557, 0.9449098683864481, 0.04804626449422617, 0.9928498059999227, 0.9376480650627981, 0.02534183959629184, 0.9791498273281922, 0.5775083929262762, 0.38500559528418415, 0.01750025433109928, 0.8488020653060929, 0.004822739007420983, 0.12539121419294555, 0.014468217022262947, 0.7682094491300685, 0.04228675866771019, 0.18324262089341084, 0.9863111251885824, 0.981533257430227, 0.9648931857037472, 0.24066265496181136, 0.6618223011449812, 0.08022088498727045, 0.982249158536687, 0.026586311349777146, 0.6912440950942058, 0.2392768021479943, 0.39785096914474555, 0.5719107681455717, 0.013865348487456311, 0.623940681935534, 0.34663371218640776, 0.6645184734993126, 0.31715654417012645, 0.9817210002094979, 0.4488202345520872, 0.5319350928024736, 0.3666893983722554, 0.5720354614607184, 0.058670303739560864, 0.9792326376380388, 0.9631611163543295, 0.3884404863586734, 0.5911050879371117, 0.9695425321578939, 0.9819550412040213, 0.9819550412040213, 0.2525900178110919, 0.2672329173943436, 0.21598276885296264, 0.21598276885296264, 0.043928698749755114, 0.98708781889571, 0.991043442672345, 0.9824457947745953, 0.1147524153265172, 0.8797685175032985, 0.9904011466138312, 0.23235198673050658, 0.531090255384015, 0.23235198673050658, 0.30233937861971066, 0.6871349514084333, 0.9016182629440219, 0.07513485524533516, 0.05609942697881047, 0.19634799442583664, 0.36464627536226807, 0.3786711321069707, 0.8682216902674378, 0.07235180752228648, 0.987087826502884, 0.37353471026731955, 0.4117371238173863, 0.11036252803352622, 0.06367068925011128, 0.038202413550066774, 0.17856800103806877, 0.14285440083045503, 0.28570880166091006, 0.35713600207613755, 0.9857508748366949, 0.12921048060713144, 0.7106576433392229, 0.09690786045534858, 0.021535080101188573, 0.03230262015178286, 0.9791498272974518, 0.9791498272974518, 0.9750934134294955, 0.4868695555109116, 0.14093592396368493, 0.2690594912033985, 0.06406178361985679, 0.021353927873285595, 0.01708314229862848, 0.4868695554360093, 0.1409359239420027, 0.2690594911620051, 0.06406178361000123, 0.021353927870000407, 0.017083142296000324, 0.4508148010333102, 0.5482882715269989, 0.23448900184083357, 0.11358061026665375, 0.14655562615052098, 0.19785009530320333, 0.12823617288170586, 0.13190006353546888, 0.04396668784515629, 0.08016837949347536, 0.8818521744282288, 0.9824457946473472, 0.9689944398166884, 0.9946047048638955, 0.3443031762356905, 0.6120945355301165, 0.17697677902629463, 0.019664086558477182, 0.10815247607162451, 0.41294581772802086, 0.27529721181868055, 0.6378984133806577, 0.06401847876221654, 0.11889146055840215, 0.059445730279201074, 0.10060046662634027, 0.018290993932061867, 0.9680764851503807, 0.9874369297115122, 0.991043442672345, 0.98708781889571, 0.843871356978829, 0.14605465793864347, 0.4851270531921737, 0.5100053636122852, 0.9857508818971321, 0.42064778421356547, 0.5756232836606685, 0.22152117782154385, 0.19634831670545932, 0.02517286111608453, 0.010069144446433812, 0.1560717389197241, 0.05034572223216906, 0.3322817667323158, 0.04549369242338543, 0.43543962748097487, 0.09748648376439735, 0.058491890258638414, 0.22096936319930066, 0.01949729675287947, 0.1299819783525298, 0.02306058332120948, 0.4842722497453991, 0.46121166642418965, 0.975093415010317, 0.4643492213155686, 0.16505304075197935, 0.09463041003113483, 0.12103889655145153, 0.004401414420052783, 0.011003536050131957, 0.0022007072100263913, 0.12323960376147793, 0.011003536050131957, 0.7375663467864128, 0.25654481627353487, 0.9946988397386972, 0.9916878141321545, 0.9613241581154665, 0.679112477359716, 0.2532283813883687, 0.02302076194439715, 0.0460415238887943, 0.9913713839759207, 0.35715061088431194, 0.6428710995917615, 0.03900457863427582, 0.9361098872226197, 0.07464323885724417, 0.8957188662869299, 0.2634995980533123, 0.579699115717287, 0.052699919610662456, 0.10539983922132491, 0.9932067899093311, 0.5861075005288253, 0.33062474388805535, 0.08265618597201384, 0.018121960534665704, 0.978585868871948, 0.23357213034287447, 0.39844657529078586, 0.3434884269748154, 0.25402319582345745, 0.7112649483056809, 0.025402319582345744, 0.4018321529476119, 0.5804242209243282, 0.40509893582047823, 0.5764869471291421, 0.729306298251148, 0.0781399605269087, 0.19100879239911017, 0.9745992413335864, 0.011202290130271108, 0.6240220312420021, 0.3403756534047284, 0.7613470140901607, 0.2175277183114745, 0.98708781889571, 0.41848598263844833, 0.5633465150902189, 0.42859107059779583, 0.15585129839919848, 0.3896282459979962, 0.14481892973999388, 0.21022102704192658, 0.16116945406547706, 0.12613261622515595, 0.00233578918935474, 0.14715471892934862, 0.07474525405935167, 0.039708416219030575, 0.011678945946773699, 0.07941683243806115, 0.07545195258005288, 0.9054234309606346, 0.991043442672345, 0.4735042222572067, 0.5165500606442255, 0.8577557807045239, 0.139095532006139, 0.9816105947960106, 0.9946988397386972, 0.9819442199955385, 0.6250928185543702, 0.13456859288323247, 0.23440980695788882, 0.7210431566084621, 0.15522456843654392, 0.12017385943474368, 0.5877810996784635, 0.16030393627594458, 0.24936167865146935, 0.62008933000305, 0.010509988644119492, 0.18917979559415085, 0.17866980695003137, 0.9801424111213525, 0.8345979677147441, 0.13534021098076932, 0.9445786289648092, 0.04885751529128323, 0.991043442672345, 0.33601642355443107, 0.21678478938995555, 0.1842670709814622, 0.26014174726794664, 0.3360164235264667, 0.216784789371914, 0.1842670709661269, 0.2601417472462968, 0.29733279259138484, 0.511412403257182, 0.09514649362924314, 0.09514649362924314, 0.3883539806311684, 0.6078584044661766, 0.25154345649892335, 0.24843798172733167, 0.05486338763145241, 0.17080111243754054, 0.16562532115155446, 0.02484379817273317, 0.08281266057577723, 0.9904011466138312, 0.991043442672345, 0.5326791792918035, 0.16211975021924455, 0.30107953612145416, 0.31306974923617836, 0.6783177900117198, 0.025822016600844412, 0.4002412573130884, 0.5680843652185771, 0.422288680829127, 0.5374583210552526, 0.06913131525128016, 0.02304377175042672, 0.04608754350085344, 0.20739394575384046, 0.6221818372615214, 0.34427594420044766, 0.6286778111486435, 0.014968519313062941, 0.9735117864306977, 0.09840348924153947, 0.8528302400933421, 0.42086564481024924, 0.5728449054361726, 0.9714384946637242, 0.4333939085552664, 0.5658198250582644, 0.491895626450143, 0.18270408982433883, 0.07027080377859186, 0.2459478132250715, 0.9714384975085173, 0.835195305606604, 0.1556264544608579, 0.9750934134496179, 0.6914361235960703, 0.2985746897346667, 0.9765456881807919, 0.8616027942184717, 0.13111346868541962, 0.7466532782151795, 0.004125156233233036, 0.016500624932932143, 0.1856320304954866, 0.049501874798796426, 0.8624903783647603, 0.1365092685181635, 0.985750882228081, 0.9913713849927552, 0.991043442672345, 0.8860687765184043, 0.05063250151533739, 0.025316250757668694, 0.9290651895032463, 0.028153490591007465, 0.98708781889571, 0.415966364030129, 0.12535972614606627, 0.10114250632239438, 0.20655863967249558, 0.0897461675818429, 0.0327644738790855, 0.015669965768258284, 0.012820881083120414, 0.36587253497105465, 0.6203925592987448, 0.04404064795176655, 0.9248536069870975, 0.34036663305430537, 0.6283691687156406, 0.9833709965578127, 0.022997280180336532, 0.9198912072134613, 0.022997280180336532, 0.18143665239145668, 0.21963384236860548, 0.1623380574028823, 0.2578310323457542, 0.18143665239145668, 0.9759350792697618, 0.9803217133001808, 0.9786279963055246, 0.5079372381149225, 0.06383910642974436, 0.0027756133230323636, 0.14988311944374763, 0.0832683996909709, 0.14988311944374763, 0.04440981316851782, 0.8286789973669711, 0.15345907358647612, 0.213658631754466, 0.7656100971201698, 0.5264470193153837, 0.10807852714421785, 0.09761931483993871, 0.2649667117084051, 0.9913713839759207, 0.07465473552099117, 0.895856826251894, 0.15999042465600166, 0.004999700770500052, 0.26998384160700284, 0.3249805500825034, 0.13999162157400147, 0.09999401541000105, 0.8625018948004567, 0.029237352366117176, 0.10233073328141012, 0.029669795196275918, 0.07417448799068979, 0.5637261087292424, 0.3263677471590351, 0.136840923992871, 0.0547363695971484, 0.136840923992871, 0.6568364351657808, 0.8209261528918201, 0.024144886849759416, 0.12072443424879709, 0.9869805431789604, 0.9779811334014248, 0.1373828222941918, 0.5953255632748312, 0.25186850753935164, 0.4668265179864937, 0.5186961310961041, 0.9877073773536151, 0.3203735691722756, 0.6585456699652332, 0.42433319353725746, 0.23868742136470733, 0.3182498951529431, 0.33121525655923606, 0.24151112457444293, 0.3450158922492042, 0.07590349629482493, 0.5675537468770009, 0.3883262478632111, 0.7315610519378616, 0.16817495446847391, 0.05886123406396587, 0.04204373861711848, 0.9524659355731431, 0.03322555589208639, 0.5074133995755623, 0.35706868859021057, 0.11275853323901386, 0.7478871517427105, 0.14861860066682067, 0.10067711658074949, 0.9735117403161754, 0.5749093454995418, 0.4058183615290883, 0.9946988397386972, 0.991043442672345, 0.23674965260368858, 0.33423480367579567, 0.41779350459474457, 0.2579959708966934, 0.2883484380610103, 0.4552870074647531, 0.30741672867694875, 0.06148334573538975, 0.5226084387508129, 0.09222501860308463, 0.641464392051209, 0.3421143424273114, 0.4817016707276932, 0.5100370631234399, 0.9946988397386972, 0.36095417688757303, 0.6091101734977794, 0.4472200536228588, 0.11516396230631558, 0.12668035853694715, 0.1017281667039121, 0.09980876733214017, 0.10748636481922788, 0.970933443910254, 0.24743334534487657, 0.7423000360346297, 0.7485331774271825, 0.15367237417379243, 0.09418629384845342, 0.9572948506183975, 0.9550788406221512, 0.1497758012802656, 0.34039954836423997, 0.07261857031770454, 0.16793044385969172, 0.0136159819345696, 0.09077321289713067, 0.1633917832148352, 0.01045681827233766, 0.6901500059742857, 0.26142045680844156, 0.02091363654467532, 0.13672079275194526, 0.5639732701017742, 0.2905316845978837, 0.962721925286994, 0.024685177571461384, 0.4743567681340638, 0.11250769500615616, 0.05625384750307808, 0.08666133263987705, 0.1231503148040358, 0.13835405737243528, 0.001520374256839948, 0.006081497027359792, 0.059506619262676794, 0.5504362281797603, 0.37935469779956454, 0.8467939955091677, 0.010997324617002178, 0.13746655771252722, 0.9808444493486008, 0.7080025306107506, 0.28762602806061743, 0.991043442672345, 0.991043442672345, 0.17645843471171732, 0.8066671301107077, 0.1502372727369431, 0.6009490909477724, 0.22535590910541464, 0.19016938468258746, 0.7923724361774477, 0.990401146613831, 0.31919754880519285, 0.3064296468529851, 0.357501254661816, 0.9689944447123068, 0.981610599070166, 0.18762106059316125, 0.25978300697514634, 0.33916114799533, 0.11545911421117616, 0.09381053029658062, 0.6672391399677817, 0.03177329237941818, 0.01588664618970909, 0.2700729852250545, 0.417602274657513, 0.09360050983702876, 0.41040223543928, 0.007200039218232982, 0.021600117654698946, 0.04320023530939789, 0.09508881286163448, 0.8874955867085885, 0.44835062672876763, 0.12262581243863731, 0.23375545496115235, 0.18777077529666336, 0.003832056638707416, 0.5102076203321797, 0.47096088030662736], "Term": ["000", "000", "000", "10", "10", "10", "19", "19", "19", "19", "19_", "2008", "2020", "2020", "2020", "2020", "2020", "2_presumptive", "30s", "30s", "30s", "30s", "30s", "30s_recently", "39", "3_000", "3_000", "_covid", "according", "according", "according", "according", "according", "according", "adult", "adult_resident", "affected", "agency", "agency", "ago", "ago", "also_reported", "americans", "americans", "andrew", "andrew", "andrew", "andrew", "andrew", "andrew_cuomo", "andrew_cuomo", "andrew_cuomo", "andrew_cuomo", "andrew_cuomo", "announced", "announced", "announced", "announced", "announced", "anxiety", "anxiety", "anxiety", "anxiety_general", "apartment", "apartment", "apartment", "apartment", "apartment_somewhat", "appropriately", "appropriately_cared", "area", "area", "arriving", "arriving", "arriving_new", "arriving_new", "back_iran", "beginning", "beginning_matter", "begun", "begun", "bill_de", "bill_de", "blasio", "blasio", "border", "border", "bringing", "buying", "california", "california", "california", "calm", "care", "care", "care", "care_center", "care_worker", "care_worker", "cared", "cared_new", "case", "case", "case", "case", "case", "case", "case", "case", "case", "case_coronavirus", "case_coronavirus", "case_coronavirus", "case_coronavirus", "case_covid", "case_covid", "case_involves", "case_reported", "case_reported", "case_woman", "case_woman", "case_woman", "case_woman", "cases", "cases", "cases", "cases", "cases", "cases", "cases", "cases", "cases", "cases", "cases_florida", "cases_isolation", "cases_reported", "cases_reported", "cases_reported", "cases_reported", "cases_reported", "cause_surprise", "cause_surprise", "center", "center", "center", "center_kirkland", "china", "china", "china", "china", "china", "china", "city", "city", "city", "city", "city", "cnn", "cnn", "cnn_cause", "coming", "coming", "coming", "coming_back", "common", "companies", "condition", "condition", "condition", "condition_controlled", "condition_statement", "conference", "conference", "confirmed", "confirmed", "confirmed", "confirmed", "confirmed", "confirmed", "confirmed", "confirmed", "confirmed", "confirmed_cases", "confirmed_cases", "confirmed_cases", "confirmed_cases", "confirmed_first", "confirmed_first", "confirmed_new", "confirmed_new", "confirms", "confirms", "confirms", "confirms", "confirms", "confirms_first", "confirms_first", "confirms_first", "constantine", "contracted", "contracted", "contracted", "contracted", "contracted_virus", "contracted_virus", "contracted_virus", "contracted_virus", "controlled", "controlled", "controlled_situation", "controlled_situation", "coronavirus_", "coronavirus_case", "coronavirus_case", "coronavirus_case", "coronavirus_case", "coronavirus_case", "coronavirus_case", "coronavirus_cases", "coronavirus_cases", "coronavirus_cases", "coronavirus_cases", "coronavirus_female", "coronavirus_new", "coronavirus_new", "coronavirus_new", "coronavirus_new", "coronavirus_new", "coronavirus_outbreak", "coronavirus_outbreak", "coronavirus_outbreak", "coronavirus_outbreak", "coronavirus_test", "coronavirus_test", "county", "county", "county", "county", "county_executive", "county_individuals", "county_one", "covid", "covid", "covid", "covid", "covid19", "covid19_cases", "covid_19", "covid_19", "covid_19", "covid_19", "crisis", "crisis", "cruise", "cruise", "cruise_ship", "cruise_ship", "cuomo", "cuomo", "cuomo", "cuomo", "cuomo", "cuomo", "cuomo_confirmed", "cuomo_revealed", "cuomo_said", "cuomo_said", "cuomo_said", "cuomo_said", "cuomo_said", "cuomo_statement", "currently_isolated", "currently_isolated", "de_blasio", "de_blasio", "death", "death", "death", "death", "death", "death_toll", "death_toll", "deaths", "deaths", "deaths", "deaths", "deaths", "declared", "department", "department", "department", "department_health", "department_health", "died_coronavirus", "diligently", "diligently", "diligently_managing", "diligently_managing", "disease", "disease", "disease", "dow_constantine", "dozens", "dozens", "economy", "effort", "essential", "evening_learned", "exactly", "exactly", "executive", "executive_dow", "expected", "expected", "expected", "facility", "facility", "fall", "female", "female_health", "financial", "financial_crisis", "first_coronavirus", "first_coronavirus", "first_coronavirus", "first_coronavirus", "first_coronavirus", "first_patient", "first_positive", "florida", "florida", "florida", "florida", "florida", "florida_2", "florida_department", "florida_new", "florida_new", "florida_new", "flu", "fortunate", "four_people", "general", "general", "general_risk", "general_risk", "global", "global", "global", "global", "global", "gov", "gov", "gov", "gov", "gov", "gov", "gov_andrew", "gov_andrew", "gov_andrew", "gov_andrew", "gov_andrew", "gov_andrew", "government", "government", "governor", "governor", "governor_andrew", "governor_andrew", "ground", "ground", "hampshire", "health", "health", "health", "health", "health", "health", "health", "health", "health_agency", "health_care", "health_care", "health_officials", "health_officials", "health_officials", "health_officials", "health_spokesperson", "health_worker", "help", "help", "hillsborough", "hillsborough_county", "home", "home", "home", "home", "home", "home", "home_patient", "home_respiratory", "home_respiratory", "hospital", "hospital", "hospital", "hospital", "hospital_manhattan", "hospital_patients", "hundreds", "hundreds_confirmed", "illness", "illness", "illness", "illness", "including", "including", "index", "individuals", "individuals_isolated", "infection", "infection", "infectious", "infectious", "infectious_disease", "infectious_disease", "involves", "involves_woman", "iran", "iran", "iran", "iran", "iran", "iran", "iran", "iran_cuomo", "iran_currently", "iran_currently", "iran_quarantine", "iran_quarantine", "iran_reported", "island", "island", "island", "island", "island", "isolated", "isolated", "isolated", "isolated", "isolated", "isolated", "isolated_appropriately", "isolated_home", "isolated_home", "isolated_home", "isolated_manhattan", "isolated_manhattan", "isolation", "isolation", "isolation", "isolation_apartment", "italy", "italy", "key", "king", "king", "king_county", "king_county", "kirkland", "knew", "knew", "knew_take", "korea", "korea", "largest", "last_week", "last_week", "last_week", "late", "late", "late", "late", "late_30s", "late_30s", "late_30s", "late_thirties", "learned", "learned_first", "life", "life", "life", "life_care", "like", "like", "like", "likely", "likely", "live", "live", "live", "live_updates", "live_updates", "lived", "local", "local", "low", "low", "low", "low_new", "low_ny", "managing", "managing", "managing_situation", "manatee", "manatee_county", "manhattan", "manhattan", "manhattan", "manhattan", "manhattan", "manhattan_remains", "manhattan_returned", "markets", "matter", "matter", "matter_would", "mayor", "mayor", "mayor", "mayor_bill", "mayor_bill", "ministers", "ministers", "monday", "monday", "monday", "monday", "month", "month", "need_isolated", "new_cases", "new_cases", "new_cases", "new_cases", "new_cases", "new_coronavirus", "new_coronavirus", "new_coronavirus", "new_coronavirus", "new_hampshire", "news", "news", "news", "news", "news", "non", "non_essential", "noting", "novel", "novel", "novel", "novel", "novel", "novel", "novel_coronavirus", "novel_coronavirus", "novel_coronavirus", "novel_coronavirus", "novel_coronavirus", "novel_coronavirus", "nursing", "nursing", "officials", "officials", "officials", "officials", "officials", "officials", "officials", "officials_said", "officials_said", "oil", "old", "one_adult", "one_confirmed", "one_confirmed", "outbreak", "outbreak", "outbreak", "outbreak", "outbreak", "patient", "patient", "patient", "patient", "patient", "patient", "patient_contracted", "patient_respiratory", "patient_test", "patient_went", "patient_woman", "patient_woman", "patients", "patients", "patients_need", "pence", "pence", "people", "people", "people", "people", "people", "people", "people", "person", "person", "person", "person", "person", "person", "person", "place", "place", "place", "plunged", "positive", "positive", "positive", "positive", "positive", "positive", "positive", "positive", "positive", "positive_case", "positive_case", "positive_covid19", "positive_novel", "positive_test", "precautions", "precautions", "precautions", "precautions", "precautions_fortunate", "president", "president", "protect", "protect", "protocols", "protocols", "public", "public", "public", "public", "public_health", "quarantine", "quarantine", "quarantine", "quarantine_home", "quarantine_home", "quarantined", "quarantined", "quarantined", "quarantined_manhattan", "quarantined_manhattan", "quarantined_manhattan", "reason", "reason", "reason_undue", "reason_undue", "recently", "recently", "recently", "recently_traveled", "recently_traveled", "released", "released", "remain", "remain", "remains_isolated", "remains_low", "remains_low", "report", "report", "report", "reported", "reported", "reported", "reported", "reported", "reported", "reported", "reported", "reported", "reported", "reported_first", "reported_first", "reported_hundreds", "reporting", "reporting", "resident", "resident", "resident_hillsborough", "resident_manatee", "residents", "respiratory", "respiratory", "respiratory", "respiratory_symptoms", "respiratory_symptoms", "respiratory_symptoms", "restrictions", "restrictions", "restrictions", "returned", "returned", "returned", "returned", "returned_iran", "reuters", "reuters", "revealed", "revealed", "revealed_state", "rhode", "rhode", "rhode", "rhode", "rhode_island", "rhode_island", "rhode_island", "rhode_island", "risk", "risk", "risk", "risk", "risk_remains", "risk_remains", "said", "said", "said", "said", "said", "said", "said", "said_beginning", "said_knew", "said_sunday", "said_sunday", "said_sunday", "said_twitter", "said_twitter", "said_woman", "said_woman", "said_woman", "said_would", "said_would", "saturday", "saturday", "saturday", "saturday", "saturday", "say", "say", "say", "say_woman", "saying", "saying", "seattle", "seattle", "seattle_area", "seattle_king", "seattle_king", "second", "second", "second", "second", "second_victim", "serious_condition", "serious_condition", "setting", "ship", "ship", "since_2008", "since_arriving", "since_arriving", "situation", "situation", "situation", "situation", "situation", "situation_since", "situation_since", "six_washington", "somewhat", "somewhat_unique", "south", "south", "south", "south_korea", "south_korea", "spokesperson_told", "state", "state", "state", "state", "state", "state", "state", "state", "state_confirmed", "state_confirmed", "state_department", "state_department", "state_new", "state_new", "state_officials", "statement_said", "statement_said", "statement_said", "states", "states", "states", "states", "states", "stock", "stock_markets", "stocks", "sunday", "sunday", "sunday", "sunday", "sunday", "sunday", "sunday", "sunday_woman", "sunday_woman", "surprise", "surprise", "symptoms", "symptoms", "symptoms", "symptoms", "take_precautions", "team", "team", "test", "test", "test", "test", "test", "test", "test_positive", "test_positive", "test_positive", "tested", "tested", "tested", "tested", "tested_positive", "tested_positive", "tested_positive", "tested_positive", "testing", "testing", "testing", "thirties", "thirties_contracted", "time", "time", "time", "times", "times", "told_cnn", "toll", "toll", "total", "total", "total", "travel", "travel", "travel", "travel", "travel_restrictions", "travel_restrictions", "traveled", "traveled", "traveled", "traveled", "traveled_iran", "traveled_iran", "travelers", "travelers", "travelers", "traveling", "traveling", "traveling", "traveling_iran", "trump", "trump", "twitter_one", "unique_case", "united", "united", "united", "united_states", "united_states", "united_states", "update", "update", "update", "update", "updates", "updates", "us_death", "us_death", "via_twitter", "victim", "victim", "virus", "virus", "virus", "virus", "virus", "virus", "virus_iran", "virus_recent", "virus_recent", "virus_traveling", "virus_traveling", "virus_traveling", "wadsworth", "wadsworth_lab", "washington", "washington", "washington", "washington", "washington", "washington", "washington", "week", "week", "week", "week", "weekend", "weekend", "weekend", "went_hospital", "went_hospital", "woman", "woman", "woman", "woman", "woman", "woman", "woman", "woman", "woman_30s", "woman_30s", "woman_30s", "woman_late", "woman_late", "woman_late", "woman_lived", "worker", "worker", "worker_coming", "worker_lives", "workers", "workers", "world", "world", "world", "worldwide", "worldwide", "would_positive", "year", "year", "year", "year_old", "york_case", "york_city", "york_city", "york_city", "york_city", "york_city", "york_first", "york_first", "york_first", "york_first", "york_gov", "york_gov", "york_gov", "york_gov", "york_gov", "york_gov", "york_said", "york_said", "york_state", "york_state", "york_state", "york_state", "york_state", "york_times", "york_times"]}, "R": 30, "lambda.step": 0.01, "plot.opts": {"xlab": "PC1", "ylab": "PC2"}, "topic.order": [5, 4, 9, 7, 2, 1, 3, 8, 6, 10]}