{
    "topic_word_count": {
        "topic0": [
            {
                "word": "wuhan",
                "count": 52
            },
            {
                "word": "people",
                "count": 55
            },
            {
                "word": "india",
                "count": 122
            },
            {
                "word": "said",
                "count": 100
            },
            {
                "word": "chinese",
                "count": 53
            },
            {
                "word": "virus",
                "count": 74
            },
            {
                "word": "china",
                "count": 133
            },
            {
                "word": "minister",
                "count": 46
            },
            {
                "word": "isolation",
                "count": 35
            },
            {
                "word": "spread",
                "count": 30
            }
        ],
        "topic1": [
            {
                "word": "said",
                "count": 100
            },
            {
                "word": "passengers",
                "count": 81
            },
            {
                "word": "health",
                "count": 64
            },
            {
                "word": "minister",
                "count": 46
            },
            {
                "word": "isolation",
                "count": 35
            },
            {
                "word": "china",
                "count": 133
            },
            {
                "word": "india",
                "count": 122
            },
            {
                "word": "spread",
                "count": 30
            },
            {
                "word": "indian",
                "count": 92
            },
            {
                "word": "government",
                "count": 32
            }
        ],
        "topic2": [
            {
                "word": "quarantined",
                "count": 53
            },
            {
                "word": "people",
                "count": 55
            },
            {
                "word": "india",
                "count": 122
            },
            {
                "word": "delhi",
                "count": 39
            },
            {
                "word": "chinese",
                "count": 53
            },
            {
                "word": "ship",
                "count": 58
            },
            {
                "word": "said",
                "count": 100
            },
            {
                "word": "friday",
                "count": 29
            },
            {
                "word": "tested",
                "count": 50
            },
            {
                "word": "china",
                "count": 133
            }
        ],
        "topic3": [
            {
                "word": "novel_coronavirus",
                "count": 36
            },
            {
                "word": "novel",
                "count": 39
            },
            {
                "word": "indian",
                "count": 92
            },
            {
                "word": "health",
                "count": 64
            },
            {
                "word": "quarantined",
                "count": 53
            },
            {
                "word": "china",
                "count": 133
            },
            {
                "word": "isolation",
                "count": 35
            },
            {
                "word": "india",
                "count": 122
            },
            {
                "word": "tested",
                "count": 50
            },
            {
                "word": "outbreak",
                "count": 63
            }
        ],
        "topic4": [
            {
                "word": "india",
                "count": 122
            },
            {
                "word": "delhi",
                "count": 39
            },
            {
                "word": "said",
                "count": 100
            },
            {
                "word": "novel",
                "count": 39
            },
            {
                "word": "people",
                "count": 55
            },
            {
                "word": "novel_coronavirus",
                "count": 36
            },
            {
                "word": "isolation",
                "count": 35
            },
            {
                "word": "friday",
                "count": 29
            },
            {
                "word": "new",
                "count": 44
            },
            {
                "word": "government",
                "count": 32
            }
        ],
        "topic5": [
            {
                "word": "quarantine",
                "count": 62
            },
            {
                "word": "indian",
                "count": 92
            },
            {
                "word": "china",
                "count": 133
            },
            {
                "word": "virus",
                "count": 74
            },
            {
                "word": "deadly",
                "count": 36
            },
            {
                "word": "chinese",
                "count": 53
            },
            {
                "word": "people",
                "count": 55
            },
            {
                "word": "new",
                "count": 44
            },
            {
                "word": "india",
                "count": 122
            },
            {
                "word": "spread",
                "count": 30
            }
        ],
        "topic6": [
            {
                "word": "ship",
                "count": 58
            },
            {
                "word": "indian",
                "count": 92
            },
            {
                "word": "quarantined",
                "count": 53
            },
            {
                "word": "passengers",
                "count": 81
            },
            {
                "word": "tested",
                "count": 50
            },
            {
                "word": "said",
                "count": 100
            },
            {
                "word": "friday",
                "count": 29
            },
            {
                "word": "new",
                "count": 44
            },
            {
                "word": "coronavirus_outbreak",
                "count": 36
            },
            {
                "word": "outbreak",
                "count": 63
            }
        ],
        "topic7": [
            {
                "word": "passengers",
                "count": 81
            },
            {
                "word": "india",
                "count": 122
            },
            {
                "word": "china",
                "count": 133
            },
            {
                "word": "chinese",
                "count": 53
            },
            {
                "word": "ship",
                "count": 58
            },
            {
                "word": "health",
                "count": 64
            },
            {
                "word": "novel_coronavirus",
                "count": 36
            },
            {
                "word": "novel",
                "count": 39
            },
            {
                "word": "government",
                "count": 32
            },
            {
                "word": "quarantined",
                "count": 53
            }
        ],
        "topic8": [
            {
                "word": "quarantine",
                "count": 62
            },
            {
                "word": "said",
                "count": 100
            },
            {
                "word": "outbreak",
                "count": 63
            },
            {
                "word": "tested",
                "count": 50
            },
            {
                "word": "virus",
                "count": 74
            },
            {
                "word": "china",
                "count": 133
            },
            {
                "word": "people",
                "count": 55
            },
            {
                "word": "deadly",
                "count": 36
            },
            {
                "word": "coronavirus_outbreak",
                "count": 36
            },
            {
                "word": "health",
                "count": 64
            }
        ],
        "topic9": [
            {
                "word": "china",
                "count": 133
            },
            {
                "word": "wuhan",
                "count": 52
            },
            {
                "word": "virus",
                "count": 74
            },
            {
                "word": "outbreak",
                "count": 63
            },
            {
                "word": "india",
                "count": 122
            },
            {
                "word": "indian",
                "count": 92
            },
            {
                "word": "coronavirus_outbreak",
                "count": 36
            },
            {
                "word": "new",
                "count": 44
            },
            {
                "word": "quarantined",
                "count": 53
            },
            {
                "word": "isolation",
                "count": 35
            }
        ]
    },
    "data": {
        "vocab": [
            "china",
            "chinese",
            "coronavirus_outbreak",
            "deadly",
            "delhi",
            "friday",
            "government",
            "health",
            "india",
            "indian",
            "isolation",
            "minister",
            "new",
            "novel",
            "novel_coronavirus",
            "outbreak",
            "passengers",
            "people",
            "quarantine",
            "quarantined",
            "said",
            "ship",
            "spread",
            "tested",
            "virus",
            "wuhan"
        ],
        "freq": [
            133,
            53,
            36,
            36,
            39,
            29,
            32,
            64,
            122,
            92,
            35,
            46,
            44,
            39,
            36,
            63,
            81,
            55,
            62,
            53,
            100,
            58,
            30,
            50,
            74,
            52
        ],
        "topic_term_dists": [
            [
                0.06512607534695711,
                0.06512694774044396,
                0.0021007720301668463,
                0.06512541182532397,
                0.0021007720234638514,
                0.002100772027983695,
                0.002100772052382074,
                0.0021007720378964155,
                0.06512706716019666,
                0.0021007720407877715,
                0.06512579095517193,
                0.0651259435751205,
                0.0021007720328662313,
                0.06512519843377691,
                0.06512515348184007,
                0.0021007720354691973,
                0.06512505864301886,
                0.0651270796149598,
                0.002100772031644269,
                0.0021007720318321575,
                0.06512695516039965,
                0.002100772015824309,
                0.06512542765050322,
                0.002100772027804701,
                0.06512611461955474,
                0.1281525114046111
            ],
            [
                0.09415761155779034,
                0.0005512843466915314,
                0.000551264809494293,
                0.0005512615893842809,
                0.0005512189420081939,
                0.0005512989849321853,
                0.03351096725247059,
                0.13609099130137906,
                0.0606965574388021,
                0.04603715008116803,
                0.09778681878826567,
                0.11526587053477966,
                0.0005512604488703528,
                0.0005512349106167392,
                0.0005512229953780261,
                0.0005514230279232929,
                0.14736425029797517,
                0.009278872374818312,
                0.0005512723828812954,
                0.000551316697820627,
                0.19506049647415813,
                0.0005512333065726359,
                0.056481267856841585,
                0.0005512370320498623,
                0.0005513041745937643,
                0.0005513123923342087
            ],
            [
                0.0028050399977566248,
                0.08586591011789245,
                0.0028040844112247366,
                0.002804321711849144,
                0.12036426059905883,
                0.03084525774575399,
                0.0028041890888092537,
                0.0028043169926114213,
                0.15513105674325092,
                0.0028042962032494173,
                0.0028041339245560627,
                0.0028041666358824577,
                0.0028040844160922237,
                0.0028041719887416847,
                0.0028041713263345577,
                0.0028040844207120777,
                0.0028044063356558865,
                0.18253437551445525,
                0.002804421648897282,
                0.22561395967407366,
                0.05242825878382445,
                0.0686990887477246,
                0.0028040843942198435,
                0.03084491270661203,
                0.0028046088174859688,
                0.0028043370532751448
            ],
            [
                0.09726501855958204,
                0.002049076336619971,
                0.002049118725364234,
                0.0020488238979932136,
                0.0020488923411104885,
                0.002048854209512506,
                0.0020488239279470807,
                0.1173557463341653,
                0.002049296777487525,
                0.1578366087728679,
                0.05158503537035527,
                0.002048958726833452,
                0.0020489640835384985,
                0.21449784760065624,
                0.21622248729771515,
                0.0020491999040000283,
                0.0020488924280447,
                0.0020489116150218018,
                0.0020490398462973654,
                0.10630625949543626,
                0.0020490663126583788,
                0.002048854461638225,
                0.0020489818976879813,
                0.002049211934536286,
                0.0020490524387092733,
                0.002048976704220796
            ],
            [
                0.0008860726994530098,
                0.0008863816788273912,
                0.0008860281693489943,
                0.0008860172854244452,
                0.13378461323075297,
                0.06290513058388092,
                0.04353472428146087,
                0.024696471336133764,
                0.14178386756882633,
                0.0008860631026827545,
                0.06640944640264561,
                0.036325026414575155,
                0.05995490705372805,
                0.08144188877790984,
                0.07242819381517686,
                0.0008860363636297567,
                0.0008859999405552089,
                0.077405368772282,
                0.0008860916360867695,
                0.02746466526068569,
                0.12727621197816505,
                0.0008859840209638387,
                0.0008859840218634419,
                0.0008859840231908871,
                0.010047218408610524,
                0.024795623173139807
            ],
            [
                0.09116725919363028,
                0.07224289712469935,
                0.0032807455743609697,
                0.07353521121517903,
                0.0541917482231317,
                0.03037295913361035,
                0.028549654241331192,
                0.00039387576060974757,
                0.06817226388467852,
                0.09494372168468734,
                0.0003938706136974334,
                0.031714457769153444,
                0.06825048399347716,
                0.00039386157767604124,
                0.00039386155489470464,
                0.011912406924484836,
                0.00039389519555037977,
                0.0698238243682918,
                0.14453556635650913,
                0.0003938815765451983,
                0.011928533926075064,
                0.0003938604467686569,
                0.062396662481280195,
                0.00039385888628626256,
                0.07804236373207515,
                0.0017882745613159961
            ],
            [
                0.0004009155228349829,
                0.0004009104314217962,
                0.04737166458185828,
                0.00040088806881015746,
                0.025048375252911342,
                0.054072879050320696,
                0.0004008937104779167,
                0.0004009311248819412,
                0.035309242245551146,
                0.13422564249508442,
                0.0004008971140398064,
                0.04143815000598196,
                0.04918348682052042,
                0.0004009340714347568,
                0.00040090642843335317,
                0.04304907643395451,
                0.10820485160411203,
                0.00040091362569657043,
                0.00040091185851644717,
                0.1274742510002758,
                0.07156120086118264,
                0.15674713704447432,
                0.0004008880688014705,
                0.10110224815377925,
                0.00040090166587224114,
                0.00040090275877168667
            ],
            [
                0.14220045577916704,
                0.12912337201108645,
                0.0006598978462741264,
                0.0006598897404726072,
                0.0006599488189312849,
                0.0006599028556750461,
                0.05875658675658881,
                0.10988494631784239,
                0.15701802629887676,
                0.0006598931826020376,
                0.0006599111062190558,
                0.0006598991792868448,
                0.0006599030099268411,
                0.05934161072430553,
                0.05976089821604681,
                0.0006599260938135611,
                0.16216374648365747,
                0.0006599444629960451,
                0.0006599521226751243,
                0.0006599584070785458,
                0.0006599363193642095,
                0.11053182178420229,
                0.0006598897404490522,
                0.0006598897411489347,
                0.000659892824158587,
                0.0006599001771547167
            ],
            [
                0.08152764019721527,
                0.04094817649919859,
                0.04819128973094703,
                0.0631061620284797,
                0.00043435768079925244,
                0.0004343854512903564,
                0.014883627065013873,
                0.04816670662999387,
                0.04718301063399064,
                0.023321779499546492,
                0.00043434225545666206,
                0.0004343518493293223,
                0.00043437908820342523,
                0.033642045103244464,
                0.02438928464635412,
                0.09269481135752666,
                0.00043435609606095677,
                0.07108196528594253,
                0.11076623823318132,
                0.00043435322145292556,
                0.10165365509390918,
                0.0004343666153934338,
                0.00043434665442863916,
                0.0911256750052947,
                0.08223117716906098,
                0.02117751690868564
            ],
            [
                0.19824844568878058,
                0.00043770621230598155,
                0.055377426227120434,
                0.00043763747691111926,
                0.0004376138188201629,
                0.00043768546299095156,
                0.008871741569445434,
                0.01598821172653879,
                0.11587053861737497,
                0.059455121796942983,
                0.020332809258498882,
                0.00043764637301761547,
                0.03516384944079445,
                0.00043764521150090903,
                0.0004376463928049399,
                0.12381894767408166,
                0.00043763066391819987,
                0.00689799261955857,
                0.0004376599383592771,
                0.023488287318375812,
                0.007848885335858782,
                0.0004376114262043273,
                0.005298951722449311,
                0.013564643144258577,
                0.1379235772289985,
                0.16747408765408875
            ]
        ],
        "doc_topic_dists": [
            [
                0.004348198945756075,
                0.004349272465268016,
                0.0043485679229290355,
                0.00434823484575369,
                0.00434843529638395,
                0.004348225332783878,
                0.9608637145158683,
                0.004348496864577642,
                0.004348417308759209,
                0.004348436501920221
            ],
            [
                0.008336944112321406,
                0.00833972740230869,
                0.00833539601474882,
                0.0083337307829623,
                0.008337882645316349,
                0.7501202189787242,
                0.008335146477470029,
                0.008335646782824722,
                0.008337838806887349,
                0.1831874679964363
            ],
            [
                0.007692994866678795,
                0.007694085727310813,
                0.007695324348536543,
                0.007693504991867811,
                0.0076944730134869,
                0.007694185568124297,
                0.389462470676616,
                0.007694236814588953,
                0.5489855380065695,
                0.0076931859862204195
            ],
            [
                0.01428985590279046,
                0.014286850358027103,
                0.19420374420068848,
                0.014293557305670985,
                0.014291001359537417,
                0.014288565867075718,
                0.014287162624104366,
                0.6914820805109368,
                0.014289349383951004,
                0.01428783248721766
            ],
            [
                0.01667212430749426,
                0.01666902876958143,
                0.01666952562423225,
                0.016669188058004245,
                0.016667721425219044,
                0.016667594978135292,
                0.6627586608682673,
                0.01666981969329646,
                0.016667616402712464,
                0.20388871987305726
            ],
            [
                0.00833541135896453,
                0.008335223574413391,
                0.008334913257598798,
                0.008337319188427278,
                0.00833707427529973,
                0.00833513031178834,
                0.008334285353835605,
                0.008337384564413687,
                0.9249771104060479,
                0.008336147709210729
            ],
            [
                0.004000313924544842,
                0.004000811489472684,
                0.004001174328394489,
                0.0040003441466827565,
                0.004000856752777932,
                0.004000521331596788,
                0.9639943663331836,
                0.0040005647152453186,
                0.004000497747723915,
                0.004000549230377541
            ],
            [
                0.012502456970390851,
                0.17845666075091793,
                0.012502840429009522,
                0.012500397073768382,
                0.012504108298747776,
                0.012502263400680167,
                0.012501679943454152,
                0.7215242143376925,
                0.01250332428315974,
                0.012502054512178964
            ],
            [
                0.009092805556669569,
                0.00909230160191256,
                0.009092520794705685,
                0.009091742036014273,
                0.0090920582686574,
                0.9181665255290761,
                0.009091251137201883,
                0.009093390641056413,
                0.009092832629949458,
                0.009094571804756695
            ],
            [
                0.006250632667449962,
                0.006251003355898235,
                0.0062504431025341275,
                0.006251373580991967,
                0.006250695454369414,
                0.006250404677315607,
                0.006250677150336127,
                0.9437436547332122,
                0.006250519539872684,
                0.006250595738019719
            ],
            [
                0.0071439635289718825,
                0.007144141047386845,
                0.007143994860268545,
                0.007143563552406842,
                0.007144147764895166,
                0.9357046726864318,
                0.007143839937373533,
                0.00714351198670421,
                0.007144030147165348,
                0.0071441344883959495
            ],
            [
                0.0066676980919130255,
                0.006666859758700153,
                0.006667895494792523,
                0.006667046744524849,
                0.006667992668736164,
                0.6621992760325395,
                0.006668199028067002,
                0.006667972313199153,
                0.006668257413350839,
                0.2844588024541767
            ],
            [
                0.007144336102159148,
                0.007143761293731805,
                0.007144934372904229,
                0.007144052923831347,
                0.7156418725916612,
                0.007144536923716548,
                0.00714341402877397,
                0.22720578271066208,
                0.0071438242505747675,
                0.007143484801984911
            ],
            [
                0.009093064680385439,
                0.00909282236634771,
                0.009091915988073141,
                0.009095803104103765,
                0.009094549067123642,
                0.009092658625241359,
                0.009091847275265118,
                0.00909482025086878,
                0.9181589493991947,
                0.009093569243396334
            ],
            [
                0.006250632667449962,
                0.006251003355898235,
                0.0062504431025341275,
                0.006251373580991967,
                0.006250695454369414,
                0.006250404677315607,
                0.006250677150336127,
                0.9437436547332122,
                0.006250519539872684,
                0.006250595738019719
            ],
            [
                0.008336140130842768,
                0.4920003359035431,
                0.008333929580002532,
                0.008333809949296517,
                0.008334687015676625,
                0.008334412034561981,
                0.008334262677178312,
                0.008334761709272049,
                0.00833470239245018,
                0.441322958607176
            ],
            [
                0.006667917489302459,
                0.00666877796610486,
                0.006668281185471617,
                0.00666720038027683,
                0.11660414497423004,
                0.4282989263621648,
                0.006668758242050674,
                0.006668112573667045,
                0.0066689249790892495,
                0.4084189558476424
            ],
            [
                0.00833536245746142,
                0.008334036399538947,
                0.008336442294437287,
                0.008335089490433567,
                0.5945459059990426,
                0.008335436360190218,
                0.00833385357388886,
                0.3387756180107133,
                0.008334595895268974,
                0.00833365951902495
            ],
            [
                0.005555826519973623,
                0.00555634898755157,
                0.005556327069469354,
                0.0055561229172121545,
                0.005556097684839697,
                0.005556049092136379,
                0.9499954541121081,
                0.005555911772392338,
                0.0055560138391319855,
                0.00555584800518493
            ],
            [
                0.0071439635289718825,
                0.007144141047386845,
                0.007143994860268545,
                0.007143563552406842,
                0.007144147764895166,
                0.9357046726864318,
                0.007143839937373533,
                0.00714351198670421,
                0.007144030147165348,
                0.0071441344883959495
            ],
            [
                0.009092512998168585,
                0.009091619239000301,
                0.009091876372115221,
                0.2426891726511258,
                0.00909276263026784,
                0.009092534175274466,
                0.009091754527470663,
                0.00909286434960736,
                0.009092724318792836,
                0.684572178738177
            ],
            [
                0.01000085835472869,
                0.01000209334357712,
                0.010001533359039414,
                0.9099890421726341,
                0.010000985010438442,
                0.010000782345353464,
                0.01000159762137154,
                0.010001076711307224,
                0.010000647340947504,
                0.010001383740602566
            ],
            [
                0.011117047897315206,
                0.011116338848813112,
                0.011127128961359613,
                0.011114706101445488,
                0.011119719211371951,
                0.011118578424416463,
                0.011112006515530865,
                0.011115367220888421,
                0.011119948186989487,
                0.8999391586318694
            ],
            [
                0.010001645459781244,
                0.010002000317488997,
                0.5917475422769987,
                0.01000092135784303,
                0.010001868214649117,
                0.010001991140480176,
                0.010001313638606266,
                0.3282391403868625,
                0.010001426892158417,
                0.010002150315131585
            ],
            [
                0.0037044767550116855,
                0.45657452457805014,
                0.003704185168693732,
                0.0037039809654157364,
                0.003704525748833416,
                0.5137885031384308,
                0.0037044907827367985,
                0.003704578989761422,
                0.0037053050706774603,
                0.0037054288023889376
            ],
            [
                0.012501820014535833,
                0.012500811063019404,
                0.012504544881553016,
                0.012500901671632935,
                0.012502253448980894,
                0.8874810792380351,
                0.012501485217219497,
                0.012503333926408873,
                0.012502135458767357,
                0.012501635079846972
            ],
            [
                0.004000313924544842,
                0.004000811489472684,
                0.004001174328394489,
                0.0040003441466827565,
                0.004000856752777932,
                0.004000521331596788,
                0.9639943663331836,
                0.0040005647152453186,
                0.004000497747723915,
                0.004000549230377541
            ],
            [
                0.01111304945237073,
                0.011113919616632446,
                0.011111816263427266,
                0.011113444411548453,
                0.011112671070320974,
                0.011112307970562391,
                0.011116414814640041,
                0.01111141920597116,
                0.011116269910138418,
                0.8999786872843881
            ],
            [
                0.006667459881572249,
                0.9399932022220514,
                0.006666756782194555,
                0.006667749564017784,
                0.0066671695702763345,
                0.006667527637869059,
                0.00666758605684274,
                0.006667665605829423,
                0.0066673176262220185,
                0.006667565053124466
            ],
            [
                0.009092512998168585,
                0.009091619239000301,
                0.009091876372115221,
                0.2426891726511258,
                0.00909276263026784,
                0.009092534175274466,
                0.009091754527470663,
                0.00909286434960736,
                0.009092724318792836,
                0.684572178738177
            ],
            [
                0.008335263034828285,
                0.008336028500928806,
                0.3883117259756261,
                0.00833400659960732,
                0.00833613057355215,
                0.5450057118224524,
                0.008334676580183855,
                0.008334784553127278,
                0.008336286164137995,
                0.008335386195555987
            ],
            [
                0.003846520777414942,
                0.0038469578166365234,
                0.0038471502545912376,
                0.0038464712482711694,
                0.003847136822576622,
                0.003846727216341933,
                0.9653786506385046,
                0.003846889973115269,
                0.003846675852580106,
                0.0038468193999676306
            ],
            [
                0.0076934096060319685,
                0.7582110773605278,
                0.1802373525109095,
                0.00769485571219206,
                0.007693908595628478,
                0.007694107151825209,
                0.007695152722618144,
                0.007693207045958169,
                0.007693415639960944,
                0.007693513654347801
            ],
            [
                0.006250815203751345,
                0.9437416782417248,
                0.006250392760508492,
                0.006250945905849124,
                0.0062507419758476195,
                0.006250897716952272,
                0.0062508764589446,
                0.006251949166629792,
                0.0062506676340806306,
                0.006251034935711249
            ],
            [
                0.009093064680385439,
                0.00909282236634771,
                0.009091915988073141,
                0.009095803104103765,
                0.009094549067123642,
                0.009092658625241359,
                0.009091847275265118,
                0.00909482025086878,
                0.9181589493991947,
                0.009093569243396334
            ],
            [
                0.014288114932435746,
                0.014287869568465386,
                0.0142857143726757,
                0.01428739210386723,
                0.014288229541365096,
                0.3799225984135794,
                0.014287203606292327,
                0.014288721200976877,
                0.014289043573004699,
                0.5057751126873374
            ],
            [
                0.010000814570583563,
                0.01000067507913338,
                0.010000869822114957,
                0.010000309897420298,
                0.01000145276442957,
                0.010001869724356075,
                0.010001108627878843,
                0.010001427096764376,
                0.010001535036425473,
                0.9099899373808934
            ],
            [
                0.00909259832043513,
                0.009091581663453849,
                0.5816589477604089,
                0.009091471111886434,
                0.009092090868742724,
                0.00909239175854192,
                0.009093852150599852,
                0.009093936601629328,
                0.009092378692460093,
                0.34560075107184185
            ],
            [
                0.0071444230962268065,
                0.007143366790846639,
                0.007143566680053597,
                0.00714390968489377,
                0.00714290373529043,
                0.2576617711292711,
                0.0071439006957157315,
                0.007144511047637709,
                0.007144970376654664,
                0.6851866767634095
            ],
            [
                0.0071439635289718825,
                0.007144141047386845,
                0.007143994860268545,
                0.007143563552406842,
                0.007144147764895166,
                0.9357046726864318,
                0.007143839937373533,
                0.00714351198670421,
                0.007144030147165348,
                0.0071441344883959495
            ],
            [
                0.012504217287159858,
                0.01250492008887933,
                0.012502591611446689,
                0.01250000004628252,
                0.01250182127563653,
                0.8874812431946565,
                0.012501492509754155,
                0.012502019852178633,
                0.0125016228883028,
                0.012500071245703098
            ],
            [
                0.007693717885355678,
                0.007694804765051317,
                0.007693736528877171,
                0.007693745551939046,
                0.4169736095392791,
                0.007695308218309395,
                0.007694282077925879,
                0.007693621452566735,
                0.007694368184547786,
                0.521472805796148
            ],
            [
                0.9437379488415943,
                0.0062523279730849896,
                0.006250980950076227,
                0.006251250952444949,
                0.0062513782349968485,
                0.00625124626256661,
                0.006250571056669704,
                0.006251589841162173,
                0.006251251779918167,
                0.0062514541074860696
            ],
            [
                0.010000814570583563,
                0.01000067507913338,
                0.010000869822114957,
                0.010000309897420298,
                0.01000145276442957,
                0.010001869724356075,
                0.010001108627878843,
                0.010001427096764376,
                0.010001535036425473,
                0.9099899373808934
            ],
            [
                0.014287734416547302,
                0.014288857856095882,
                0.014288382787376763,
                0.6059632733846989,
                0.014289158194015189,
                0.014288363439934712,
                0.014287339916769722,
                0.2797289982354335,
                0.014287956834108436,
                0.014289934935019673
            ],
            [
                0.012501676909013834,
                0.012505303265481407,
                0.012500552038302986,
                0.5033927112998714,
                0.01250268950986009,
                0.012502592511557584,
                0.01250096806638411,
                0.012503077857840088,
                0.3965887539810559,
                0.012501674560632546
            ],
            [
                0.006668607827194351,
                0.0066719714493192655,
                0.006669136049690212,
                0.0066682861411218675,
                0.006670010950969774,
                0.0066676213886838935,
                0.006670217644092845,
                0.006666976746576665,
                0.006669878276161836,
                0.9399772935261893
            ],
            [
                0.014287435198139447,
                0.014289206873186522,
                0.01428675658826723,
                0.014286330775523097,
                0.01428671756616243,
                0.01428979212219249,
                0.014288682495071472,
                0.5249680729173248,
                0.36072627105433064,
                0.01429073440980191
            ],
            [
                0.006251143614207115,
                0.006250439052264308,
                0.006255196544816683,
                0.006251439097902984,
                0.006251722443420175,
                0.43616735773528886,
                0.0062523864290199415,
                0.006251097877135535,
                0.006251304250814229,
                0.5138179129551301
            ],
            [
                0.005557633462421555,
                0.8053156351853834,
                0.0055587834883607115,
                0.0055562900626224725,
                0.0055577687889689815,
                0.0055574853527502075,
                0.00555625361473475,
                0.005556865403130041,
                0.005557420354049916,
                0.15022586428757795
            ],
            [
                0.00909105594446902,
                0.009091477279991387,
                0.009092178962593652,
                0.009091980314613394,
                0.00909101328336284,
                0.009091383582198848,
                0.9181743933516024,
                0.009091721865808108,
                0.009092166354105364,
                0.009092629061254976
            ],
            [
                0.003846945281575973,
                0.4209270200082047,
                0.003846661136390128,
                0.0038464718854910435,
                0.0038470444550917937,
                0.5482961957764424,
                0.0038469098926842277,
                0.0038470131362761868,
                0.003847809328577928,
                0.0038479290992655827
            ],
            [
                0.005264095760275478,
                0.005264378909939164,
                0.005264505174213149,
                0.0052651588544232585,
                0.005264207744090381,
                0.005264294874843915,
                0.4314083013209309,
                0.005265249872314976,
                0.5264755194702311,
                0.005264288018737764
            ],
            [
                0.004000313924544842,
                0.004000811489472684,
                0.004001174328394489,
                0.0040003441466827565,
                0.004000856752777932,
                0.004000521331596788,
                0.9639943663331836,
                0.0040005647152453186,
                0.004000497747723915,
                0.004000549230377541
            ],
            [
                0.006250632667449962,
                0.006251003355898235,
                0.0062504431025341275,
                0.006251373580991967,
                0.006250695454369414,
                0.006250404677315607,
                0.006250677150336127,
                0.9437436547332122,
                0.006250519539872684,
                0.006250595738019719
            ],
            [
                0.007693543397025201,
                0.007693504805089929,
                0.007695384359688465,
                0.007692519896959803,
                0.007695468256954581,
                0.48906823243437514,
                0.007693622514137526,
                0.007693669729800262,
                0.44937947523044447,
                0.0076945793755245
            ],
            [
                0.0071439635289718825,
                0.007144141047386845,
                0.007143994860268545,
                0.007143563552406842,
                0.007144147764895166,
                0.9357046726864318,
                0.007143839937373533,
                0.00714351198670421,
                0.007144030147165348,
                0.0071441344883959495
            ],
            [
                0.00714432941551586,
                0.007144539780388081,
                0.00714353743427127,
                0.2645670820676773,
                0.007144211488698221,
                0.007143425207720163,
                0.007145054916276118,
                0.007144451007732769,
                0.007145792628403145,
                0.6782775760533171
            ],
            [
                0.02500242367909342,
                0.025007905138093485,
                0.025003871893874055,
                0.02500000007125814,
                0.7749656382268822,
                0.025003525416090577,
                0.025002293732373098,
                0.025007213500433695,
                0.02500415429822124,
                0.025002974043680102
            ],
            [
                0.005001238118229988,
                0.22641150383033784,
                0.005000230394280335,
                0.005000701923234601,
                0.005000662837150563,
                0.0050014723320905095,
                0.005000238960183744,
                0.005000943753600188,
                0.005000808865537381,
                0.7335821989853548
            ],
            [
                0.9437379488415943,
                0.0062523279730849896,
                0.006250980950076227,
                0.006251250952444949,
                0.0062513782349968485,
                0.00625124626256661,
                0.006250571056669704,
                0.006251589841162173,
                0.006251251779918167,
                0.0062514541074860696
            ],
            [
                0.007693908393468689,
                0.5371005101429044,
                0.00769280807172446,
                0.007693459639752799,
                0.007693357468153552,
                0.0076937190645696395,
                0.0076936119527052215,
                0.007693709952944877,
                0.007693640413971251,
                0.4013512748998051
            ],
            [
                0.0071439635289718825,
                0.007144141047386845,
                0.007143994860268545,
                0.007143563552406842,
                0.007144147764895166,
                0.9357046726864318,
                0.007143839937373533,
                0.00714351198670421,
                0.007144030147165348,
                0.0071441344883959495
            ],
            [
                0.005884250028413034,
                0.4266366956134081,
                0.005884002001155086,
                0.0058826139212186605,
                0.0058835909165758015,
                0.005884393881103041,
                0.0058831209251933355,
                0.005884836198269888,
                0.5262925182219909,
                0.005883978292672139
            ],
            [
                0.00625092317495107,
                0.006251282628196687,
                0.0062506837042409355,
                0.0062513367396888056,
                0.006250526363799517,
                0.006252006835672728,
                0.006251173081102221,
                0.006250932336150615,
                0.9437397934871005,
                0.00625134164909691
            ],
            [
                0.016667544746679943,
                0.016677903381620694,
                0.01666666678879923,
                0.016678512743235,
                0.016670172535934565,
                0.01667179012649846,
                0.016670693893827405,
                0.016674985062860213,
                0.016671917168176686,
                0.8499498135523678
            ],
            [
                0.004349233724116934,
                0.004348284498863376,
                0.004348423417860006,
                0.004348910984391865,
                0.00434875437659649,
                0.0043484612956423765,
                0.004348373869575108,
                0.004348499837829558,
                0.9608613134260421,
                0.004349744569082229
            ],
            [
                0.008334298266037267,
                0.008334619352582461,
                0.008337123316547975,
                0.008335809216483548,
                0.9249867052691434,
                0.008333897648144989,
                0.008335266836511977,
                0.008334219965360577,
                0.008334035589094367,
                0.008334024540093464
            ],
            [
                0.00625092317495107,
                0.006251282628196687,
                0.0062506837042409355,
                0.0062513367396888056,
                0.006250526363799517,
                0.006252006835672728,
                0.006251173081102221,
                0.006250932336150615,
                0.9437397934871005,
                0.00625134164909691
            ],
            [
                0.012504998125458997,
                0.012503359181778714,
                0.012501726623422324,
                0.01250050015536149,
                0.6899229255606638,
                0.012504787816566495,
                0.012500996258236002,
                0.012500765694793178,
                0.21005422164674784,
                0.012505718936971113
            ],
            [
                0.007693233986732975,
                0.007693061732521575,
                0.007693638878157278,
                0.00769313417597025,
                0.007693603112587833,
                0.9307593314525076,
                0.007693195706051952,
                0.007693073841663659,
                0.007693917698237303,
                0.007693809415569667
            ],
            [
                0.00625092317495107,
                0.006251282628196687,
                0.0062506837042409355,
                0.0062513367396888056,
                0.006250526363799517,
                0.006252006835672728,
                0.006251173081102221,
                0.006250932336150615,
                0.9437397934871005,
                0.00625134164909691
            ],
            [
                0.006668537365527932,
                0.006667925249355983,
                0.006667351406648653,
                0.006668763921521404,
                0.42910491498067416,
                0.0066685193494838875,
                0.006667850611390599,
                0.006668237120295811,
                0.517548143056471,
                0.006669756938630612
            ],
            [
                0.008335165215862106,
                0.008334515952026897,
                0.008334058329369216,
                0.28653621076977176,
                0.008334323045207566,
                0.3376104957846416,
                0.008335203554083783,
                0.008335603948474378,
                0.008335504362058566,
                0.3175089190385042
            ],
            [
                0.00625092317495107,
                0.006251282628196687,
                0.0062506837042409355,
                0.0062513367396888056,
                0.006250526363799517,
                0.006252006835672728,
                0.006251173081102221,
                0.006250932336150615,
                0.9437397934871005,
                0.00625134164909691
            ],
            [
                0.008334929625766041,
                0.5733402920593861,
                0.008340407492910772,
                0.008337787537443762,
                0.008335379021173938,
                0.008334591673091552,
                0.008338337972778708,
                0.008334391508448483,
                0.008334483768712925,
                0.3599693993402877
            ],
            [
                0.007693001894054731,
                0.007694538552030118,
                0.007693119527125167,
                0.007692682208149981,
                0.007693425677741045,
                0.007692814568668793,
                0.9307605257671817,
                0.007692876706914696,
                0.0076937168471432225,
                0.007693298250990504
            ],
            [
                0.004762221677509126,
                0.00476260667000711,
                0.004763248598442216,
                0.004762316614694812,
                0.004763090377717144,
                0.004762672301829326,
                0.9571365967881722,
                0.004762497439317579,
                0.0047623351683500695,
                0.004762414363960335
            ],
            [
                0.006250692758842006,
                0.9437430883879386,
                0.006250078718518442,
                0.006250945780665376,
                0.0062506017007549885,
                0.006250862109230128,
                0.006250802994550593,
                0.006251493331068574,
                0.006250621413042802,
                0.006250812805388515
            ],
            [
                0.005883482620233944,
                0.005883287717658801,
                0.0058836855380990745,
                0.16732744355534035,
                0.005883679457347036,
                0.00588396334536527,
                0.005882940799757669,
                0.005883831180819561,
                0.283766567514337,
                0.5077211182710414
            ],
            [
                0.006250632667449962,
                0.006251003355898235,
                0.0062504431025341275,
                0.006251373580991967,
                0.006250695454369414,
                0.006250404677315607,
                0.006250677150336127,
                0.9437436547332122,
                0.006250519539872684,
                0.006250595738019719
            ],
            [
                0.006668873095552434,
                0.44561807928552033,
                0.0066675415361034445,
                0.0066671550471666995,
                0.006667811240360126,
                0.35378008049832155,
                0.006668235179607523,
                0.006669015064665517,
                0.0066681757750162995,
                0.15392503327768603
            ],
            [
                0.01111174248084184,
                0.011112281099151987,
                0.19077657255112598,
                0.011112708652611677,
                0.011112805531871597,
                0.16093731293358943,
                0.011114700774070965,
                0.5704942670923436,
                0.011114486283432555,
                0.01111312260096042
            ],
            [
                0.01250173672539734,
                0.887485962811074,
                0.012501504556062188,
                0.012500705079934829,
                0.01250231321329705,
                0.012500820289409567,
                0.012501550557746644,
                0.012503198368929347,
                0.012500921913013607,
                0.0125012864851355
            ],
            [
                0.01000264936075887,
                0.01000066626797953,
                0.010001630542290715,
                0.010001550856808424,
                0.010000648096112858,
                0.33098463068887346,
                0.01000214281906786,
                0.010002466421767464,
                0.010002862723294167,
                0.5890007522230467
            ],
            [
                0.02000349675631246,
                0.8199688183532942,
                0.020004067295034886,
                0.020002794951717855,
                0.020006414014924725,
                0.02000188030816664,
                0.020000945944562445,
                0.020005700310882304,
                0.02000184709577679,
                0.020004034969327712
            ],
            [
                0.004546020452309488,
                0.00454614788155479,
                0.0045463244796378295,
                0.12438535714200957,
                0.004546708230370015,
                0.00454599956143973,
                0.8392452640461914,
                0.004546164031705077,
                0.004546060032178174,
                0.0045459541426040575
            ],
            [
                0.00833510140300747,
                0.48085877743520355,
                0.008336255170626845,
                0.00833580547701869,
                0.4524602355188553,
                0.008334530368827602,
                0.008333951399144238,
                0.008335979503523059,
                0.00833520529570083,
                0.008334158428092486
            ],
            [
                0.006250632667449962,
                0.006251003355898235,
                0.0062504431025341275,
                0.006251373580991967,
                0.006250695454369414,
                0.006250404677315607,
                0.006250677150336127,
                0.9437436547332122,
                0.006250519539872684,
                0.006250595738019719
            ],
            [
                0.020004508155740286,
                0.02000418555978263,
                0.02000986406945206,
                0.02000182520570784,
                0.020006803619181664,
                0.02000590708676981,
                0.020003055817192042,
                0.020008546124584553,
                0.8199467177464842,
                0.020008586615105073
            ],
            [
                0.007693975425326901,
                0.007695461585090497,
                0.007693300164269889,
                0.007692509488293409,
                0.007695389652276848,
                0.007695247126566181,
                0.20847284030236446,
                0.0076960776310573825,
                0.49431656379977706,
                0.24334863482497737
            ],
            [
                0.007693233986732975,
                0.007693061732521575,
                0.007693638878157278,
                0.00769313417597025,
                0.007693603112587833,
                0.9307593314525076,
                0.007693195706051952,
                0.007693073841663659,
                0.007693917698237303,
                0.007693809415569667
            ],
            [
                0.004349233724116934,
                0.004348284498863376,
                0.004348423417860006,
                0.004348910984391865,
                0.00434875437659649,
                0.0043484612956423765,
                0.004348373869575108,
                0.004348499837829558,
                0.9608613134260421,
                0.004349744569082229
            ],
            [
                0.007693233986732975,
                0.007693061732521575,
                0.007693638878157278,
                0.00769313417597025,
                0.007693603112587833,
                0.9307593314525076,
                0.007693195706051952,
                0.007693073841663659,
                0.007693917698237303,
                0.007693809415569667
            ],
            [
                0.007693233986732975,
                0.007693061732521575,
                0.007693638878157278,
                0.00769313417597025,
                0.007693603112587833,
                0.9307593314525076,
                0.007693195706051952,
                0.007693073841663659,
                0.007693917698237303,
                0.007693809415569667
            ],
            [
                0.01250255591817813,
                0.012506985917158714,
                0.012501622433052898,
                0.01250302304871567,
                0.012505951759314345,
                0.012503709361585383,
                0.01250636419452272,
                0.012505783644063576,
                0.012506182066256873,
                0.8874578216571517
            ],
            [
                0.007693971321891635,
                0.007693281384149492,
                0.007694548334388928,
                0.007693708765538266,
                0.7130783340734782,
                0.007694193240873117,
                0.007692910864814237,
                0.2253727897791497,
                0.007693383435520964,
                0.0076928788001955194
            ],
            [
                0.010000871112913423,
                0.010000813810356043,
                0.010001540001293916,
                0.010000182420908775,
                0.010001499959321853,
                0.010003717112114624,
                0.010000930974942665,
                0.010001946672694937,
                0.20212766562672055,
                0.7178608323087332
            ],
            [
                0.012500905838063538,
                0.012503523330518806,
                0.29896565222005383,
                0.012503723555797376,
                0.012503427471777693,
                0.01250230940033374,
                0.01250168561243042,
                0.6010135651932608,
                0.012501905338261829,
                0.012503302039502158
            ],
            [
                0.004546277323893148,
                0.004546432511363443,
                0.00454643138800713,
                0.004546901753268484,
                0.004546520317237895,
                0.00454655969236015,
                0.482483973094069,
                0.00454742393771986,
                0.4811426892192605,
                0.004546790762820346
            ],
            [
                0.006668816667618296,
                0.006668677667109576,
                0.006668942253207928,
                0.006668884282950194,
                0.9399788426116685,
                0.006669592570113374,
                0.00666800541519192,
                0.006668231248012854,
                0.006669560747251418,
                0.006670446536875917
            ],
            [
                0.008334298266037267,
                0.008334619352582461,
                0.008337123316547975,
                0.008335809216483548,
                0.9249867052691434,
                0.008333897648144989,
                0.008335266836511977,
                0.008334219965360577,
                0.008334035589094367,
                0.008334024540093464
            ],
            [
                0.9437379488415943,
                0.0062523279730849896,
                0.006250980950076227,
                0.006251250952444949,
                0.0062513782349968485,
                0.00625124626256661,
                0.006250571056669704,
                0.006251589841162173,
                0.006251251779918167,
                0.0062514541074860696
            ],
            [
                0.011113387945382554,
                0.011114015876009497,
                0.011116543233001765,
                0.011114490231118638,
                0.011113673367218035,
                0.011112039957921068,
                0.011113945078734595,
                0.011112316251216814,
                0.011112265205172467,
                0.8999773228542246
            ],
            [
                0.006250692758842006,
                0.9437430883879386,
                0.006250078718518442,
                0.006250945780665376,
                0.0062506017007549885,
                0.006250862109230128,
                0.006250802994550593,
                0.006251493331068574,
                0.006250621413042802,
                0.006250812805388515
            ],
            [
                0.011112047822995191,
                0.39552931766959903,
                0.011112084286355762,
                0.011111861179545933,
                0.011112159902762132,
                0.011114185243327065,
                0.3135377414757928,
                0.011114356559712464,
                0.2131448912334858,
                0.01111135462642384
            ],
            [
                0.0052641639810835986,
                0.0052648115276280145,
                0.00526496012868592,
                0.005263951288375344,
                0.0052647052931541335,
                0.005264734519926288,
                0.4987139932139741,
                0.00526453676544369,
                0.4591692487400419,
                0.005264894541687084
            ],
            [
                0.0071449334735491435,
                0.007145321810370168,
                0.007143927179501509,
                0.007144828805111319,
                0.9357004896401853,
                0.007143821325187359,
                0.007143492925699382,
                0.007144427325644705,
                0.007144080600480607,
                0.007144676914270708
            ],
            [
                0.00625092317495107,
                0.006251282628196687,
                0.0062506837042409355,
                0.0062513367396888056,
                0.006250526363799517,
                0.006252006835672728,
                0.006251173081102221,
                0.006250932336150615,
                0.9437397934871005,
                0.00625134164909691
            ],
            [
                0.01000085835472869,
                0.01000209334357712,
                0.010001533359039414,
                0.9099890421726341,
                0.010000985010438442,
                0.010000782345353464,
                0.01000159762137154,
                0.010001076711307224,
                0.010000647340947504,
                0.010001383740602566
            ],
            [
                0.014287799450257746,
                0.014290542342645252,
                0.01428834111926359,
                0.014286260437315491,
                0.3182157958621221,
                0.014288762278672186,
                0.014288773374752838,
                0.014288634911713796,
                0.014289517851053082,
                0.5674755723722039
            ],
            [
                0.008334908568500441,
                0.008333812167024645,
                0.008338056562736595,
                0.008335140235280434,
                0.008334005971564463,
                0.008335157814598218,
                0.008335663426291036,
                0.24615499222340348,
                0.008335099168483668,
                0.687163163862117
            ],
            [
                0.006250632667449962,
                0.006251003355898235,
                0.0062504431025341275,
                0.006251373580991967,
                0.006250695454369414,
                0.006250404677315607,
                0.006250677150336127,
                0.9437436547332122,
                0.006250519539872684,
                0.006250595738019719
            ],
            [
                0.00833616588279605,
                0.26938668671827354,
                0.008336602721475387,
                0.23305084160119013,
                0.00833562097025654,
                0.008334554572944148,
                0.008335964616859917,
                0.22597616639820686,
                0.008335612340600726,
                0.22157178417739662
            ],
            [
                0.006252221560029653,
                0.0062523840684390545,
                0.006250947312302171,
                0.00625242325232999,
                0.47048531913136826,
                0.006251774041776672,
                0.006251559134604643,
                0.006250939667010398,
                0.006251052871415834,
                0.47950137896072337
            ],
            [
                0.005556381591870761,
                0.5059557606842343,
                0.005556096665155065,
                0.005556249992818129,
                0.005556776537183614,
                0.005556607461024981,
                0.4495899917092755,
                0.005557168626785372,
                0.005557027099095084,
                0.005557939632557196
            ],
            [
                0.010001141075623832,
                0.010001818963788874,
                0.9099817752883742,
                0.010000312992759504,
                0.01000299504576586,
                0.010001609185626363,
                0.010005171080296079,
                0.010001564062973246,
                0.010003005228329215,
                0.010000607076462973
            ],
            [
                0.016670100633000874,
                0.016667608688998366,
                0.016671239126434294,
                0.01666666670930511,
                0.016668904890253522,
                0.8499762797853355,
                0.01666720773459195,
                0.016673151436590303,
                0.016670326647234862,
                0.016668514348255104
            ],
            [
                0.006250632667449962,
                0.006251003355898235,
                0.0062504431025341275,
                0.006251373580991967,
                0.006250695454369414,
                0.006250404677315607,
                0.006250677150336127,
                0.9437436547332122,
                0.006250519539872684,
                0.006250595738019719
            ],
            [
                0.006251373760820377,
                0.006252737321425612,
                0.006251092567942644,
                0.00625011841403897,
                0.1423656324267284,
                0.3452874338409282,
                0.1472696712412457,
                0.006252599048249395,
                0.006252018321151607,
                0.32756732305746916
            ]
        ],
        "doc_length": [
            22,
            11,
            12,
            6,
            5,
            11,
            24,
            7,
            10,
            15,
            13,
            14,
            13,
            10,
            15,
            11,
            14,
            11,
            17,
            13,
            10,
            9,
            8,
            9,
            26,
            7,
            24,
            8,
            14,
            10,
            11,
            25,
            12,
            15,
            10,
            6,
            9,
            10,
            13,
            13,
            7,
            12,
            15,
            9,
            6,
            7,
            14,
            6,
            15,
            17,
            10,
            25,
            18,
            24,
            15,
            12,
            13,
            13,
            3,
            19,
            15,
            12,
            13,
            16,
            15,
            5,
            22,
            11,
            15,
            7,
            12,
            15,
            14,
            11,
            15,
            11,
            12,
            20,
            15,
            16,
            15,
            14,
            8,
            7,
            9,
            4,
            21,
            11,
            15,
            4,
            12,
            12,
            22,
            12,
            12,
            7,
            12,
            9,
            7,
            21,
            14,
            11,
            15,
            8,
            15,
            8,
            18,
            13,
            15,
            9,
            6,
            11,
            15,
            11,
            15,
            17,
            9,
            5,
            15,
            15
        ],
        "model": [
            [
                3.1001020277747697,
                3.1001435550555585,
                0.10000000147279026,
                3.1000704431176347,
                0.10000000115371731,
                0.10000000136886888,
                0.10000000253026947,
                0.10000000184072971,
                3.1001492396206967,
                0.10000000197836274,
                3.100088490285443,
                3.1000957552313113,
                0.10000000160128517,
                3.1000602853495796,
                3.100058145567782,
                0.10000000172519037,
                3.100053631093044,
                3.1001498324867067,
                0.10000000154311788,
                0.10000000155206164,
                3.100143908256938,
                0.10000000079006328,
                3.100071196420671,
                0.10000000136034848,
                3.1001038972112265,
                6.100257974295799
            ],
            [
                17.08170831289227,
                0.10001186576263561,
                0.10000832140016766,
                0.10000773722031166,
                0.10000000029892446,
                0.10001452137542068,
                6.079429569411446,
                24.68909925562125,
                11.011333790364683,
                8.351881024092236,
                17.740104997901323,
                20.911086701665653,
                0.10000753031270299,
                0.1000028972618871,
                0.10000073564554182,
                0.10003702477325867,
                26.734250133278692,
                1.6833370001311023,
                0.10000969533463325,
                0.1000177347788698,
                35.38711792932945,
                0.10000260626243375,
                10.24661232066991,
                0.10000328212404763,
                0.10001546286367499,
                0.10001695369424025
            ],
            [
                0.10003408035523839,
                3.0621728600585136,
                0.10000000197489668,
                0.10000846465270138,
                4.292462184601542,
                1.1000117625361967,
                0.10000373501467841,
                0.10000829635399407,
                5.5323248895767945,
                0.1000075549582525,
                0.1000017677324504,
                0.10000293429244803,
                0.10000000214848229,
                0.10000312518753346,
                0.10000310156459481,
                0.10000000231323675,
                0.10001148252934143,
                6.509589311528438,
                0.10001202863421746,
                8.045904867434968,
                1.869710469818894,
                2.4499651233557196,
                0.10000000136846367,
                1.0999994576588046,
                0.10001870349006824,
                0.10000901176270428
            ],
            [
                4.747358698556827,
                0.10001232215568681,
                0.10001439108629287,
                0.10000000100746378,
                0.1000033416126779,
                0.10000148046695405,
                0.10000000246946682,
                5.727956786887824,
                0.1000230815415955,
                7.7037665617632,
                2.517787689834272,
                0.10000658179958208,
                0.10000684325226747,
                10.469316077957759,
                10.55349313759296,
                0.10001835329293697,
                0.1000033458558055,
                0.10000428234318803,
                0.100010541118136,
                5.18864801755575,
                0.10001183290125636,
                0.10000149277282973,
                0.10000771273400672,
                0.10001894048524719,
                0.10001115573474835,
                0.10000745924871485
            ],
            [
                0.10001000938722952,
                0.10004488353486032,
                0.10000498332545903,
                0.10000375486937749,
                15.100115863330505,
                7.100029945717181,
                4.913714401478687,
                2.7874623963506573,
                16.00298252645579,
                0.10000892621077695,
                7.49555805322667,
                4.099964071746778,
                6.767041599357842,
                9.19225258403801,
                8.174887171027276,
                0.100005908204531,
                0.10000179717387889,
                8.73665520032019,
                0.10001214674336434,
                3.099905269888024,
                14.365520078166384,
                0.10000000034785846,
                0.10000000044939564,
                0.10000000059922286,
                1.1340180190417564,
                2.7986535504803998
            ],
            [
                23.147188647874803,
                18.342330163318803,
                0.8329748792175992,
                18.67044618116581,
                13.759178792627406,
                7.711634868463741,
                7.2487013254629495,
                0.10000428460062778,
                17.308804352008078,
                24.10602508186764,
                0.1000029778096664,
                8.052238746022805,
                17.32866428451492,
                0.10000068358152307,
                0.1000006777973863,
                3.024536799397015,
                0.10000921909401009,
                17.728132325841067,
                36.69729736720324,
                0.10000576125525394,
                3.028631413531907,
                0.10000039644635196,
                15.842390461518626,
                0.10000000024292671,
                19.814803382381612,
                0.4540394105416852
            ],
            [
                0.10000684849716748,
                0.10000557846356141,
                11.816681103780784,
                0.10000000019535582,
                6.248221698437871,
                13.488273501489937,
                0.10000140748786693,
                0.10001074036829129,
                8.80775584549778,
                33.48207472367187,
                0.10000225649340266,
                10.336588517069845,
                12.268633252813096,
                0.10001147537465604,
                0.10000457993335751,
                10.738427972132913,
                26.99128765209958,
                0.1000063752632242,
                0.10000593444688063,
                31.797965858063545,
                17.850668694974253,
                39.099975665506115,
                0.10000000019318889,
                25.219570303342163,
                0.10000339193064757,
                0.10000366455024708
            ],
            [
                21.549123666555243,
                19.567416267853954,
                0.10000122867916948,
                0.100000000322211,
                0.10000895309950768,
                0.10000198780613094,
                8.904000674995803,
                16.65201622822703,
                23.79458524273331,
                0.10000052194411696,
                0.10000323809743421,
                0.10000143068454113,
                0.1000020111815202,
                8.992655481052152,
                9.056194503918606,
                0.10000550932452479,
                24.574370089467777,
                0.10000829299904139,
                0.10000945375039635,
                0.10001040609183408,
                0.10000705890925905,
                16.75004403935513,
                0.10000000031864147,
                0.100000000424702,
                0.1000004676254286,
                0.10000158190190578
            ],
            [
                18.770784183213056,
                9.427837993388007,
                11.095479972952734,
                14.529454614435506,
                0.10000576816501801,
                0.10001216199530567,
                3.4267807926856544,
                11.089820001911875,
                10.863335521333248,
                5.36956655062638,
                0.10000221666057098,
                0.10000442553737339,
                0.10001069696907364,
                7.745686819676783,
                5.6153471064811,
                21.341894536464345,
                0.10000540329758822,
                16.36578989007269,
                25.502628895328034,
                0.1000047414527607,
                23.404563367550054,
                0.1000078252506731,
                0.10000322947234144,
                20.980619271406614,
                18.932765330115895,
                4.87587520585272
            ],
            [
                45.30368352489309,
                0.10002451040811398,
                12.654835116109858,
                0.10000880301346088,
                0.10000339667263551,
                0.10001976878001087,
                2.0273680884628504,
                3.653622007837458,
                26.47870551086764,
                13.586669052886867,
                4.6464483119585935,
                0.1000108359494161,
                8.035633777848558,
                0.10001057051991881,
                0.10001084047121037,
                28.295073892371743,
                0.10000724611008135,
                1.5763274890140295,
                0.10001393589778347,
                5.3675373419267025,
                1.7936252465612337,
                0.1000028499126837,
                1.2109150768545798,
                3.0997887423557193,
                31.518260189604682,
                38.27113518767134
            ]
        ]
    },
    "doc_count": 120,
    "place": "India",
    "folder": "quarantine",
    "date": "20200207"
}